rtl/LOD.v
`timescale 1ns/1ps

module LOD #(parameter W = 16)(
    input  [W-1:0] x_in,
    output [W-1:0] x_out
);

    wire [W-1:0] BR_x;
    wire [W-1:0] NOT_out;
    wire [W-1:0] adder_out;
    wire [W-1:0] AND_out;

    // step 1: bit reversal of x_in
    // genvar i;
    // generate
    //     for(i = 0; i < W; i = i+1) begin
    //         assign BR_x[W-i-1] = x_in[i];
    //     end
    // endgenerate

    assign BR_x = bit_reverse(x_in); 

    // step 2: NOT of BR_x
    assign NOT_out = ~BR_x;

    // step 3: 2's complement = NOT + 1
    assign adder_out = NOT_out + 1;

    // step 4: AND between BR_x and its 2's complement
    assign AND_out = BR_x & adder_out;

    // step 5: bit reverse AND_out to get LOD(x_in)
    // generate
    //     for(i = 0; i < W; i = i+1) begin
    //         assign x_out[W-i-1] = AND_out[i];
    //     end
    // endgenerate

    assign x_out = bit_reverse(AND_out);

    function [W-1:0] bit_reverse;
        input [W-1:0] in;
        integer k;
        begin
            for (k = 0; k < W; k = k + 1)
                bit_reverse[k] = in[W-1-k];
        end
    endfunction


    // integer i;
    // always @(*) begin
    //     x_out = 0;
    //     for(i = 0; i < W; i = i + 1) begin
    //         if (x_in[i])
    //             x_out = i;
    //     end
    // end

endmodule

rtl/initial_approx.v
`timescale 1ns/1ps

module initial_approx #(parameter N = 8, parameter W = 16) (
    input  [W-1:0] a_in,
    output reg [W-1:0] approx_out
);

    integer j;
    integer i;
    integer target_idx;
    integer shift;
    reg next_bit;
    reg found;

    wire [W-1:0] lod_out;

    LOD #(W) lod_inst (
        .x_in(a_in),
        .x_out(lod_out)
    );

    always @(*) begin
        approx_out = 0;

        // extract index from one-hot
        j = 0;
        for (i = 0; i < W; i = i + 1) begin
            if (lod_out[i])
                j = i;
        end

        // ------------------------
        // same logic as before
        // ------------------------

        if (j[0]) begin
            // ODD

            if (j >= N) begin
                shift = (j - N + 1) >> 1;
                if ((N - shift) >= 0 && (N - shift) < W)
                    approx_out[N - shift] = 1'b1;
            end else begin
                shift = (N - j) >> 1;
                if ((N + shift) < W)
                    approx_out[N + shift] = 1'b1;
            end

        end else begin
            // EVEN

            if (j >= N) begin
                shift = (j - N) >> 1;

                if ((N - (shift+1)) >= 0 && (N - (shift+1)) < W)
                    approx_out[N - (shift+1)] = 1'b1;

                if ((N - (shift+2)) >= 0 && (N - (shift+2)) < W)
                    approx_out[N - (shift+2)] = 1'b1;

            end else begin
                shift = (N - j) >> 1;

                if ((N + shift) < W)
                    approx_out[N + shift] = 1'b1;
            end
        end
    end
endmodule

sim/tb_approx.v
`timescale 1ns/1ps

module tb_approx;
    parameter N = 8;
    parameter W = 16;
    
    reg clk, rst;
    reg [W-1:0] a_in;
    wire [W-1:0] approx_out;
    

    initial clk = 0;
    always #5 clk = ~clk;

    initial_approx #(N, W) dut (
        .a_in(a_in),
        .approx_out(approx_out)
    );

    initial begin       
        a_in = 16'd1024; #10; $display("Time: %t | Input A: %d | Approx Output: %d ", $time, a_in, approx_out);
        a_in = 16'd512;  #10; $display("Time: %t | Input A: %d | Approx Output: %d ", $time, a_in, approx_out);
        a_in = 16'd256;  #10; $display("Time: %t | Input A: %d | Approx Output: %d ", $time, a_in, approx_out);
        a_in = 16'd64;   #10; $display("Time: %t | Input A: %d | Approx Output: %d ", $time, a_in, approx_out);
        a_in = 16'd2048; #10; $display("Time: %t | Input A: %d | Approx Output: %d ", $time, a_in, approx_out);
        a_in = 16'd4096; #10; $display("Time: %t | Input A: %d | Approx Output: %d ", $time, a_in, approx_out);
        a_in = 16'd16384;#10; $display("Time: %t | Input A: %d | Approx Output: %d ", $time, a_in, approx_out);

        // Non power-of-2 values
        a_in = 16'd300;   #10; $display("Time: %t | Input A: %d | Approx Output: %d ", $time, a_in, approx_out);
        a_in = 16'd700;   #10; $display("Time: %t | Input A: %d | Approx Output: %d ", $time, a_in, approx_out);
        a_in = 16'd1500;  #10; $display("Time: %t | Input A: %d | Approx Output: %d ", $time, a_in, approx_out);
        a_in = 16'd25600; #10; $display("Time: %t | Input A: %d | Approx Output: %d ", $time, a_in, approx_out);
        a_in = 16'd36864; #10; $display("Time: %t | Input A: %d | Approx Output: %d ", $time, a_in, approx_out);
        a_in = 16'd57600; #10; $display("Time: %t | Input A: %d | Approx Output: %d ", $time, a_in, approx_out);

        // Boundary around 1.0 (Q8.8)
        a_in = 16'd255; #10; $display("Time: %t | Input A: %d | Approx Output: %d ", $time, a_in, approx_out);
        a_in = 16'd256; #10; $display("Time: %t | Input A: %d | Approx Output: %d ", $time, a_in, approx_out);
        a_in = 16'd257; #10; $display("Time: %t | Input A: %d | Approx Output: %d ", $time, a_in, approx_out);

        // Power-of-2 edges
        a_in = 16'd511;  #10; $display("Time: %t | Input A: %d | Approx Output: %d ", $time, a_in, approx_out);
        a_in = 16'd513;  #10; $display("Time: %t | Input A: %d | Approx Output: %d ", $time, a_in, approx_out);
        a_in = 16'd1023; #10; $display("Time: %t | Input A: %d | Approx Output: %d ", $time, a_in, approx_out);
        a_in = 16'd1025; #10; $display("Time: %t | Input A: %d | Approx Output: %d ", $time, a_in, approx_out);

        // very small
        a_in = 16'd1; #10; $display("Time: %t | Input A: %d | Approx Output: %d ", $time, a_in, approx_out);
        a_in = 16'd2; #10; $display("Time: %t | Input A: %d | Approx Output: %d ", $time, a_in, approx_out);
        a_in = 16'd3; #10; $display("Time: %t | Input A: %d | Approx Output: %d ", $time, a_in, approx_out);
        a_in = 16'd4; #10; $display("Time: %t | Input A: %d | Approx Output: %d ", $time, a_in, approx_out);
        a_in = 16'd8; #10; $display("Time: %t | Input A: %d | Approx Output: %d ", $time, a_in, approx_out);

        // Upper range stress
        a_in = 16'd32768; #10; $display("Time: %t | Input A: %d | Approx Output: %d ", $time, a_in, approx_out);
        a_in = 16'd40000; #10; $display("Time: %t | Input A: %d | Approx Output: %d ", $time, a_in, approx_out);
        a_in = 16'd50000; #10; $display("Time: %t | Input A: %d | Approx Output: %d ", $time, a_in, approx_out);
        a_in = 16'd65535; #10; $display("Time: %t | Input A: %d | Approx Output: %d ", $time, a_in, approx_out);        $finish;
    end

    initial begin
        $dumpfile("approx.vcd");   // output file
        $dumpvars(0, tb_approx); // dump entire testbench hierarchy
    end
endmodule

out/vcd/approx.vcd
$date
	Sun Apr  5 19:52:32 2026
$end
$version
	Icarus Verilog
$end
$timescale
	1ps
$end
$scope module tb_approx $end
$var wire 16 ! approx_out [15:0] $end
$var reg 16 " a_in [15:0] $end
$var reg 1 # clk $end
$scope module dut $end
$var wire 16 $ a_in [15:0] $end
$var wire 16 % lod_out [15:0] $end
$var reg 16 & approx_out [15:0] $end
$var integer 32 ' i [31:0] $end
$var integer 32 ( j [31:0] $end
$var integer 32 ) shift [31:0] $end
$scope module lod_inst $end
$var wire 16 * AND_out [15:0] $end
$var wire 16 + NOT_out [15:0] $end
$var wire 16 , x_in [15:0] $end
$var wire 16 - x_out [15:0] $end
$var wire 16 . adder_out [15:0] $end
$var wire 16 / BR_x [15:0] $end
$scope function bit_reverse $end
$var reg 16 0 in [15:0] $end
$var integer 32 1 k [31:0] $end
$upscope $end
$upscope $end
$upscope $end
$upscope $end
$enddefinitions $end
#0
$dumpvars
b10000 1
b100000 0
b100000 /
b1111111111100000 .
b10000000000 -
b10000000000 ,
b1111111111011111 +
b100000 *
b1 )
b1010 (
b10000 '
b1100000 &
b10000000000 %
b10000000000 $
0#
b10000000000 "
b1100000 !
$end
#5000
1#
#10000
b10000 '
b1001 (
b10000000 !
b10000000 &
b1000000000 %
b1000000000 -
b1000000 *
b1111111111000000 .
b1111111110111111 +
b1000000 /
b10000 1
b1000000 0
0#
b1000000000 "
b1000000000 $
b1000000000 ,
#15000
1#
#20000
b0 )
b10000 '
b1000 (
b11000000 !
b11000000 &
b100000000 %
b100000000 -
b10000000 *
b1111111110000000 .
b1111111101111111 +
b10000000 /
b10000 1
b10000000 0
0#
b100000000 "
b100000000 $
b100000000 ,
#25000
1#
#30000
b1 )
b10000 '
b110 (
b1000000000 !
b1000000000 &
b1000000 %
b1000000 -
b1000000000 *
b1111111000000000 .
b1111110111111111 +
b1000000000 /
b10000 1
b1000000000 0
0#
b1000000 "
b1000000 $
b1000000 ,
#35000
1#
#40000
b10 )
b10000 '
b1011 (
b1000000 !
b1000000 &
b100000000000 %
b100000000000 -
b10000 *
b1111111111110000 .
b1111111111101111 +
b10000 /
b10000 1
b10000 0
0#
b100000000000 "
b100000000000 $
b100000000000 ,
#45000
1#
#50000
b10000 '
b1100 (
b110000 !
b110000 &
b1000000000000 %
b1000000000000 -
b1000 *
b1111111111111000 .
b1111111111110111 +
b1000 /
b10000 1
b1000 0
0#
b1000000000000 "
b1000000000000 $
b1000000000000 ,
#55000
1#
#60000
b11 )
b10000 '
b1110 (
b11000 !
b11000 &
b100000000000000 %
b100000000000000 -
b10 *
b1111111111111110 .
b1111111111111101 +
b10 /
b10000 1
b10 0
0#
b100000000000000 "
b100000000000000 $
b100000000000000 ,
#65000
1#
#70000
b0 )
b10000 '
b1000 (
b11000000 !
b11000000 &
b100000000 %
b100000000 -
b10000000 *
b1100101110000000 .
b1100101101111111 +
b11010010000000 /
b10000 1
b10000000 0
0#
b100101100 "
b100101100 $
b100101100 ,
#75000
1#
#80000
b1 )
b10000 '
b1001 (
b10000000 !
b10000000 &
b1000000000 %
b1000000000 -
b1000000 *
b1100001011000000 .
b1100001010111111 +
b11110101000000 /
b10000 1
b1000000 0
0#
b1010111100 "
b1010111100 $
b1010111100 ,
#85000
1#
#90000
b10000 '
b1010 (
b1100000 !
b1100000 &
b10000000000 %
b10000000000 -
b100000 *
b1100010001100000 .
b1100010001011111 +
b11101110100000 /
b10000 1
b100000 0
0#
b10111011100 "
b10111011100 $
b10111011100 ,
#95000
1#
#100000
b11 )
b10000 '
b1110 (
b11000 !
b11000 &
b100000000000000 %
b100000000000000 -
b10 *
b1111111111011010 .
b1111111111011001 +
b100110 /
b10000 1
b10 0
0#
b110010000000000 "
b110010000000000 $
b110010000000000 ,
#105000
1#
#110000
b100 )
b10000 '
b1111 (
b10000 !
b10000 &
b1000000000000000 %
b1000000000000000 -
b1 *
b1111111111110111 .
b1111111111110110 +
b1001 /
b10000 1
b1 0
0#
b1001000000000000 "
b1001000000000000 $
b1001000000000000 ,
#115000
1#
#120000
b1111111101111001 .
b1111111101111000 +
b10000111 /
b10000 1
b1110000100000000 0
0#
b1110000100000000 "
b1110000100000000 $
b1110000100000000 ,
#125000
1#
#130000
b0 )
b10000 '
b111 (
b100000000 !
b100000000 &
b10000000 %
b10000000 -
b100000000 *
b100000000 .
b11111111 +
b1111111100000000 /
b10000 1
b100000000 0
0#
b11111111 "
b11111111 $
b11111111 ,
#135000
1#
#140000
b10000 '
b1000 (
b11000000 !
b11000000 &
b100000000 %
b100000000 -
b10000000 0
b10000000 *
b1111111110000000 .
b1111111101111111 +
b10000000 /
b10000 1
0#
b100000000 "
b100000000 $
b100000000 ,
#145000
1#
#150000
b111111110000000 .
b111111101111111 +
b1000000010000000 /
b10000 1
b100000001 0
0#
b100000001 "
b100000001 $
b100000001 ,
#155000
1#
#160000
b10000000 .
b1111111 +
b1111111110000000 /
b10000 1
b111111111 0
0#
b111111111 "
b111111111 $
b111111111 ,
#165000
1#
#170000
b1 )
b10000 '
b1001 (
b10000000 !
b10000000 &
b1000000000 %
b1000000000 -
b1000000 *
b111111111000000 .
b111111110111111 +
b1000000001000000 /
b10000 1
b1000000 0
0#
b1000000001 "
b1000000001 $
b1000000001 ,
#175000
1#
#180000
b1000000 .
b111111 +
b1111111111000000 /
b10000 1
b1111111111 0
0#
b1111111111 "
b1111111111 $
b1111111111 ,
#185000
1#
#190000
b10000 '
b1010 (
b1100000 !
b1100000 &
b10000000000 %
b10000000000 -
b100000 *
b111111111100000 .
b111111111011111 +
b1000000000100000 /
b10000 1
b100000 0
0#
b10000000001 "
b10000000001 $
b10000000001 ,
#195000
1#
#200000
b100 )
b10000 '
b0 (
b1000000000000 !
b1000000000000 &
b1 %
b1 -
b1000000000000000 *
b1000000000000000 .
b111111111111111 +
b1000000000000000 /
b10000 1
b1000000000000000 0
0#
b1 "
b1 $
b1 ,
#205000
1#
#210000
b11 )
b1 (
b10000 '
b100000000000 !
b100000000000 &
b10 %
b10 -
b100000000000000 *
b1100000000000000 .
b1011111111111111 +
b100000000000000 /
b10000 1
b100000000000000 0
0#
b10 "
b10 $
b10 ,
#215000
1#
#220000
b100000000000000 .
b11111111111111 +
b1100000000000000 /
b10000 1
b11 0
0#
b11 "
b11 $
b11 ,
#225000
1#
#230000
b10000 '
b10 (
b100000000000 !
b100000000000 &
b100 %
b100 -
b10000000000000 *
b1110000000000000 .
b1101111111111111 +
b10000000000000 /
b10000 1
b10000000000000 0
0#
b100 "
b100 $
b100 ,
#235000
1#
#240000
b10 )
b10000 '
b11 (
b10000000000 !
b10000000000 &
b1000 %
b1000 -
b1000000000000 *
b1111000000000000 .
b1110111111111111 +
b1000000000000 /
b10000 1
b1000000000000 0
0#
b1000 "
b1000 $
b1000 ,
#245000
1#
#250000
b100 )
b10000 '
b1111 (
b10000 !
b10000 &
b1000000000000000 %
b1000000000000000 -
b1 *
b1111111111111111 .
b1111111111111110 +
b1 /
b10000 1
b1 0
0#
b1000000000000000 "
b1000000000000000 $
b1000000000000000 ,
#255000
1#
#260000
b1111110111000111 .
b1111110111000110 +
b1000111001 /
b10000 1
b1001110001000000 0
0#
b1001110001000000 "
b1001110001000000 $
b1001110001000000 ,
#265000
1#
#270000
b1111010100111101 .
b1111010100111100 +
b101011000011 /
b10000 1
b1100001101010000 0
0#
b1100001101010000 "
b1100001101010000 $
b1100001101010000 ,
#275000
1#
#280000
b1 .
b0 +
b1111111111111111 /
b10000 1
b1111111111111111 0
0#
b1111111111111111 "
b1111111111111111 $
b1111111111111111 ,
