rtl/LOD.v
`timescale 1ns/1ps

module LOD #(parameter W = 16)(
    input  [W-1:0] x_in,
    output [W-1:0] x_out
);

    wire [W-1:0] BR_x;
    wire [W-1:0] NOT_out;
    wire [W-1:0] adder_out;
    wire [W-1:0] AND_out;

    // step 1: bit reversal of x_in
    // genvar i;
    // generate
    //     for(i = 0; i < W; i = i+1) begin
    //         assign BR_x[W-i-1] = x_in[i];
    //     end
    // endgenerate

    assign BR_x = bit_reverse(x_in); 

    // step 2: NOT of BR_x
    assign NOT_out = ~BR_x;

    // step 3: 2's complement = NOT + 1
    assign adder_out = NOT_out + 1;

    // step 4: AND between BR_x and its 2's complement
    assign AND_out = BR_x & adder_out;

    // step 5: bit reverse AND_out to get LOD(x_in)
    // generate
    //     for(i = 0; i < W; i = i+1) begin
    //         assign x_out[W-i-1] = AND_out[i];
    //     end
    // endgenerate

    assign x_out = bit_reverse(AND_out);

    function [W-1:0] bit_reverse;
        input [W-1:0] in;
        integer k;
        begin
            for (k = 0; k < W; k = k + 1)
                bit_reverse[k] = in[W-1-k];
        end
    endfunction


    // integer i;
    // always @(*) begin
    //     x_out = 0;
    //     for(i = 0; i < W; i = i + 1) begin
    //         if (x_in[i])
    //             x_out = i;
    //     end
    // end

endmodule

sim/tb_lod.v
`timescale 1ns/1ps

module tb_lod;
    parameter N = 16;
    
    reg clk, rst;
    reg [N-1:0] x_in;
    wire [N-1:0] x_out;
    

    initial clk = 0;
    always #5 clk = ~clk;

    LOD #(N) dut (
        .x_in(x_in),
        .x_out(x_out)
    );

    initial begin       
        x_in = 16'd1024; #10; $display("Time: %t | Input A: %d | LOD Output: %d ", $time, x_in, x_out);
        x_in = 16'd512; #10; $display("Time: %t | Input A: %d | LOD Output: %d ", $time, x_in, x_out);
        x_in = 16'd256; #10; $display("Time: %t | Input A: %d | LOD Output: %d ", $time, x_in, x_out);
        x_in = 16'd64; #10; $display("Time: %t | Input A: %d | LOD Output: %d ", $time, x_in, x_out);
        x_in = 16'd2048; #10; $display("Time: %t | Input A: %d | LOD Output: %d ", $time, x_in, x_out);
        x_in = 16'd4096; #10; $display("Time: %t | Input A: %d | LOD Output: %d ", $time, x_in, x_out);
        x_in = 16'd16384; #10; $display("Time: %t | Input A: %d | LOD Output: %d ", $time, x_in, x_out);
        x_in = 16'd25600; #10; $display("Time: %t | Input A: %d | LOD Output: %d ", $time, x_in, x_out);
        x_in = 16'd57600; #10; $display("Time: %t | Input A: %d | LOD Output: %d ", $time, x_in, x_out);
        $finish;
    end

    initial begin
        $dumpfile("lod.vcd");   // output file
        $dumpvars(0, tb_lod); // dump entire testbench hierarchy
    end
endmodule

out/vcd/lod.vcd
$date
	Mon Apr  6 00:04:24 2026
$end
$version
	Icarus Verilog
$end
$timescale
	1ps
$end
$scope module tb_lod $end
$var wire 16 ! x_out [15:0] $end
$var reg 1 " clk $end
$var reg 16 # x_in [15:0] $end
$scope module dut $end
$var wire 16 $ AND_out [15:0] $end
$var wire 16 % NOT_out [15:0] $end
$var wire 16 & x_in [15:0] $end
$var wire 16 ' x_out [15:0] $end
$var wire 16 ( adder_out [15:0] $end
$var wire 16 ) BR_x [15:0] $end
$scope function bit_reverse $end
$var reg 16 * in [15:0] $end
$var integer 32 + k [31:0] $end
$upscope $end
$upscope $end
$upscope $end
$enddefinitions $end
#0
$dumpvars
b10000 +
b100000 *
b100000 )
b1111111111100000 (
b10000000000 '
b10000000000 &
b1111111111011111 %
b100000 $
b10000000000 #
0"
b10000000000 !
$end
#5000
1"
#10000
b1000000000 !
b1000000000 '
b1000000 $
b1111111111000000 (
b1111111110111111 %
b1000000 )
b10000 +
b1000000 *
0"
b1000000000 #
b1000000000 &
#15000
1"
#20000
b100000000 !
b100000000 '
b10000000 $
b1111111110000000 (
b1111111101111111 %
b10000000 )
b10000 +
b10000000 *
0"
b100000000 #
b100000000 &
#25000
1"
#30000
b1000000 !
b1000000 '
b1000000000 $
b1111111000000000 (
b1111110111111111 %
b1000000000 )
b10000 +
b1000000000 *
0"
b1000000 #
b1000000 &
#35000
1"
#40000
b100000000000 !
b100000000000 '
b10000 $
b1111111111110000 (
b1111111111101111 %
b10000 )
b10000 +
b10000 *
0"
b100000000000 #
b100000000000 &
#45000
1"
#50000
b1000000000000 !
b1000000000000 '
b1000 $
b1111111111111000 (
b1111111111110111 %
b1000 )
b10000 +
b1000 *
0"
b1000000000000 #
b1000000000000 &
#55000
1"
#60000
b100000000000000 !
b100000000000000 '
b10 $
b1111111111111110 (
b1111111111111101 %
b10 )
b10000 +
b10 *
0"
b100000000000000 #
b100000000000000 &
#65000
1"
#70000
b1111111111011010 (
b1111111111011001 %
b100110 )
b10000 +
b110010000000000 *
0"
b110010000000000 #
b110010000000000 &
#75000
1"
#80000
b1000000000000000 !
b1000000000000000 '
b1 $
b1111111101111001 (
b1111111101111000 %
b10000111 )
b10000 +
b1 *
0"
b1110000100000000 #
b1110000100000000 &
