rtl/NR_stage.v
`timescale 1ns/1ps

module NR_stage #(parameter N = 8, parameter W = 2*N)(
    input  signed [W-1:0] x_in,
    input  signed [W-1:0] a,
    output signed [W-1:0] x_out
);

    wire signed [2*W-1:0] x_sq_full;
    assign x_sq_full = x_in * x_in;

    wire signed [W-1:0] x_sq;
    wire signed [2*W-1:0] x_sq_shifted;
    assign x_sq_shifted = x_sq_full >>> N;

    assign x_sq = x_sq_shifted[W-1:0];
    wire signed [2*W-1:0] ax2_full;
    assign ax2_full = a * x_sq;

    wire signed [W-1:0] ax2;
    wire signed [2*W-1:0] ax2_shifted;
    assign ax2_shifted = ax2_full >>> N;
    assign ax2 = ax2_shifted[W-1:0];


    wire signed [W-1:0] term;
    assign term = (3 <<< N) - ax2;

    wire signed [2*W-1:0] mult_full;
    assign mult_full = x_in * term;

    wire signed [W-1:0] mult;
    wire signed [2*W-1:0] mult_shifted;
    assign mult_shifted = mult_full >>> N;
    assign mult = mult_shifted[W-1:0];


    assign x_out = mult >>> 1;

endmodule

rtl/inv_sqr_root.v
`timescale 1ns/1ps

module inv_sqr_root #(parameter N = 8, parameter W = 2*N)(
    input clk,
    input rst,
    input  signed [W-1:0] x0,
    input  signed [W-1:0] a,
    output signed [W-1:0] result
);

    localparam ITER = 4;

    // pipeline registers
    reg signed [W-1:0] x_pipe [0:ITER];

    // combinational outputs
    wire signed [W-1:0] x_next [0:ITER-1];

    // Stage 0 input
    always @(posedge clk) begin
        if(rst)
            x_pipe[0] <= 0;
        else
            x_pipe[0] <= x0;
    end

    // NR stages (combinational)
    genvar i;
    generate
        for (i = 0; i < ITER; i = i + 1) begin : NR

            NR_stage #(N, W) stage (
                .x_in(x_pipe[i]),
                .a(a),
                .x_out(x_next[i])
            );

            // pipeline register AFTER stage
            always @(posedge clk) begin
                if(rst)
                    x_pipe[i+1] <= 0;
                else
                    x_pipe[i+1] <= x_next[i];
            end

        end
    endgenerate

    assign result = x_pipe[ITER];

endmodule

sim/tb_nonpipeline.v
`timescale 1ns/1ps

module tb_nonpipeline;

    parameter N = 8;
    parameter W = 16;

    reg [W-1:0] a;
    reg [W-1:0] x0;
    reg clk;
    reg rst;
    wire [W-1:0] result;

    localparam ITER = 4;

     // Clock generation
    initial begin
        clk = 0;
        forever #5 clk = ~clk; // 100 MHz clock
    end
    
    inv_sqr_root #(N, W) dut (
        .clk(clk),
        .rst(rst),
        .a(a),
        .x0(x0),
        .result(result)
    );

    initial begin
        // TEST 1: a = 4.0, x0 = 0.4
        rst = 1;
        #10;
        rst = 0;

        a = 16'd1024; // 4.0 in fixed-point
        x0 = 16'd50;  // 0.4 in fixed-point

        repeat(ITER+2) @(posedge clk);
        $display("TEST 1 (a=4.0, x0=0.4): Result = %d -- Expected: 128", result);

        // TEST 2: a = 8.0, x0 = 0.33
        a = 16'd2048; // 8.0 in fixed-point
        x0 = 16'd50;  // 0.33 in fixed-point
        #(ITER * 10); // Wait for all iterations to complete

        repeat(ITER+2) @(posedge clk);
        $display("TEST 2 (a=8.0, x0=0.33): Result = %d -- Expected: 91", result);

        
        // TEST 3: a = 2.0, x0 = 0.7
        a = 16'd512; // 2.0 in fixed-point
        x0 = 16'd120; // 0.7 in fixed-point
        #(ITER * 10); // Wait for all iterations to complete

        repeat(ITER+2) @(posedge clk);
        $display("TEST 3 (a=2.0, x0=0.7): Result = %d -- Expected: 181", result);

        $finish;
    end


    initial begin
        $dumpfile("nr_nonpipe.vcd");   // output file
        $dumpvars(0, tb_nonpipeline); // dump entire testbench hierarchy
    end




endmodule

out/vcd/nr_nonpipe.vcd
$date
	Mon Apr  6 01:03:00 2026
$end
$version
	Icarus Verilog
$end
$timescale
	1ps
$end
$scope module tb_nonpipeline $end
$var wire 16 ! result [15:0] $end
$var reg 16 " a [15:0] $end
$var reg 1 # clk $end
$var reg 1 $ rst $end
$var reg 16 % x0 [15:0] $end
$scope module dut $end
$var wire 16 & a [15:0] $end
$var wire 1 # clk $end
$var wire 16 ' result [15:0] $end
$var wire 1 $ rst $end
$var wire 16 ( x0 [15:0] $end
$scope begin NR[0] $end
$scope module stage $end
$var wire 16 ) a [15:0] $end
$var wire 16 * x_in [15:0] $end
$var wire 32 + x_sq_shifted [31:0] $end
$var wire 32 , x_sq_full [31:0] $end
$var wire 16 - x_sq [15:0] $end
$var wire 16 . x_out [15:0] $end
$var wire 16 / term [15:0] $end
$var wire 32 0 mult_shifted [31:0] $end
$var wire 32 1 mult_full [31:0] $end
$var wire 16 2 mult [15:0] $end
$var wire 32 3 ax2_shifted [31:0] $end
$var wire 32 4 ax2_full [31:0] $end
$var wire 16 5 ax2 [15:0] $end
$upscope $end
$upscope $end
$scope begin NR[1] $end
$scope module stage $end
$var wire 16 6 a [15:0] $end
$var wire 16 7 x_in [15:0] $end
$var wire 32 8 x_sq_shifted [31:0] $end
$var wire 32 9 x_sq_full [31:0] $end
$var wire 16 : x_sq [15:0] $end
$var wire 16 ; x_out [15:0] $end
$var wire 16 < term [15:0] $end
$var wire 32 = mult_shifted [31:0] $end
$var wire 32 > mult_full [31:0] $end
$var wire 16 ? mult [15:0] $end
$var wire 32 @ ax2_shifted [31:0] $end
$var wire 32 A ax2_full [31:0] $end
$var wire 16 B ax2 [15:0] $end
$upscope $end
$upscope $end
$scope begin NR[2] $end
$scope module stage $end
$var wire 16 C a [15:0] $end
$var wire 16 D x_in [15:0] $end
$var wire 32 E x_sq_shifted [31:0] $end
$var wire 32 F x_sq_full [31:0] $end
$var wire 16 G x_sq [15:0] $end
$var wire 16 H x_out [15:0] $end
$var wire 16 I term [15:0] $end
$var wire 32 J mult_shifted [31:0] $end
$var wire 32 K mult_full [31:0] $end
$var wire 16 L mult [15:0] $end
$var wire 32 M ax2_shifted [31:0] $end
$var wire 32 N ax2_full [31:0] $end
$var wire 16 O ax2 [15:0] $end
$upscope $end
$upscope $end
$scope begin NR[3] $end
$scope module stage $end
$var wire 16 P a [15:0] $end
$var wire 16 Q x_in [15:0] $end
$var wire 32 R x_sq_shifted [31:0] $end
$var wire 32 S x_sq_full [31:0] $end
$var wire 16 T x_sq [15:0] $end
$var wire 16 U x_out [15:0] $end
$var wire 16 V term [15:0] $end
$var wire 32 W mult_shifted [31:0] $end
$var wire 32 X mult_full [31:0] $end
$var wire 16 Y mult [15:0] $end
$var wire 32 Z ax2_shifted [31:0] $end
$var wire 32 [ ax2_full [31:0] $end
$var wire 16 \ ax2 [15:0] $end
$upscope $end
$upscope $end
$upscope $end
$upscope $end
$enddefinitions $end
#0
$dumpvars
bx \
bx [
bx Z
bx Y
bx X
bx W
bx V
bx U
bx T
bx S
bx R
bx Q
bx P
bx O
bx N
bx M
bx L
bx K
bx J
bx I
bx H
bx G
bx F
bx E
bx D
bx C
bx B
bx A
bx @
bx ?
bx >
bx =
bx <
bx ;
bx :
bx 9
bx 8
bx 7
bx 6
bx 5
bx 4
bx 3
bx 2
bx 1
bx 0
bx /
bx .
bx -
bx ,
bx +
bx *
bx )
bx (
bx '
bx &
bx %
1$
0#
bx "
bx !
$end
#5000
b0 :
b0 G
b0 T
b0 -
b0 8
b0 E
b0 R
b0 +
b0 9
b0 7
b0 F
b0 D
b0 S
b0 Q
b0 !
b0 '
b0 ,
b0 *
1#
#10000
b0 .
b0 ;
b0 H
b0 U
b0 2
b0 ?
b0 L
b0 Y
b0 0
b0 =
b0 J
b0 W
b0 1
b1100000000 /
b0 5
b0 >
b1100000000 <
b0 B
b0 K
b1100000000 I
b0 O
b0 X
b1100000000 V
b0 \
b0 3
b0 @
b0 M
b0 Z
0#
b110010 %
b110010 (
b0 4
b0 A
b0 N
b0 [
b10000000000 "
b10000000000 &
b10000000000 )
b10000000000 6
b10000000000 C
b10000000000 P
0$
#15000
b1011011100 /
b100100 5
b100100 3
b1000111 .
b10010000000000 4
b1001 -
b10001110 2
b1001 +
b10001110 0
b100111000100 ,
b1000111011111000 1
b110010 *
1#
#20000
0#
#25000
b1010110100 <
b1001100 B
b1001100 @
b1011111 ;
b100110000000000 A
b10011 :
b10111111 ?
b10011 8
b10111111 =
b1001110110001 9
b1011111111101100 >
b1000111 7
1#
#30000
0#
#35000
b1001110100 I
b10001100 O
b10001100 M
b1110100 H
b1000110000000000 N
b100011 G
b11101001 L
b100011 E
b11101001 J
b10001101000001 F
b1110100100001100 K
b1011111 D
1#
#40000
0#
#45000
b1000110000 V
b11010000 \
b11010000 Z
b1111110 U
b1101000000000000 [
b110100 T
b11111101 Y
b110100 R
b11111101 W
b11010010010000 S
b1111110111000000 X
b1110100 Q
1#
#50000
0#
#55000
b1111110 !
b1111110 '
1#
#60000
0#
#65000
b1000011 .
b1010101 ;
b1011010 H
b1001111 U
b10000111 2
b10101010 ?
b10110101 L
b10011111 Y
b10000111 0
b10101010 =
b10110101 J
b10011111 W
b1000011111110000 1
b1010111000 /
b1001000 5
b1010101011011000 >
b1001101000 <
b10011000 B
b1011010100011000 K
b111101000 I
b100011000 O
b1001111110000000 X
b101100000 V
b110100000 \
b1001000 3
b10011000 @
b100011000 M
b110100000 Z
b100100000000000 4
b1001100000000000 A
b10001100000000000 N
b11010000000000000 [
b100000000000 "
b100000000000 &
b100000000000 )
b100000000000 6
b100000000000 C
b100000000000 P
1#
#70000
0#
#75000
b1000001000 V
b11111000 \
b1000100000 I
b11100000 O
b1001111000 <
b10001000 B
b11111000 Z
b1011011 U
b11100000 M
b1011010 H
b10001000 @
b1010010 ;
b1111100000000000 [
b11111 T
b10110110 Y
b1110000000000000 N
b11100 G
b10110100 L
b1000100000000000 A
b10001 :
b10100101 ?
b11111 R
b10110110 W
b11100 E
b10110100 J
b10001 8
b10100101 =
b1001111 !
b1001111 '
b1111110100100 S
b1011011011010000 X
b1011010 Q
b1110000111001 F
b1011010010100000 K
b1010101 D
b1000110001001 9
b1010010101101000 >
b1000011 7
1#
#80000
0#
#85000
b1000110000 I
b11010000 O
b11010000 M
b1011001 H
b1101000000000000 N
b11010 G
b10110011 L
b11010 E
b10110011 J
b1101001000100 F
b1011001101100000 K
b1010010 D
b1011011 !
b1011011 '
1#
#90000
0#
#95000
b1000010000 V
b11110000 \
b11110000 Z
b1011011 U
b1111000000000000 [
b11110 T
b10110111 Y
b11110 R
b10110111 W
b1111011110001 S
b1011011110010000 X
b1011001 Q
1#
#100000
0#
#105000
1#
#110000
0#
#115000
1#
#120000
0#
#125000
1#
#130000
0#
#135000
1#
#140000
0#
#145000
1#
#150000
0#
#155000
b1001001 .
b1100000 ;
b1110010 H
b1111011 U
b10010010 2
b11000000 ?
b11100101 L
b11110110 Y
b10010010 0
b11000000 =
b11100101 J
b11110110 W
b1001001001111100 1
b1011101110 /
b10010 5
b1100000000011010 >
b1011011110 <
b100010 B
b1110010101011000 K
b1011001100 I
b110100 O
b1111011000100100 X
b1011000100 V
b111100 \
b10010 3
b100010 @
b110100 M
b111100 Z
b1111000 %
b1111000 (
b1001000000000 4
b10001000000000 A
b11010000000000 N
b11110000000000 [
b1000000000 "
b1000000000 &
b1000000000 )
b1000000000 6
b1000000000 C
b1000000000 P
1#
#160000
0#
#165000
b1011011000 <
b101000 B
b1010111000 I
b1001000 O
b1010011100 V
b1100100 \
b1010010000 /
b1110000 5
b101000 @
b1100111 ;
b1001000 M
b10000010 H
b1100100 Z
b10010100 U
b1110000 3
b10011001 .
b10100000000000 A
b10100 :
b11001111 ?
b100100000000000 N
b100100 G
b100000101 L
b110010000000000 [
b110010 T
b100101001 Y
b111000000000000 4
b111000 -
b100110011 2
b10100 8
b11001111 =
b100100 E
b100000101 J
b110010 R
b100101001 W
b111000 +
b100110011 0
b1010011010001 9
b1100111110011000 >
b1001001 7
b10010000000000 F
b10000010100000000 K
b1100000 D
b11001011000100 S
b10010100101111000 X
b1110010 Q
b1111011 !
b1111011 '
b11100001000000 ,
b10011001110000000 1
b1111000 *
1#
#170000
0#
#175000
b1001111100 V
b10000100 \
b1010101110 I
b1010010 O
b1001001010 <
b10110110 B
b10000100 Z
b10100001 U
b1010010 M
b10001010 H
b10110110 @
b10101111 ;
b1000010000000000 [
b1000010 T
b101000010 Y
b101001000000000 N
b101001 G
b100010100 L
b1011011000000000 A
b1011011 :
b101011110 ?
b1000010 R
b101000010 W
b101001 E
b100010100 J
b1011011 8
b101011110 =
b10010100 !
b10010100 '
b100001000000100 S
b10100001011111000 X
b10000010 Q
b10100101110001 F
b10001010000000010 K
b1100111 D
b101101101110001 9
b10101111000111010 >
b10011001 7
1#
#180000
0#
#185000
b1000010010 I
b11101110 O
b1001101100 V
b10010100 \
b11101110 M
b10110101 H
b10010100 Z
b10100111 U
b1110111000000000 N
b1110111 G
b101101010 L
b1001010000000000 [
b1001010 T
b101001110 Y
b1110111 E
b101101010 J
b1001010 R
b101001110 W
b111011110100001 F
b10110101001001110 K
b10101111 D
b100101001100100 S
b10100111000111000 X
b10001010 Q
b10100001 !
b10100001 '
1#
#190000
0#
#195000
b1000000010 V
b11111110 \
b11111110 Z
b10110101 U
b1111111000000000 [
b1111111 T
b101101011 Y
b1111111 R
b101101011 W
b10100111 !
b10100111 '
b111111111111001 S
b10110101101101010 X
b10110101 Q
1#
#200000
0#
#205000
b10110101 !
b10110101 '
1#
