rtl/NR_stage_pipeline.v
`timescale 1ns/1ps

module NR_stage_pipeline #(parameter N = 8, parameter W = 16)(
    input  clk, rst,
    input [W-1:0] x_in,
    input [W-1:0] a_in,
    output [W-1:0] x_out
);
    // Stage 1: x^2 (Q8.8 * Q8.8 = Q16.16)
    reg [W-1:0] x_reg1, a_reg1, x_sq_reg1;
    wire [(2*W)-1:0] x_sq_full = x_in * x_in;

    always @(posedge clk) begin
        if (rst) begin
            x_reg1 <= 0; a_reg1 <= 0; x_sq_reg1 <= 0;
        end else begin
            x_reg1 <= x_in;
            a_reg1 <= a_in;
            x_sq_reg1 <= x_sq_full >>> N;
        end
    end

    // Stage 2: (3 - a*x^2)
    reg [W-1:0] x_reg2, term_reg2;
    wire [(2*W)-1:0] ax2_full = a_reg1 * x_sq_reg1;

    always @(posedge clk) begin
        if (rst) begin
            x_reg2 <= 0; term_reg2 <= 0;
        end else begin
            x_reg2 <= x_reg1;
            term_reg2 <= (3 << N) - (ax2_full >>> N);
        end
    end

    // Stage 3: (x * term) / 2
    reg [W-1:0] x_final_reg;
    wire [(2*W)-1:0] mult_full = x_reg2 * term_reg2;

    always @(posedge clk) begin
        if (rst) x_final_reg <= 0;
        else begin
            x_final_reg <= mult_full >>> (N + 1);
        end
    end

    assign x_out = x_final_reg;
endmodule

rtl/top_pipelined.v
`timescale 1ns/1ps

module top_pipelined #(
    parameter N = 8, 
    parameter W = 16,
    parameter N_ITERS = 3
)(
    input clk,
    input rst,
    input [W-1:0] x0,
    input [W-1:0] a_in,
    output [W-1:0] result
);

    wire [W-1:0] x_bus [0:N_ITERS];
    wire [W-1:0] a_pipe [0:N_ITERS];

    assign x_bus[0] = x0;
    assign a_pipe[0] = a_in;

    genvar i;
    generate
        for (i = 0; i < N_ITERS; i = i + 1) begin : NR_ITER
            NR_stage_pipeline #(N, W) stage_inst (
                .clk(clk), .rst(rst),
                .x_in(x_bus[i]), .a_in(a_pipe[i]),
                .x_out(x_bus[i+1])
            );
            reg [W-1:0] a_d1, a_d2, a_d3;

            always @(posedge clk) begin
                if (rst) begin
                    a_d1 <= 0;
                    a_d2 <= 0;
                    a_d3 <= 0;
                end else begin
                    a_d1 <= a_pipe[i];
                    a_d2 <= a_d1;
                    a_d3 <= a_d2;
                end
            end

            assign a_pipe[i+1] = a_d3;
            // assign a_pipe[i+1] = d3;
        end
    endgenerate
    assign result = x_bus[N_ITERS];
endmodule

sim/tb_pipeline.v
`timescale 1ns/1ps

module tb_pipeline;

    parameter N = 8;
    parameter W = 16;
    parameter N_ITERS = 3;
    localparam LATENCY = N_ITERS * 3;

    reg clk, rst;
    reg [W-1:0] a_in, x0_in;
    wire [W-1:0] result;

    reg [W-1:0] a_history [0:LATENCY + N_ITERS];
    reg [W-1:0] x0_history [0:LATENCY + N_ITERS];

    initial clk = 0;
    always #5 clk = ~clk;

    top_pipelined #(N, W, N_ITERS) dut (
        .clk(clk), .rst(rst), .x0(x0_in), .a_in(a_in), .result(result)
    );

    integer j;
    always @(posedge clk) begin
        a_history[0] <= a_in;
        x0_history[0] <= x0_in;
        for (j = 1; j <= LATENCY + N_ITERS; j = j + 1) begin
            a_history[j] <= a_history[j-1];
            x0_history[j] <= x0_history[j-1];
        end
    end

    integer i;
    integer total_inputs = 36; // Total count of cases in your list

    initial begin
        // --- Setup ---
        rst = 1; a_in = 0; x0_in = 0;
        repeat(10) @(posedge clk);
        rst = 0;
        @(posedge clk);

        // --- Feeding your specific stream ---
        // 1. Boundary around 1.0
        @(posedge clk); a_in <= 16'd255;  x0_in <= 16'd260; 
        @(posedge clk); a_in <= 16'd256;  x0_in <= 16'd256; 
        @(posedge clk); a_in <= 16'd257;  x0_in <= 16'd250; 

        // 2. Transition edges
        @(posedge clk); a_in <= 16'd511;  x0_in <= 16'd130; 
        @(posedge clk); a_in <= 16'd513;  x0_in <= 16'd125; 
        @(posedge clk); a_in <= 16'd1023; x0_in <= 16'd100; 
        @(posedge clk); a_in <= 16'd1025; x0_in <= 16'd95;  

        // 3. Mid-range random
        @(posedge clk); a_in <= 16'd300;   x0_in <= 16'd200;
        @(posedge clk); a_in <= 16'd700;   x0_in <= 16'd140;
        @(posedge clk); a_in <= 16'd1500;  x0_in <= 16'd80;
        @(posedge clk); a_in <= 16'd3000;  x0_in <= 16'd60;
        @(posedge clk); a_in <= 16'd10000; x0_in <= 16'd30;

        // 4. Very small numbers
        @(posedge clk); a_in <= 16'd1;    x0_in <= 16'd4096;
        @(posedge clk); a_in <= 16'd3;    x0_in <= 16'd2048;
        @(posedge clk); a_in <= 16'd5;    x0_in <= 16'd2500;
        @(posedge clk); a_in <= 16'd7;    x0_in <= 16'd2000;
        @(posedge clk); a_in <= 16'd9;    x0_in <= 16'd1800;

        // 5. Large values
        @(posedge clk); a_in <= 16'd32767; x0_in <= 16'd20;
        @(posedge clk); a_in <= 16'd40000; x0_in <= 16'd18;
        @(posedge clk); a_in <= 16'd50000; x0_in <= 16'd17;
        @(posedge clk); a_in <= 16'd65535; x0_in <= 16'd16;

        // 6. Single-bit sweep
        @(posedge clk); a_in <= 16'd1;     x0_in <= 16'd4096;
        @(posedge clk); a_in <= 16'd2;     x0_in <= 16'd4096;
        @(posedge clk); a_in <= 16'd4;     x0_in <= 16'd2048;
        @(posedge clk); a_in <= 16'd8;     x0_in <= 16'd1500;
        @(posedge clk); a_in <= 16'd16;    x0_in <= 16'd1000;
        @(posedge clk); a_in <= 16'd32;    x0_in <= 16'd800;
        @(posedge clk); a_in <= 16'd64;    x0_in <= 16'd600;
        @(posedge clk); a_in <= 16'd128;   x0_in <= 16'd400;
        @(posedge clk); a_in <= 16'd256;   x0_in <= 16'd256;
        @(posedge clk); a_in <= 16'd512;   x0_in <= 16'd180;
        @(posedge clk); a_in <= 16'd1024;  x0_in <= 16'd128;
        @(posedge clk); a_in <= 16'd2048;  x0_in <= 16'd90;
        @(posedge clk); a_in <= 16'd4096;  x0_in <= 16'd64;
        @(posedge clk); a_in <= 16'd8192;  x0_in <= 16'd45;
        @(posedge clk); a_in <= 16'd16384; x0_in <= 16'd32;
        @(posedge clk); a_in <= 16'd32768; x0_in <= 16'd22;

        // --- End of Data ---
        @(posedge clk); a_in <= 0; x0_in <= 0;

        // --- Wait for last result to exit pipeline ---
        repeat (LATENCY + 5) @(posedge clk);
        $display("Simulation completed all cases.");
        $finish;
    end

    initial begin
        forever begin
            @(posedge clk);
            if (result !== 0 && a_history[8] !== 0) begin
                $display("Time: %t | Input A: %d | Start x0: %d | Result: %d", $time, a_history[8], x0_history[8], result);
            end
        end
    end

    initial begin
        $dumpfile("nr_pipeline.vcd");
        $dumpvars(0, tb_pipeline);
    end
endmodule

out/vcd/nr_pipeline.vcd
$date
	Mon Apr  6 01:12:53 2026
$end
$version
	Icarus Verilog
$end
$timescale
	1ps
$end
$scope module tb_pipeline $end
$var wire 16 ! result [15:0] $end
$var reg 16 " a_in [15:0] $end
$var reg 1 # clk $end
$var reg 1 $ rst $end
$var reg 16 % x0_in [15:0] $end
$var integer 32 & j [31:0] $end
$var integer 32 ' total_inputs [31:0] $end
$scope module dut $end
$var wire 16 ( a_in [15:0] $end
$var wire 1 # clk $end
$var wire 16 ) result [15:0] $end
$var wire 1 $ rst $end
$var wire 16 * x0 [15:0] $end
$scope begin NR_ITER[0] $end
$var reg 16 + a_d1 [15:0] $end
$var reg 16 , a_d2 [15:0] $end
$var reg 16 - a_d3 [15:0] $end
$scope module stage_inst $end
$var wire 16 . a_in [15:0] $end
$var wire 1 # clk $end
$var wire 1 $ rst $end
$var wire 16 / x_in [15:0] $end
$var wire 16 0 x_out [15:0] $end
$var wire 32 1 x_sq_full [31:0] $end
$var wire 32 2 mult_full [31:0] $end
$var wire 32 3 ax2_full [31:0] $end
$var reg 16 4 a_reg1 [15:0] $end
$var reg 16 5 term_reg2 [15:0] $end
$var reg 16 6 x_final_reg [15:0] $end
$var reg 16 7 x_reg1 [15:0] $end
$var reg 16 8 x_reg2 [15:0] $end
$var reg 16 9 x_sq_reg1 [15:0] $end
$upscope $end
$upscope $end
$scope begin NR_ITER[1] $end
$var reg 16 : a_d1 [15:0] $end
$var reg 16 ; a_d2 [15:0] $end
$var reg 16 < a_d3 [15:0] $end
$scope module stage_inst $end
$var wire 16 = a_in [15:0] $end
$var wire 1 # clk $end
$var wire 1 $ rst $end
$var wire 16 > x_in [15:0] $end
$var wire 16 ? x_out [15:0] $end
$var wire 32 @ x_sq_full [31:0] $end
$var wire 32 A mult_full [31:0] $end
$var wire 32 B ax2_full [31:0] $end
$var reg 16 C a_reg1 [15:0] $end
$var reg 16 D term_reg2 [15:0] $end
$var reg 16 E x_final_reg [15:0] $end
$var reg 16 F x_reg1 [15:0] $end
$var reg 16 G x_reg2 [15:0] $end
$var reg 16 H x_sq_reg1 [15:0] $end
$upscope $end
$upscope $end
$scope begin NR_ITER[2] $end
$var reg 16 I a_d1 [15:0] $end
$var reg 16 J a_d2 [15:0] $end
$var reg 16 K a_d3 [15:0] $end
$scope module stage_inst $end
$var wire 16 L a_in [15:0] $end
$var wire 1 # clk $end
$var wire 1 $ rst $end
$var wire 16 M x_in [15:0] $end
$var wire 16 N x_out [15:0] $end
$var wire 32 O x_sq_full [31:0] $end
$var wire 32 P mult_full [31:0] $end
$var wire 32 Q ax2_full [31:0] $end
$var reg 16 R a_reg1 [15:0] $end
$var reg 16 S term_reg2 [15:0] $end
$var reg 16 T x_final_reg [15:0] $end
$var reg 16 U x_reg1 [15:0] $end
$var reg 16 V x_reg2 [15:0] $end
$var reg 16 W x_sq_reg1 [15:0] $end
$upscope $end
$upscope $end
$upscope $end
$upscope $end
$enddefinitions $end
#0
$dumpvars
bx W
bx V
bx U
bx T
bx S
bx R
bx Q
bx P
bx O
bx N
bx M
bx L
bx K
bx J
bx I
bx H
bx G
bx F
bx E
bx D
bx C
bx B
bx A
bx @
bx ?
bx >
bx =
bx <
bx ;
bx :
bx 9
bx 8
bx 7
bx 6
bx 5
bx 4
bx 3
bx 2
b0 1
bx 0
b0 /
b0 .
bx -
bx ,
bx +
b0 *
bx )
b0 (
b100100 '
bx &
b0 %
1$
0#
b0 "
bx !
$end
#5000
b0 3
b0 9
b0 4
b0 7
b0 2
b0 5
b0 8
b0 @
b0 0
b0 6
b0 >
b0 =
b0 -
b0 ,
b0 +
b0 B
b0 H
b0 C
b0 F
b0 A
b0 D
b0 G
b0 O
b0 ?
b0 E
b0 M
b0 L
b0 <
b0 ;
b0 :
b0 Q
b0 W
b0 R
b0 U
b0 P
b0 S
b0 V
b0 !
b0 )
b0 N
b0 T
b0 K
b0 J
b0 I
b1101 &
1#
#10000
0#
#15000
b1101 &
1#
#20000
0#
#25000
b1101 &
1#
#30000
0#
#35000
b1101 &
1#
#40000
0#
#45000
b1101 &
1#
#50000
0#
#55000
b1101 &
1#
#60000
0#
#65000
b1101 &
1#
#70000
0#
#75000
b1101 &
1#
#80000
0#
#85000
b1101 &
1#
#90000
0#
#95000
0$
b1101 &
1#
#100000
0#
#105000
b1100000000 5
b1100000000 D
b1100000000 S
b1101 &
1#
#110000
0#
#115000
b10000100000010000 1
b100000100 /
b100000100 %
b100000100 *
b11111111 .
b11111111 "
b11111111 (
b1101 &
1#
#120000
0#
#125000
b10000011011111000 3
b100001000 9
b11111111 4
b100000100 7
b11111111 +
b10000000000000000 1
b100000000 /
b100000000 %
b100000000 *
b100000000 .
b100000000 "
b100000000 (
b1101 &
1#
#130000
0#
#135000
b1111010000100100 1
b11111010 /
b11111010 %
b11111010 *
b100000001 .
b100000001 "
b100000001 (
b11111111 ,
b100000000 +
b111111010 5
b100000000111101000 2
b100000100 8
b100000000 9
b10000000000000000 3
b100000000 4
b100000000 7
b1101 &
1#
#140000
0#
#145000
b11110100 9
b1111010011110100 3
b100000001 4
b11111010 7
b1000000000 5
b100000000000000000 2
b100000000 8
b10000000000000000 @
b100000000 0
b100000000 6
b100000000 >
b11111111 =
b11111111 -
b100000000 ,
b100000001 +
b100001000000100 1
b10000010 /
b10000010 %
b10000010 *
b111111111 .
b111111111 "
b111111111 (
b1101 &
1#
#150000
0#
#155000
b11110100001001 1
b1111101 /
b1111101 %
b1111101 *
b1000000001 .
b1000000001 "
b1000000001 (
b11111111 :
b1111111100000000 B
b100000000 H
b11111111 C
b100000000 F
b100000000 =
b100000000 -
b100000001 ,
b111111111 +
b1000001100 5
b11111111110111000 2
b11111010 8
b1000010 9
b1000001110111110 3
b111111111 4
b10000010 7
b1101 &
1#
#160000
0#
#165000
b111101 9
b111101000111101 3
b1000000001 4
b1111101 7
b1001111101 5
b10100001101111010 2
b10000010 8
b1111111000000001 @
b11111111 0
b11111111 6
b11111111 >
b100000001 =
b100000001 -
b111111111 ,
b1000000001 +
b10000000000000000 B
b100000000 C
b1000000001 D
b100000000100000000 A
b100000000 G
b11111111 ;
b100000000 :
b10011100010000 1
b1100100 /
b1100100 %
b1100100 *
b1111111111 .
b1111111111 "
b1111111111 (
b1101 &
1#
#170000
0#
#175000
b10001101000001 1
b1011111 /
b1011111 %
b1011111 *
b10000000001 .
b10000000001 "
b10000000001 (
b11111111 L
b11111111 <
b100000000 ;
b100000001 :
b10000000000000000 O
b100000000 ?
b100000000 E
b100000000 M
b100000000000000000 A
b1000000000 D
b11111110 H
b1111111011111110 B
b100000001 C
b11111111 F
b111111111 =
b111111111 -
b1000000001 ,
b1111111111 +
b110010101000001 @
b10100001 0
b10100001 6
b10100001 >
b1010000110 5
b10011101101101110 2
b1111101 8
b100111 9
b1001101111011001 3
b1111111111 4
b1100100 7
b1101 &
1#
#180000
0#
#185000
b100011 9
b1000110000100011 3
b10000000001 4
b1011111 7
b1001100101 5
b1110111101110100 2
b1100100 8
b110000001001001 @
b10011101 0
b10011101 6
b10011101 >
b1000000001 =
b1000000001 -
b1111111111 ,
b10000000001 +
b1100101 H
b1100100110011011 B
b111111111 C
b10100001 F
b1000000010 D
b11111111111111110 A
b11111111 G
b100000000 L
b100000000 <
b100000001 ;
b111111111 :
b1111111100000000 Q
b100000000 W
b11111111 R
b100000000 U
b11111111 I
b1001110001000000 1
b11001000 /
b11001000 %
b11001000 *
b100101100 .
b100101100 "
b100101100 (
b1101 &
1#
#190000
0#
#195000
b100110010010000 1
b10001100 /
b10001100 %
b10001100 *
b1010111100 .
b1010111100 "
b1010111100 (
b11111111 J
b100000000 I
b1000000001 S
b100000000100000000 P
b100000000 V
b10000000000000000 Q
b100000000 R
b100000001 L
b100000001 <
b111111111 ;
b1000000001 :
b1111111000000001 O
b11111111 ?
b11111111 E
b11111111 M
b1000110111 D
b10110010010010111 A
b10100001 G
b1100000 H
b1100000001100000 B
b1000000001 C
b10011101 F
b1111111111 =
b1111111111 -
b10000000001 ,
b100101100 +
b11011101010001 @
b1110111 0
b1110111 6
b1110111 >
b1001110100 5
b1110100100001100 2
b1011111 8
b10011100 9
b1011011011010000 3
b100101100 4
b11001000 7
b1101 &
1#
#200000
0#
#205000
b1001100 9
b1100111111010000 3
b1010111100 4
b10001100 7
b1001001010 5
b11100100111010000 2
b11001000 8
b11010010010000 @
b1110100 0
b1110100 6
b1110100 >
b10000000001 =
b10000000001 -
b100101100 ,
b1010111100 +
b110111 H
b1101101111001001 B
b1111111111 C
b1110111 F
b1001000000 D
b10110000101000000 A
b10011101 G
b111101111000100 O
b10110010 ?
b10110010 E
b10110010 M
b111111111 L
b111111111 <
b1000000001 ;
b1111111111 :
b11111110 W
b1111111011111110 Q
b100000001 R
b11111111 U
b100000000000000000 P
b1000000000 S
b100000000 !
b100000000 )
b100000000 N
b100000000 T
b11111111 K
b100000000 J
b100000001 I
b1100100000000 1
b1010000 /
b1010000 %
b1010000 *
b10111011100 .
b10111011100 "
b10111011100 (
b1101 &
1#
#210000
0#
#215000
b111000010000 1
b111100 /
b111100 %
b111100 *
b101110111000 .
b101110111000 "
b101110111000 (
b100000000 K
b100000001 J
b111111111 I
b1000000010 S
b11111111111111110 P
b11111111 V
b1111011 W
b1111010110000101 Q
b111111111 R
b10110010 U
b1000000001 L
b1000000001 <
b1111111111 ;
b10000000001 :
b111100100000000 O
b10110000 ?
b10110000 E
b10110000 M
b1000100101 D
b1111111100110011 A
b1110111 G
b110100 H
b1101000000110100 B
b10000000001 C
b1110100 F
b100101100 =
b100101100 -
b1010111100 ,
b10111011100 +
b1100101100010000 @
b11100100 0
b11100100 6
b11100100 >
b1000110001 5
b10011001011001100 2
b10001100 8
b11001 9
b1001001001111100 3
b10111011100 4
b1010000 7
b1101 &
1#
#220000
0#
#225000
b1110 9
b1010010000010000 3
b101110111000 4
b111100 7
b1001101110 5
b1100001001100000 2
b1010000 8
b101101101110001 @
b10011001 0
b10011001 6
b10011001 >
b1010111100 =
b1010111100 -
b10111011100 ,
b101110111000 +
b11001011 H
b1110110111100100 B
b100101100 C
b11100100 F
b1000110000 D
b1111110111000000 A
b1110100 G
b11111100000001 O
b1111111 ?
b1111111 E
b1111111 M
b1111111111 L
b1111111111 <
b10000000001 ;
b100101100 :
b1111001 W
b1111001001111001 Q
b1000000001 R
b10110000 U
b1000001011 S
b10110101110100110 P
b10110010 V
b11111111 !
b11111111 )
b11111111 N
b11111111 T
b100000001 K
b111111111 J
b1000000001 I
b1110000100 1
b11110 /
b11110 %
b11110 *
b10011100010000 .
b10011100010000 "
b10011100010000 (
b1101 &
1#
#230000
0#
#235000
b1000000000000000000000000 1
b1000000000000 /
b1000000000000 %
b1000000000000 *
b1 .
b1 "
b1 (
b111111111 K
b1000000001 J
b1111111111 I
b10110101 !
b10110101 )
b10110101 N
b10110101 T
b1000001110 S
b10110100110100000 P
b10110000 V
b111111 W
b1111101111000001 Q
b1111111111 R
b1111111 U
b10000000001 L
b10000000001 <
b100101100 ;
b1010111100 :
b11111000000100 O
b1111110 ?
b1111110 E
b1111110 M
b1000010011 D
b11101100011101100 A
b11100100 G
b1011011 H
b1111100011010100 B
b1010111100 C
b10011001 F
b10111011100 =
b10111011100 -
b101110111000 ,
b10011100010000 +
b10010011000001 @
b1100001 0
b1100001 6
b1100001 >
b1001011100 5
b1000110110010000 2
b111100 8
b11 9
b111010100110000 3
b10011100010000 4
b11110 7
b1101 &
1#
#240000
0#
#245000
b0 9
b0 3
b1 4
b1000000000000 7
b1010001011 5
b100110001001010 2
b11110 8
b1001100100100 @
b1000110 0
b1000110 6
b1000110 >
b101110111000 =
b101110111000 -
b10011100010000 ,
b1 +
b100100 H
b1101001011110000 B
b10111011100 C
b1100001 F
b1000001000 D
b10011011011001000 A
b10011001 G
b1101100110010000 O
b11101100 ?
b11101100 E
b11101100 M
b100101100 L
b100101100 <
b1010111100 ;
b10111011100 :
b111110 W
b1111100000111110 Q
b10000000001 R
b1111110 U
b1000000101 S
b10000000001111011 P
b1111111 V
b10110100 !
b10110100 )
b10110100 N
b10110100 T
b1000000001 K
b1111111111 J
b10000000001 I
b10000000000000000000000 1
b100000000000 /
b100000000000 %
b100000000000 *
b11 .
b11 "
b11 (
b1101 &
1#
#250000
0#
#255000
b10111110101111000010000 1
b100111000100 /
b100111000100 %
b100111000100 *
b101 .
b101 "
b101 (
b1111111111 K
b10000000001 J
b100101100 I
b10000000 !
b10000000 )
b10000000 N
b10000000 T
b1000001000 S
b1111111111110000 P
b1111110 V
b11011001 W
b1111111001001100 Q
b100101100 R
b11101100 U
b1010111100 L
b1010111100 <
b10111011100 ;
b101110111000 :
b101110111011001 O
b10011011 ?
b10011011 E
b10011011 M
b1000101110 D
b1101001101101110 A
b1100001 G
b10011 H
b1101111010101000 B
b101110111000 C
b1000110 F
b10011100010000 =
b10011100010000 -
b1 ,
b11 +
b10110100100 @
b100110 0
b100110 6
b100110 >
b1100000000 5
b1100000000000000000000 2
b1000000000000 8
b1100000000000000 3
b100000000000000 9
b11 4
b100000000000 7
b1101 &
1#
#260000
0#
#265000
b101111101011110 9
b11101110011010110 3
b101 4
b100111000100 7
b1001000000 5
b100100000000000000000 2
b100000000000 8
b10010000000000000000000000 @
b1100000000000 0
b1100000000000 6
b1100000000000 >
b1 =
b1 -
b11 ,
b101 +
b101 H
b1100001101010000 B
b10011100010000 C
b100110 F
b1000100010 D
b1001010101001100 A
b1000110 G
b10101100010001 O
b1101001 ?
b1101001 E
b1101001 M
b10111011100 L
b10111011100 <
b101110111000 ;
b10011100010000 :
b1011101 W
b1111111001001100 Q
b1010111100 R
b10011011 U
b1000000010 S
b11101100111011000 P
b11101100 V
b1111111 !
b1111111 )
b1111111 N
b1111111 T
b10000000001 K
b100101100 J
b1010111100 I
b1111010000100100000000 1
b11111010000 /
b11111010000 %
b11111010000 *
b111 .
b111 "
b111 (
b1101 &
1#
#270000
0#
#275000
b1100010111000001000000 1
b11100001000 /
b11100001000 %
b11100001000 *
b1001 .
b1001 "
b1001 (
b100101100 K
b1010111100 J
b10111011100 I
b11101100 !
b11101100 )
b11101100 N
b11101100 T
b10011011100110110 P
b10011011 V
b101011 W
b1111101111110100 Q
b10111011100 R
b1101001 U
b101110111000 L
b101110111000 <
b10011100010000 ;
b1 :
b1010101100100 O
b1001010 ?
b1001010 E
b1001010 M
b1000111101 D
b101010100001110 A
b100110 G
b100000000000000 H
b100000000000000 B
b1 C
b1100000000000 F
b11 =
b11 -
b101 ,
b111 +
b10100010000000000000000 @
b100100000000 0
b100100000000 6
b100100000000 >
b100100100 5
b10110010001110010000 2
b100111000100 8
b11110100001001 9
b11010101100111111 3
b111 4
b11111010000 7
b1101 &
1#
#280000
0#
#285000
b11000101110000 9
b11011110011110000 3
b1001 4
b11100001000 7
b101010101 5
b10100110100000010000 2
b11111010000 8
b111101111110000100001 @
b10110010001 0
b10110010001 6
b10110010001 >
b101 =
b101 -
b111 ,
b1001 +
b101000100000000 H
b1111001100000000 B
b11 C
b100100000000 F
b1011000000 D
b10000100000000000000000 A
b1100000000000 G
b11011100100 O
b101010 ?
b101010 E
b101010 M
b10011100010000 L
b10011100010000 <
b1 ;
b11 :
b10101 W
b1111011000011000 Q
b101110111000 R
b1001010 U
b1000000101 S
b1101010000001101 P
b1101001 V
b10011011 !
b10011011 )
b10011011 N
b10011011 T
b1010111100 K
b10111011100 J
b101110111000 I
b110010000 1
b10100 /
b10100 %
b10100 *
b111111111111111 .
b111111111111111 "
b111111111111111 (
b1101 &
1#
#290000
0#
#295000
b101000100 1
b10010 /
b10010 %
b10010 *
b1001110001000000 .
b1001110001000000 "
b1001110001000000 (
b10111011100 K
b101110111000 J
b10011100010000 I
b1101010 !
b1101010 )
b1101010 N
b1101010 T
b1000001010 S
b1001011011100100 P
b1001010 V
b110 W
b1110101001100000 Q
b10011100010000 R
b101010 U
b1 L
b1 <
b11 ;
b101 :
b100010000010000000000000000 O
b10000100000000 ?
b10000100000000 E
b10000100000000 M
b1000001101 D
b100100111010100000000 A
b100100000000 G
b1111011111100 H
b1001101011101100 B
b101 C
b10110010001 F
b111 =
b111 -
b1001 ,
b111111111111111 +
b110110001001010010000 @
b10100110100 0
b10100110100 6
b10100110100 >
b101000100 5
b10001110011000100000 2
b11100001000 8
b1 9
b111111111111111 3
b111111111111111 4
b10100 7
b1101 &
1#
#300000
0#
#305000
b1001110001000000 3
b1001110001000000 4
b10010 7
b1010000001 5
b11001000010100 2
b10100 8
b100111100101110101001 @
b10001110011 0
b10001110011 6
b10001110011 >
b1001 =
b1001 -
b111111111111111 ,
b1001110001000000 +
b1101100010010 H
b1011110101111110 B
b111 C
b10100110100 F
b1001100110 D
b11010101100111000110 A
b10110010001 G
b10101010010000100100100 O
b100100111010 ?
b100100111010 E
b100100111010 M
b11 L
b11 <
b101 ;
b111 :
b100000100000000 W
b100000100000000 Q
b1 R
b10000100000000 U
b1000010110 S
b101011110011100 P
b101010 V
b1001011 !
b1001011 )
b1001011 N
b1001011 T
b101110111000 K
b10011100010000 J
b1 I
b100100001 1
b10001 /
b10001 %
b10001 *
b1100001101010000 .
b1100001101010000 "
b1100001101010000 (
b1101 &
1#
#310000
0#
#315000
b100000000 1
b10000 /
b10000 %
b10000 *
b1111111111111111 .
b1111111111111111 "
b1111111111111111 (
b10011100010000 K
b1 J
b11 I
b101011 !
b101011 )
b101011 N
b101011 T
b1010111111 S
b10110101001111100000000 P
b10000100000000 V
b101010100100001 W
b1111111101100011 Q
b11 R
b100100111010 U
b101 L
b101 <
b111 ;
b1001 :
b1011001000001110010000 O
b11010101100 ?
b11010101100 E
b11010101100 M
b1001000011 D
b10111100010010011100 A
b10100110100 G
b1001111001011 H
b1011001000100011 B
b1001 C
b10001110011 F
b111111111111111 =
b111111111111111 -
b1001110001000000 ,
b1100001101010000 +
b1001110001 @
b11001 0
b11001 6
b11001 >
b1001100100 5
b10101100001000 2
b10010 8
b1100001101010000 3
b1100001101010000 4
b10001 7
b1101 &
1#
#320000
0#
#325000
b1111111111111111 3
b1111111111111111 4
b10000 7
b1000111101 5
b10011000001101 2
b10001 8
b110111001 @
b10101 0
b10101 6
b10101 >
b1001110001000000 =
b1001110001000000 -
b1100001101010000 ,
b1111111111111111 +
b10 H
b1111111111111110 B
b111111111111111 C
b11001 F
b1001001110 D
b10100100000100001010 A
b10001110011 G
b1000101001101110000100 O
b10111100010 ?
b10111100010 E
b10111100010 M
b111 L
b111 <
b1001 ;
b111111111111111 :
b10110010000011 W
b1101111010001111 Q
b101 R
b11010101100 U
b1000000001 S
b100100111110100111010 P
b100100111010 V
b10110101001111 !
b10110101001111 )
b10110101001111 N
b10110101001111 T
b1 K
b11 J
b101 I
b1000000000000000000000000 1
b1000000000000 /
b1000000000000 %
b1000000000000 *
b1 .
b1 "
b1 (
b1101 &
1#
#330000
0#
#335000
b10 .
b10 "
b10 (
b11 K
b101 J
b111 I
b100100111110 !
b100100111110 )
b100100111110 N
b100100111110 T
b1000100010 S
b11100011101011011000 P
b11010101100 V
b10001010011011 W
b1111001000111101 Q
b111 R
b10111100010 U
b1001 L
b1001 <
b111111111111111 ;
b1001110001000000 :
b110100100010000000000 O
b10100100000 ?
b10100100000 E
b10100100000 M
b1000000001 D
b11001000011001 A
b11001 G
b1 H
b1001110001000000 B
b1001110001000000 C
b10101 F
b1100001101010000 =
b1100001101010000 -
b1111111111111111 ,
b1 +
b101101001 @
b10011 0
b10011 6
b10011 >
b1000000001 5
b10000000010000 2
b10000 8
b0 9
b0 3
b1 4
b1000000000000 7
b1101 &
1#
#340000
0#
#345000
b10 4
b1100000000 5
b1100000000000000000000 2
b1000000000000 8
b100000000 @
b10000 0
b10000 6
b10000 >
b1111111111111111 =
b1111111111111111 -
b1 ,
b10 +
b1100001101010000 B
b1100001101010000 C
b10011 F
b1001100100 D
b11001000110100 A
b10101 G
b1001110001 O
b11001 ?
b11001 E
b11001 M
b111111111111111 L
b111111111111111 <
b1001110001000000 ;
b1100001101010000 :
b1101001000100 W
b1110110001100100 Q
b1001 R
b10100100000 U
b1000001110 S
b11000001011001011100 P
b10111100010 V
b11100011101 !
b11100011101 )
b11100011101 N
b11100011101 T
b101 K
b111 J
b1001 I
b10000000000000000000000 1
b100000000000 /
b100000000000 %
b100000000000 *
b100 .
b100 "
b100 (
b1101 &
1#
#350000
0#
#355000
b1000100101010100010000 1
b10111011100 /
b10111011100 %
b10111011100 *
b1000 .
b1000 "
b1000 (
b111 K
b1001 J
b111111111111111 I
b11000001011 !
b11000001011 )
b11000001011 N
b11000001011 T
b1000010100 S
b10101010011010000000 P
b10100100000 V
b10 W
b1111111111111110 Q
b111111111111111 R
b11001 U
b1001110001000000 L
b1001110001000000 <
b1100001101010000 ;
b1111111111111111 :
b1000111101 D
b10101010000111 A
b10011 G
b1111111111111111 B
b1111111111111111 C
b10000 F
b1 =
b1 -
b10 ,
b100 +
b10010000000000000000000000 @
b1100000000000 0
b1100000000000 6
b1100000000000 >
b10000000000000000 3
b100000000000000 9
b100 4
b100000000000 7
b1101 &
1#
#360000
0#
#365000
b10001001010101 9
b10001001010101000 3
b1000 4
b10111011100 7
b1000000000 5
b100000000000000000000 2
b100000000000 8
b10 =
b10 -
b100 ,
b1000 +
b100000000000000 H
b100000000000000 B
b1 C
b1100000000000 F
b1000000001 D
b10000000010000 A
b10000 G
b110111001 O
b10101 ?
b10101 E
b10101 M
b1100001101010000 L
b1100001101010000 <
b1111111111111111 ;
b1 :
b10011100010000000 Q
b1001110001000000 R
b1000000001 S
b11001000011001 P
b11001 V
b10101010011 !
b10101010011 )
b10101010011 N
b10101010011 T
b1001 K
b111111111111111 J
b1001110001000000 I
b11110100001001000000 1
b1111101000 /
b1111101000 %
b1111101000 *
b10000 .
b10000 "
b10000 (
b1101 &
1#
#370000
0#
#375000
b10011100010000000000 1
b1100100000 /
b1100100000 %
b1100100000 *
b100000 .
b100000 "
b100000 (
b111111111111111 K
b1001110001000000 J
b1100001101010000 I
b11001 !
b11001 )
b11001 N
b11001 T
b10110010001000 P
b111001000 S
b1 W
b1100001101010000 Q
b1100001101010000 R
b10101 U
b1111111111111111 L
b1111111111111111 <
b1 ;
b10 :
b100000000 O
b10000 ?
b10000 E
b10000 M
b1011000000 D
b10000100000000000000000 A
b1100000000000 G
b1000000000000000 B
b10 C
b100 =
b100 -
b1000 ,
b10000 +
b10000000000000000000000 @
b100000000000 0
b100000000000 6
b100000000000 >
b111101110 5
b10110100111010001000 2
b10111011100 8
b111101000010 9
b1111010000100000 3
b10000 4
b1111101000 7
b1101 &
1#
#380000
0#
