rtl/NR_stage_pipeline.v
`timescale 1ns/1ps

module NR_stage_pipeline #(parameter N = 8, parameter W = 16)(
    input  clk, rst,
    input [W-1:0] x_in,
    input [W-1:0] a_in,
    output [W-1:0] x_out
);
    // Stage 1: x^2 (Q8.8 * Q8.8 = Q16.16)
    reg [W-1:0] x_reg1, a_reg1, x_sq_reg1;
    wire [(2*W)-1:0] x_sq_full = x_in * x_in;

    always @(posedge clk) begin
        if (rst) begin
            x_reg1 <= 0; a_reg1 <= 0; x_sq_reg1 <= 0;
        end else begin
            x_reg1 <= x_in;
            a_reg1 <= a_in;
            x_sq_reg1 <= x_sq_full >>> N;
        end
    end

    // Stage 2: (3 - a*x^2)
    reg [W-1:0] x_reg2, term_reg2;
    wire [(2*W)-1:0] ax2_full = a_reg1 * x_sq_reg1;

    always @(posedge clk) begin
        if (rst) begin
            x_reg2 <= 0; term_reg2 <= 0;
        end else begin
            x_reg2 <= x_reg1;
            term_reg2 <= (3 << N) - (ax2_full >>> N);
        end
    end

    // Stage 3: (x * term) / 2
    reg [W-1:0] x_final_reg;
    wire [(2*W)-1:0] mult_full = x_reg2 * term_reg2;

    always @(posedge clk) begin
        if (rst) x_final_reg <= 0;
        else begin
            x_final_reg <= mult_full >>> (N + 1);
        end
    end

    assign x_out = x_final_reg;
endmodule

rtl/top_pipelined.v
`timescale 1ns/1ps

module top_pipelined #(
    parameter N = 8, 
    parameter W = 16,
    parameter N_ITERS = 3
)(
    input clk,
    input rst,
    input [W-1:0] x0,
    input [W-1:0] a_in,
    output [W-1:0] result
);

    wire [W-1:0] x_bus [0:N_ITERS];
    wire [W-1:0] a_bus [0:N_ITERS];

    assign x_bus[0] = x0;
    assign a_bus[0] = a_in;

    genvar i;
    generate
        for (i = 0; i < N_ITERS; i = i + 1) begin : NR_ITER
            NR_stage_pipeline #(N, W) stage_inst (
                .clk(clk), .rst(rst),
                .x_in(x_bus[i]), .a_in(a_bus[i]),
                .x_out(x_bus[i+1])
            );
            reg signed [W-1:0] d1, d2, d3;
            always @(posedge clk) begin
                if (rst) {d1, d2, d3} <= 0;
                else     {d3, d2, d1} <= {d2, d1, a_bus[i]};
            end
            assign a_bus[i+1] = d3;
        end
    endgenerate
    assign result = x_bus[N_ITERS];
endmodule

sim/tb_pipeline.v
`timescale 1ns/1ps

module tb_pipeline;

    parameter N = 8;
    parameter W = 16;
    parameter N_ITERS = 3;
    localparam LATENCY = N_ITERS * 3;

    reg clk, rst;
    reg [W-1:0] a_in, x0_in;
    wire [W-1:0] result;

    reg [W-1:0] a_history [0:LATENCY + N_ITERS];
    reg [W-1:0] x0_history [0:LATENCY + N_ITERS];

    initial clk = 0;
    always #5 clk = ~clk;

    top_pipelined #(N, W, N_ITERS) dut (
        .clk(clk), .rst(rst), .x0(x0_in), .a_in(a_in), .result(result)
    );

    integer j;
    always @(posedge clk) begin
        a_history[0] <= a_in;
        x0_history[0] <= x0_in;
        for (j = 1; j <= LATENCY + N_ITERS; j = j + 1) begin
            a_history[j] <= a_history[j-1];
            x0_history[j] <= x0_history[j-1];
        end
    end

    integer i;
    integer total_inputs = 36; // Total count of cases in your list

    initial begin
        // --- Setup ---
        rst = 1; a_in = 0; x0_in = 0;
        repeat(10) @(posedge clk);
        rst = 0;
        @(posedge clk);

        // --- Feeding your specific stream ---
        // 1. Boundary around 1.0
        @(posedge clk); a_in <= 16'd255;  x0_in <= 16'd260; 
        @(posedge clk); a_in <= 16'd256;  x0_in <= 16'd256; 
        @(posedge clk); a_in <= 16'd257;  x0_in <= 16'd250; 

        // 2. Transition edges
        @(posedge clk); a_in <= 16'd511;  x0_in <= 16'd130; 
        @(posedge clk); a_in <= 16'd513;  x0_in <= 16'd125; 
        @(posedge clk); a_in <= 16'd1023; x0_in <= 16'd100; 
        @(posedge clk); a_in <= 16'd1025; x0_in <= 16'd95;  

        // 3. Mid-range random
        @(posedge clk); a_in <= 16'd300;   x0_in <= 16'd200;
        @(posedge clk); a_in <= 16'd700;   x0_in <= 16'd140;
        @(posedge clk); a_in <= 16'd1500;  x0_in <= 16'd80;
        @(posedge clk); a_in <= 16'd3000;  x0_in <= 16'd60;
        @(posedge clk); a_in <= 16'd10000; x0_in <= 16'd30;

        // 4. Very small numbers
        @(posedge clk); a_in <= 16'd1;    x0_in <= 16'd4096;
        @(posedge clk); a_in <= 16'd3;    x0_in <= 16'd2048;
        @(posedge clk); a_in <= 16'd5;    x0_in <= 16'd2500;
        @(posedge clk); a_in <= 16'd7;    x0_in <= 16'd2000;
        @(posedge clk); a_in <= 16'd9;    x0_in <= 16'd1800;

        // 5. Large values
        @(posedge clk); a_in <= 16'd32767; x0_in <= 16'd20;
        @(posedge clk); a_in <= 16'd40000; x0_in <= 16'd18;
        @(posedge clk); a_in <= 16'd50000; x0_in <= 16'd17;
        @(posedge clk); a_in <= 16'd65535; x0_in <= 16'd16;

        // 6. Single-bit sweep
        @(posedge clk); a_in <= 16'd1;     x0_in <= 16'd4096;
        @(posedge clk); a_in <= 16'd2;     x0_in <= 16'd4096;
        @(posedge clk); a_in <= 16'd4;     x0_in <= 16'd2048;
        @(posedge clk); a_in <= 16'd8;     x0_in <= 16'd1500;
        @(posedge clk); a_in <= 16'd16;    x0_in <= 16'd1000;
        @(posedge clk); a_in <= 16'd32;    x0_in <= 16'd800;
        @(posedge clk); a_in <= 16'd64;    x0_in <= 16'd600;
        @(posedge clk); a_in <= 16'd128;   x0_in <= 16'd400;
        @(posedge clk); a_in <= 16'd256;   x0_in <= 16'd256;
        @(posedge clk); a_in <= 16'd512;   x0_in <= 16'd180;
        @(posedge clk); a_in <= 16'd1024;  x0_in <= 16'd128;
        @(posedge clk); a_in <= 16'd2048;  x0_in <= 16'd90;
        @(posedge clk); a_in <= 16'd4096;  x0_in <= 16'd64;
        @(posedge clk); a_in <= 16'd8192;  x0_in <= 16'd45;
        @(posedge clk); a_in <= 16'd16384; x0_in <= 16'd32;
        @(posedge clk); a_in <= 16'd32768; x0_in <= 16'd22;

        // --- End of Data ---
        @(posedge clk); a_in <= 0; x0_in <= 0;

        // --- Wait for last result to exit pipeline ---
        repeat (LATENCY + 5) @(posedge clk);
        $display("Simulation completed all cases.");
        $finish;
    end

    initial begin
        forever begin
            @(posedge clk);
            if (result !== 0 && a_history[8] !== 0) begin
                $display("Time: %t | Input A: %d | Start x0: %d | Result: %d", $time, a_history[8], x0_history[8], result);
            end
        end
    end

    initial begin
        $dumpfile("nr_pipeline.vcd");
        $dumpvars(0, tb_pipeline);
    end
endmodule

out/vcd/nr_pipeline.vcd
$date
	Sun Apr  5 19:52:41 2026
$end
$version
	Icarus Verilog
$end
$timescale
	1ps
$end
$scope module tb_pipeline $end
$var wire 16 ! result [15:0] $end
$var reg 16 " a_in [15:0] $end
$var reg 1 # clk $end
$var reg 1 $ rst $end
$var reg 16 % x0_in [15:0] $end
$var integer 32 & j [31:0] $end
$scope module dut $end
$var wire 16 ' a_in [15:0] $end
$var wire 1 # clk $end
$var wire 16 ( result [15:0] $end
$var wire 1 $ rst $end
$var wire 16 ) x0 [15:0] $end
$scope begin NR_ITER[0] $end
$var reg 16 * d1 [15:0] $end
$var reg 16 + d2 [15:0] $end
$var reg 16 , d3 [15:0] $end
$scope module stage_inst $end
$var wire 16 - a_in [15:0] $end
$var wire 1 # clk $end
$var wire 1 $ rst $end
$var wire 16 . x_in [15:0] $end
$var wire 16 / x_out [15:0] $end
$var wire 32 0 x_sq_full [31:0] $end
$var wire 32 1 mult_full [31:0] $end
$var wire 32 2 ax2_full [31:0] $end
$var reg 16 3 a_reg1 [15:0] $end
$var reg 16 4 term_reg2 [15:0] $end
$var reg 16 5 x_final_reg [15:0] $end
$var reg 16 6 x_reg1 [15:0] $end
$var reg 16 7 x_reg2 [15:0] $end
$var reg 16 8 x_sq_reg1 [15:0] $end
$upscope $end
$upscope $end
$scope begin NR_ITER[1] $end
$var reg 16 9 d1 [15:0] $end
$var reg 16 : d2 [15:0] $end
$var reg 16 ; d3 [15:0] $end
$scope module stage_inst $end
$var wire 16 < a_in [15:0] $end
$var wire 1 # clk $end
$var wire 1 $ rst $end
$var wire 16 = x_in [15:0] $end
$var wire 16 > x_out [15:0] $end
$var wire 32 ? x_sq_full [31:0] $end
$var wire 32 @ mult_full [31:0] $end
$var wire 32 A ax2_full [31:0] $end
$var reg 16 B a_reg1 [15:0] $end
$var reg 16 C term_reg2 [15:0] $end
$var reg 16 D x_final_reg [15:0] $end
$var reg 16 E x_reg1 [15:0] $end
$var reg 16 F x_reg2 [15:0] $end
$var reg 16 G x_sq_reg1 [15:0] $end
$upscope $end
$upscope $end
$scope begin NR_ITER[2] $end
$var reg 16 H d1 [15:0] $end
$var reg 16 I d2 [15:0] $end
$var reg 16 J d3 [15:0] $end
$scope module stage_inst $end
$var wire 16 K a_in [15:0] $end
$var wire 1 # clk $end
$var wire 1 $ rst $end
$var wire 16 L x_in [15:0] $end
$var wire 16 M x_out [15:0] $end
$var wire 32 N x_sq_full [31:0] $end
$var wire 32 O mult_full [31:0] $end
$var wire 32 P ax2_full [31:0] $end
$var reg 16 Q a_reg1 [15:0] $end
$var reg 16 R term_reg2 [15:0] $end
$var reg 16 S x_final_reg [15:0] $end
$var reg 16 T x_reg1 [15:0] $end
$var reg 16 U x_reg2 [15:0] $end
$var reg 16 V x_sq_reg1 [15:0] $end
$upscope $end
$upscope $end
$scope begin NR_ITER[3] $end
$var reg 16 W d1 [15:0] $end
$var reg 16 X d2 [15:0] $end
$var reg 16 Y d3 [15:0] $end
$scope module stage_inst $end
$var wire 16 Z a_in [15:0] $end
$var wire 1 # clk $end
$var wire 1 $ rst $end
$var wire 16 [ x_in [15:0] $end
$var wire 16 \ x_out [15:0] $end
$var wire 32 ] x_sq_full [31:0] $end
$var wire 32 ^ mult_full [31:0] $end
$var wire 32 _ ax2_full [31:0] $end
$var reg 16 ` a_reg1 [15:0] $end
$var reg 16 a term_reg2 [15:0] $end
$var reg 16 b x_final_reg [15:0] $end
$var reg 16 c x_reg1 [15:0] $end
$var reg 16 d x_reg2 [15:0] $end
$var reg 16 e x_sq_reg1 [15:0] $end
$upscope $end
$upscope $end
$upscope $end
$upscope $end
$enddefinitions $end
#0
$dumpvars
bx e
bx d
bx c
bx b
bx a
bx `
bx _
bx ^
bx ]
bx \
bx [
bx Z
bx Y
bx X
bx W
bx V
bx U
bx T
bx S
bx R
bx Q
bx P
bx O
bx N
bx M
bx L
bx K
bx J
bx I
bx H
bx G
bx F
bx E
bx D
bx C
bx B
bx A
bx @
bx ?
bx >
bx =
bx <
bx ;
bx :
bx 9
bx 8
bx 7
bx 6
bx 5
bx 4
bx 3
bx 2
bx 1
b0 0
bx /
b0 .
b0 -
bx ,
bx +
bx *
b0 )
bx (
b0 '
bx &
b0 %
1$
0#
b0 "
bx !
$end
#5000
b0 2
b0 8
b0 3
b0 6
b0 1
b0 4
b0 7
b0 ?
b0 /
b0 5
b0 =
b0 *
b0 +
b0 <
b0 ,
b0 A
b0 G
b0 B
b0 E
b0 @
b0 C
b0 F
b0 N
b0 >
b0 D
b0 L
b0 9
b0 :
b0 K
b0 ;
b0 P
b0 V
b0 Q
b0 T
b0 O
b0 R
b0 U
b0 ]
b0 M
b0 S
b0 [
b0 H
b0 I
b0 Z
b0 J
b0 _
b0 e
b0 `
b0 c
b0 ^
b0 a
b0 d
b0 !
b0 (
b0 \
b0 b
b0 W
b0 X
b0 Y
b10001 &
1#
#10000
0#
#15000
b10001 &
1#
#20000
0#
#25000
b10001 &
1#
#30000
0#
#35000
b10001 &
1#
#40000
0#
#45000
b1100000000 4
b1100000000 C
b1100000000 R
b1100000000 a
b10001 &
0$
1#
#50000
0#
#55000
b10000100000010000 0
b100000100 .
b100000100 %
b100000100 )
b11111111 -
b11111111 "
b11111111 '
b10001 &
1#
#60000
0#
#65000
b10000011011111000 2
b100001000 8
b11111111 3
b100000100 6
b11111111 *
b10000000000000000 0
b100000000 .
b100000000 %
b100000000 )
b100000000 -
b100000000 "
b100000000 '
b10001 &
1#
#70000
0#
#75000
b1111010000100100 0
b11111010 .
b11111010 %
b11111010 )
b100000001 -
b100000001 "
b100000001 '
b11111111 +
b100000000 *
b111111010 4
b100000000111101000 1
b100000100 7
b100000000 8
b10000000000000000 2
b100000000 3
b100000000 6
b10001 &
1#
#80000
0#
#85000
b11110100 8
b1111010011110100 2
b100000001 3
b11111010 6
b1000000000 4
b100000000000000000 1
b100000000 7
b10000000000000000 ?
b100000000 /
b100000000 5
b100000000 =
b11111111 <
b11111111 ,
b100000000 +
b100000001 *
b100001000000100 0
b10000010 .
b10000010 %
b10000010 )
b111111111 -
b111111111 "
b111111111 '
b10001 &
1#
#90000
0#
#95000
b11110100001001 0
b1111101 .
b1111101 %
b1111101 )
b1000000001 -
b1000000001 "
b1000000001 '
b11111111 9
b1111111100000000 A
b100000000 G
b11111111 B
b100000000 E
b100000000 <
b100000000 ,
b100000001 +
b111111111 *
b1000001100 4
b11111111110111000 1
b11111010 7
b1000010 8
b1000001110111110 2
b111111111 3
b10000010 6
b10001 &
1#
#100000
0#
#105000
b111101 8
b111101000111101 2
b1000000001 3
b1111101 6
b1001111101 4
b10100001101111010 1
b10000010 7
b1111111000000001 ?
b11111111 /
b11111111 5
b11111111 =
b100000001 <
b100000001 ,
b111111111 +
b1000000001 *
b10000000000000000 A
b100000000 B
b1000000001 C
b100000000100000000 @
b100000000 F
b11111111 :
b100000000 9
b10011100010000 0
b1100100 .
b1100100 %
b1100100 )
b1111111111 -
b1111111111 "
b1111111111 '
b10001 &
1#
#110000
0#
#115000
b10001101000001 0
b1011111 .
b1011111 %
b1011111 )
b10000000001 -
b10000000001 "
b10000000001 '
b11111111 K
b11111111 ;
b100000000 :
b100000001 9
b10000000000000000 N
b100000000 >
b100000000 D
b100000000 L
b100000000000000000 @
b1000000000 C
b11111110 G
b1111111011111110 A
b100000001 B
b11111111 E
b111111111 <
b111111111 ,
b1000000001 +
b1111111111 *
b110010101000001 ?
b10100001 /
b10100001 5
b10100001 =
b1010000110 4
b10011101101101110 1
b1111101 7
b100111 8
b1001101111011001 2
b1111111111 3
b1100100 6
b10001 &
1#
#120000
0#
#125000
b100011 8
b1000110000100011 2
b10000000001 3
b1011111 6
b1001100101 4
b1110111101110100 1
b1100100 7
b110000001001001 ?
b10011101 /
b10011101 5
b10011101 =
b1000000001 <
b1000000001 ,
b1111111111 +
b10000000001 *
b1100101 G
b1100100110011011 A
b111111111 B
b10100001 E
b1000000010 C
b11111111111111110 @
b11111111 F
b100000000 K
b100000000 ;
b100000001 :
b111111111 9
b1111111100000000 P
b100000000 V
b11111111 Q
b100000000 T
b11111111 H
b1001110001000000 0
b11001000 .
b11001000 %
b11001000 )
b100101100 -
b100101100 "
b100101100 '
b10001 &
1#
#130000
0#
#135000
b100110010010000 0
b10001100 .
b10001100 %
b10001100 )
b1010111100 -
b1010111100 "
b1010111100 '
b11111111 I
b100000000 H
b1000000001 R
b100000000100000000 O
b100000000 U
b10000000000000000 P
b100000000 Q
b100000001 K
b100000001 ;
b111111111 :
b1000000001 9
b1111111000000001 N
b11111111 >
b11111111 D
b11111111 L
b1000110111 C
b10110010010010111 @
b10100001 F
b1100000 G
b1100000001100000 A
b1000000001 B
b10011101 E
b1111111111 <
b1111111111 ,
b10000000001 +
b100101100 *
b11011101010001 ?
b1110111 /
b1110111 5
b1110111 =
b1001110100 4
b1110100100001100 1
b1011111 7
b10011100 8
b1011011011010000 2
b100101100 3
b11001000 6
b10001 &
1#
#140000
0#
#145000
b1001100 8
b1100111111010000 2
b1010111100 3
b10001100 6
b1001001010 4
b11100100111010000 1
b11001000 7
b11010010010000 ?
b1110100 /
b1110100 5
b1110100 =
b10000000001 <
b10000000001 ,
b100101100 +
b1010111100 *
b110111 G
b1101101111001001 A
b1111111111 B
b1110111 E
b1001000000 C
b10110000101000000 @
b10011101 F
b111101111000100 N
b10110010 >
b10110010 D
b10110010 L
b111111111 K
b111111111 ;
b1000000001 :
b1111111111 9
b11111110 V
b1111111011111110 P
b100000001 Q
b11111111 T
b100000000000000000 O
b1000000000 R
b10000000000000000 ]
b100000000 M
b100000000 S
b100000000 [
b11111111 Z
b11111111 J
b100000000 I
b100000001 H
b1100100000000 0
b1010000 .
b1010000 %
b1010000 )
b10111011100 -
b10111011100 "
b10111011100 '
b10001 &
1#
#150000
0#
#155000
b111000010000 0
b111100 .
b111100 %
b111100 )
b101110111000 -
b101110111000 "
b101110111000 '
b11111111 W
b1111111100000000 _
b100000000 e
b11111111 `
b100000000 c
b100000000 Z
b100000000 J
b100000001 I
b111111111 H
b1000000010 R
b11111111111111110 O
b11111111 U
b1111011 V
b1111010110000101 P
b111111111 Q
b10110010 T
b1000000001 K
b1000000001 ;
b1111111111 :
b10000000001 9
b111100100000000 N
b10110000 >
b10110000 D
b10110000 L
b1000100101 C
b1111111100110011 @
b1110111 F
b110100 G
b1101000000110100 A
b10000000001 B
b1110100 E
b100101100 <
b100101100 ,
b1010111100 +
b10111011100 *
b1100101100010000 ?
b11100100 /
b11100100 5
b11100100 =
b1000110001 4
b10011001011001100 1
b10001100 7
b11001 8
b1001001001111100 2
b10111011100 3
b1010000 6
b10001 &
1#
#160000
0#
#165000
b1110 8
b1010010000010000 2
b101110111000 3
b111100 6
b1001101110 4
b1100001001100000 1
b1010000 7
b101101101110001 ?
b10011001 /
b10011001 5
b10011001 =
b1010111100 <
b1010111100 ,
b10111011100 +
b101110111000 *
b11001011 G
b1110110111100100 A
b100101100 B
b11100100 E
b1000110000 C
b1111110111000000 @
b1110100 F
b11111100000001 N
b1111111 >
b1111111 D
b1111111 L
b1111111111 K
b1111111111 ;
b10000000001 :
b100101100 9
b1111001 V
b1111001001111001 P
b1000000001 Q
b10110000 T
b1000001011 R
b10110101110100110 O
b10110010 U
b1111111000000001 ]
b11111111 M
b11111111 S
b11111111 [
b100000001 Z
b100000001 J
b111111111 I
b1000000001 H
b10000000000000000 _
b100000000 `
b1000000001 a
b100000000100000000 ^
b100000000 d
b11111111 X
b100000000 W
b1110000100 0
b11110 .
b11110 %
b11110 )
b10011100010000 -
b10011100010000 "
b10011100010000 '
b10001 &
1#
#170000
0#
#175000
b1000000000000000000000000 0
b1000000000000 .
b1000000000000 %
b1000000000000 )
b1 -
b1 "
b1 '
b11111111 Y
b100000000 X
b100000001 W
b100000000 !
b100000000 (
b100000000 \
b100000000 b
b100000000000000000 ^
b1000000000 a
b11111110 e
b1111111011111110 _
b100000001 `
b11111111 c
b111111111 Z
b111111111 J
b1000000001 I
b1111111111 H
b111111111111001 ]
b10110101 M
b10110101 S
b10110101 [
b1000001110 R
b10110100110100000 O
b10110000 U
b111111 V
b1111101111000001 P
b1111111111 Q
b1111111 T
b10000000001 K
b10000000001 ;
b100101100 :
b1010111100 9
b11111000000100 N
b1111110 >
b1111110 D
b1111110 L
b1000010011 C
b11101100011101100 @
b11100100 F
b1011011 G
b1111100011010100 A
b1010111100 B
b10011001 E
b10111011100 <
b10111011100 ,
b101110111000 +
b10011100010000 *
b10010011000001 ?
b1100001 /
b1100001 5
b1100001 =
b1001011100 4
b1000110110010000 1
b111100 7
b11 8
b111010100110000 2
b10011100010000 3
b11110 6
b10001 &
1#
#180000
0#
#185000
b0 8
b0 2
b1 3
b1000000000000 6
b1010001011 4
b100110001001010 1
b11110 7
b1001100100100 ?
b1000110 /
b1000110 5
b1000110 =
b101110111000 <
b101110111000 ,
b10011100010000 +
b1 *
b100100 G
b1101001011110000 A
b10111011100 B
b1100001 E
b1000001000 C
b10011011011001000 @
b10011001 F
b1101100110010000 N
b11101100 >
b11101100 D
b11101100 L
b100101100 K
b100101100 ;
b1010111100 :
b10111011100 9
b111110 V
b1111100000111110 P
b10000000001 Q
b1111110 T
b1000000101 R
b10000000001111011 O
b1111111 U
b111111010010000 ]
b10110100 M
b10110100 S
b10110100 [
b1000000001 Z
b1000000001 J
b1111111111 I
b10000000001 H
b1111111 e
b1111110110000001 _
b111111111 `
b10110101 c
b1000000010 a
b11111111111111110 ^
b11111111 d
b100000000 Y
b100000001 X
b111111111 W
b100010010101010001000000 0
b101110111000 .
b101110111000 %
b101110111000 )
b11 -
b11 "
b11 '
b10001 &
1#
#190000
0#
#195000
b10111110101111000010000 0
b100111000100 .
b100111000100 %
b100111000100 )
b101 -
b101 "
b101 '
b100000001 Y
b111111111 X
b1000000001 W
b11111111 !
b11111111 (
b11111111 \
b11111111 b
b1000000011 a
b10110110000011111 ^
b10110101 d
b1111110 e
b1111110001111110 _
b1000000001 `
b10110100 c
b1111111111 Z
b1111111111 J
b10000000001 I
b100101100 H
b100000000000000 ]
b10000000 M
b10000000 S
b10000000 [
b1000001000 R
b1111111111110000 O
b1111110 U
b11011001 V
b1111111001001100 P
b100101100 Q
b11101100 T
b1010111100 K
b1010111100 ;
b10111011100 :
b101110111000 9
b101110111011001 N
b10011011 >
b10011011 D
b10011011 L
b1000101110 C
b1101001101101110 @
b1100001 F
b10011 G
b1101111010101000 A
b101110111000 B
b1000110 E
b10011100010000 <
b10011100010000 ,
b1 +
b11 *
b10110100100 ?
b100110 /
b100110 5
b100110 =
b1100000000 4
b1100000000000000000000 1
b1000000000000 7
b11001101111111100 2
b1000100101010100 8
b11 3
b101110111000 6
b10001 &
1#
#200000
0#
#205000
b101111101011110 8
b11101110011010110 2
b101 3
b100111000100 6
b101100101 4
b100000101011110011000 1
b101110111000 7
b10010000000000000000000000 ?
b1100000000000 /
b1100000000000 5
b1100000000000 =
b1 <
b1 ,
b11 +
b101 *
b101 G
b1100001101010000 A
b10011100010000 B
b100110 E
b1000100010 C
b1001010101001100 @
b1000110 F
b10101100010001 N
b1101001 >
b1101001 D
b1101001 L
b10111011100 K
b10111011100 ;
b101110111000 :
b10011100010000 9
b1011101 V
b1111111001001100 P
b1010111100 Q
b10011011 T
b1000000010 R
b11101100111011000 O
b11101100 U
b11111100000001 ]
b1111111 M
b1111111 S
b1111111 [
b10000000001 Z
b10000000001 J
b100101100 I
b1010111100 H
b1000000 e
b1111111111000000 _
b1111111111 `
b10000000 c
b1000000100 a
b10110101011010000 ^
b10110100 d
b10110110 !
b10110110 (
b10110110 \
b10110110 b
b111111111 Y
b1000000001 X
b1111111111 W
b1111010000100100000000 0
b11111010000 .
b11111010000 %
b11111010000 )
b111 -
b111 "
b111 '
b10001 &
1#
#210000
0#
#215000
b1100010111000001000000 0
b11100001000 .
b11100001000 %
b11100001000 )
b1001 -
b1001 "
b1001 '
b1000000001 Y
b1111111111 X
b10000000001 W
b10110101 !
b10110101 (
b10110101 \
b10110101 b
b1000000001 a
b10000000010000000 ^
b10000000 d
b111111 e
b1111110000111111 _
b10000000001 `
b1111111 c
b100101100 Z
b100101100 J
b1010111100 I
b10111011100 H
b1101100110010000 ]
b11101100 M
b11101100 S
b11101100 [
b10011011100110110 O
b10011011 U
b101011 V
b1111101111110100 P
b10111011100 Q
b1101001 T
b101110111000 K
b101110111000 ;
b10011100010000 :
b1 9
b1010101100100 N
b1001010 >
b1001010 D
b1001010 L
b1000111101 C
b101010100001110 @
b100110 F
b100000000000000 G
b100000000000000 A
b1 B
b1100000000000 E
b11 <
b11 ,
b101 +
b111 *
b10000101011011100111001 ?
b100000101011 /
b100000101011 5
b100000101011 =
b100100100 4
b10110010001110010000 1
b100111000100 7
b11110100001001 8
b11010101100111111 2
b111 3
b11111010000 6
b10001 &
1#
#220000
0#
#225000
b11000101110000 8
b11011110011110000 2
b1001 3
b11100001000 6
b101010101 4
b10100110100000010000 1
b11111010000 7
b111101111110000100001 ?
b10110010001 /
b10110010001 5
b10110010001 =
b101 <
b101 ,
b111 +
b1001 *
b100001010110111 G
b1100100000100101 A
b11 B
b100000101011 E
b1011000000 C
b10000100000000000000000 @
b1100000000000 F
b11011100100 N
b101010 >
b101010 D
b101010 L
b10011100010000 K
b10011100010000 ;
b1 :
b11 9
b10101 V
b1111011000011000 P
b101110111000 Q
b1001010 T
b1000000101 R
b1101010000001101 O
b1101001 U
b101110111011001 ]
b10011011 M
b10011011 S
b10011011 [
b1010111100 Z
b1010111100 J
b10111011100 I
b101110111000 H
b11011001 e
b1111111001001100 _
b100101100 `
b11101100 c
b1000000100 a
b1111111111111100 ^
b1111111 d
b10000000 !
b10000000 (
b10000000 \
b10000000 b
b1111111111 Y
b10000000001 X
b100101100 W
b110010000 0
b10100 .
b10100 %
b10100 )
b111111111111111 -
b111111111111111 "
b111111111111111 '
b10001 &
1#
#230000
0#
#235000
b101000100 0
b10010 .
b10010 %
b10010 )
b1001110001000000 -
b1001110001000000 "
b1001110001000000 '
b10000000001 Y
b100101100 X
b1010111100 W
b1111111 !
b1111111 (
b1111111 \
b1111111 b
b1000000010 a
b11101100111011000 ^
b11101100 d
b1011101 e
b1111111001001100 _
b1010111100 `
b10011011 c
b10111011100 Z
b10111011100 J
b101110111000 I
b10011100010000 H
b10101111100100 ]
b1101010 M
b1101010 S
b1101010 [
b1000001010 R
b1001011011100100 O
b1001010 U
b110 V
b1110101001100000 P
b10011100010000 Q
b101010 T
b1 K
b1 ;
b11 :
b101 9
b100010000010000000000000000 N
b10000100000000 >
b10000100000000 D
b10000100000000 L
b1000111000 C
b100100001111101101000 @
b100000101011 F
b1111011111100 G
b1001101011101100 A
b101 B
b10110010001 E
b111 <
b111 ,
b1001 +
b111111111111111 *
b110110001001010010000 ?
b10100110100 /
b10100110100 5
b10100110100 =
b101000100 4
b10001110011000100000 1
b11100001000 7
b1 8
b111111111111111 2
b111111111111111 3
b10100 6
b10001 &
1#
#240000
0#
#245000
b1001110001000000 2
b1001110001000000 3
b10010 6
b1010000001 4
b11001000010100 1
b10100 7
b100111100101110101001 ?
b10001110011 /
b10001110011 5
b10001110011 =
b1001 <
b1001 ,
b111111111111111 +
b1001110001000000 *
b1101100010010 G
b1011110101111110 A
b111 B
b10100110100 E
b1001100110 C
b11010101100111000110 @
b10110010001 F
b10100100000111011100001 N
b100100001111 >
b100100001111 D
b100100001111 L
b11 K
b11 ;
b101 :
b111 9
b100000100000000 V
b100000100000000 P
b1 Q
b10000100000000 T
b1000010110 R
b101011110011100 O
b101010 U
b1010111111001 ]
b1001011 M
b1001011 S
b1001011 [
b101110111000 Z
b101110111000 J
b10011100010000 I
b1 H
b101011 e
b1111101111110100 _
b10111011100 `
b1101010 c
b10011011100110110 ^
b10011011 d
b11101100 !
b11101100 (
b11101100 \
b11101100 b
b100101100 Y
b1010111100 X
b10111011100 W
b100100001 0
b10001 .
b10001 %
b10001 )
b1100001101010000 -
b1100001101010000 "
b1100001101010000 '
b10001 &
1#
#250000
0#
#255000
b100000000 0
b10000 .
b10000 %
b10000 )
b1111111111111111 -
b1111111111111111 "
b1111111111111111 '
b1010111100 Y
b10111011100 X
b101110111000 W
b10011011 !
b10011011 (
b10011011 \
b10011011 b
b1000000101 a
b1101011000010010 ^
b1101010 d
b10101 e
b1111011000011000 _
b101110111000 `
b1001011 c
b10011100010000 Z
b10011100010000 J
b1 I
b11 H
b11100111001 ]
b101011 M
b101011 S
b101011 [
b1010111111 R
b10110101001111100000000 O
b10000100000000 U
b101001000001110 V
b1111011000101010 P
b11 Q
b100100001111 T
b101 K
b101 ;
b111 :
b1001 9
b1011001000001110010000 N
b11010101100 >
b11010101100 D
b11010101100 L
b1001000011 C
b10111100010010011100 @
b10100110100 F
b1001111001011 G
b1011001000100011 A
b1001 B
b10001110011 E
b111111111111111 <
b111111111111111 ,
b1001110001000000 +
b1100001101010000 *
b1001110001 ?
b11001 /
b11001 5
b11001 =
b1001100100 4
b10101100001000 1
b10010 7
b1100001101010000 2
b1100001101010000 3
b10001 6
b10001 &
1#
#260000
0#
#265000
b1111111111111111 2
b1111111111111111 3
b10000 6
b1000111101 4
b10011000001101 1
b10001 7
b110111001 ?
b10101 /
b10101 5
b10101 =
b1001110001000000 <
b1001110001000000 ,
b1100001101010000 +
b1111111111111111 *
b10 G
b1111111111111110 A
b111111111111111 B
b11001 E
b1001001110 C
b10100100000100001010 @
b10001110011 F
b1000101001101110000100 N
b10111100010 >
b10111100010 D
b10111100010 L
b111 K
b111 ;
b1001 :
b111111111111111 9
b10110010000011 V
b1101111010001111 P
b101 Q
b11010101100 T
b1000001010 R
b100100111100010010110 O
b100100001111 U
b1000000001001101111001100001 ]
b10110101001111 M
b10110101001111 S
b10110101001111 [
b1 Z
b1 J
b11 I
b101 H
b111 e
b10001000101110000 _
b10011100010000 `
b101011 c
b1000001010 a
b1001100011101110 ^
b1001011 d
b1101011 !
b1101011 (
b1101011 \
b1101011 b
b10111011100 Y
b101110111000 X
b10011100010000 W
b100111000100 0
b110010 .
b110010 %
b110010 )
b1010101010101010 -
b1010101010101010 "
b1010101010101010 '
b10001 &
1#
#270000
0#
