rtl/NR_stage_pipeline.v
`timescale 1ns/1ps

module NR_stage_pipeline #(parameter N = 8, parameter W = 16)(
    input  clk, rst,
    input [W-1:0] x_in,
    input [W-1:0] a_in,
    output [W-1:0] x_out
);
    // Stage 1: x^2 (Q8.8 * Q8.8 = Q16.16)
    reg [W-1:0] x_reg1, a_reg1, x_sq_reg1;
    wire [(2*W)-1:0] x_sq_full = x_in * x_in;
    wire [W-1:0] x_sq_scaled = x_sq_full >>> N; // Scale back to Q8.8

    always @(posedge clk) begin
        if (rst) begin
            x_reg1 <= 0; a_reg1 <= 0; x_sq_reg1 <= 0;
        end else begin
            x_reg1 <= x_in;
            a_reg1 <= a_in;
            x_sq_reg1 <= x_sq_scaled;
        end
    end

    // Stage 2: (3 - a*x^2)
    reg [W-1:0] x_reg2, term_reg2;
    wire [(2*W)-1:0] ax2_full = a_reg1 * x_sq_reg1;
    wire [W-1:0] term_full = (3 << N) - (ax2_full >>> N);

    always @(posedge clk) begin
        if (rst) begin
            x_reg2 <= 0; term_reg2 <= 0;
        end else begin
            x_reg2 <= x_reg1;
            term_reg2 <= term_full;
        end
    end

    // Stage 3: (x * term) / 2
    reg [W-1:0] x_final_reg;
    wire [(2*W)-1:0] mult_full = x_reg2 * term_reg2;
    wire [W-1:0] mult_scaled = mult_full >>> (N + 1);

    always @(posedge clk) begin
        if (rst) x_final_reg <= 0;
        else begin
            x_final_reg <= mult_scaled;
        end
    end

    assign x_out = x_final_reg;
endmodule

rtl/top_pipelined.v
`timescale 1ns/1ps

module top_pipelined #(
    parameter N = 8, 
    parameter W = 16,
    parameter N_ITERS = 3
)(
    input clk,
    input rst,
    input [W-1:0] x0,
    input [W-1:0] a_in,
    output [W-1:0] result
);

    wire [W-1:0] x_bus [0:N_ITERS];
    wire [W-1:0] a_pipe [0:N_ITERS];

    assign x_bus[0] = x0;
    assign a_pipe[0] = a_in;

    genvar i;
    generate
        for (i = 0; i < N_ITERS; i = i + 1) begin : NR_ITER
            NR_stage_pipeline #(N, W) stage_inst (
                .clk(clk), .rst(rst),
                .x_in(x_bus[i]), .a_in(a_pipe[i]),
                .x_out(x_bus[i+1])
            );
            reg [W-1:0] a_d1, a_d2, a_d3;

            always @(posedge clk) begin
                if (rst) begin
                    a_d1 <= 0;
                    a_d2 <= 0;
                    a_d3 <= 0;
                end else begin
                    a_d1 <= a_pipe[i];
                    a_d2 <= a_d1;
                    a_d3 <= a_d2;
                end
            end

            assign a_pipe[i+1] = a_d3;
            // assign a_pipe[i+1] = d3;
        end
    endgenerate
    assign result = x_bus[N_ITERS];
endmodule

sim/tb_pipeline.v
`timescale 1ns/1ps

module tb_pipeline;

    parameter N = 8;
    parameter W = 16;
    parameter N_ITERS = 3;
    localparam LATENCY = N_ITERS * 3;

    reg clk, rst;
    reg [W-1:0] a_in, x0_in;
    wire [W-1:0] result;

    reg [W-1:0] a_history [0:LATENCY + N_ITERS];
    reg [W-1:0] x0_history [0:LATENCY + N_ITERS];

    initial clk = 0;
    always #5 clk = ~clk;

    top_pipelined #(N, W, N_ITERS) dut (
        .clk(clk), .rst(rst), .x0(x0_in), .a_in(a_in), .result(result)
    );

    integer j;
    always @(posedge clk) begin
        a_history[0] <= a_in;
        x0_history[0] <= x0_in;
        for (j = 1; j <= LATENCY + N_ITERS; j = j + 1) begin
            a_history[j] <= a_history[j-1];
            x0_history[j] <= x0_history[j-1];
        end
    end

    integer i;
    integer total_inputs = 36; // Total count of cases in your list

    initial begin
        // --- Setup ---
        rst = 1; a_in = 0; x0_in = 0;
        repeat(10) @(posedge clk);
        rst = 0;
        @(posedge clk);

        // --- Feeding your specific stream ---
        // 1. Boundary around 1.0
        @(posedge clk); a_in <= 16'd255;  x0_in <= 16'd260; 
        @(posedge clk); a_in <= 16'd256;  x0_in <= 16'd256; 
        @(posedge clk); a_in <= 16'd257;  x0_in <= 16'd250; 

        // 2. Transition edges
        @(posedge clk); a_in <= 16'd511;  x0_in <= 16'd130; 
        @(posedge clk); a_in <= 16'd513;  x0_in <= 16'd125; 
        @(posedge clk); a_in <= 16'd1023; x0_in <= 16'd100; 
        @(posedge clk); a_in <= 16'd1025; x0_in <= 16'd95;  

        // 3. Mid-range random
        @(posedge clk); a_in <= 16'd300;   x0_in <= 16'd200;
        @(posedge clk); a_in <= 16'd700;   x0_in <= 16'd140;
        @(posedge clk); a_in <= 16'd1500;  x0_in <= 16'd80;
        @(posedge clk); a_in <= 16'd3000;  x0_in <= 16'd60;
        @(posedge clk); a_in <= 16'd10000; x0_in <= 16'd30;

        // 4. Very small numbers
        @(posedge clk); a_in <= 16'd1;    x0_in <= 16'd4096;
        @(posedge clk); a_in <= 16'd3;    x0_in <= 16'd2048;
        @(posedge clk); a_in <= 16'd5;    x0_in <= 16'd2500;
        @(posedge clk); a_in <= 16'd7;    x0_in <= 16'd2000;
        @(posedge clk); a_in <= 16'd9;    x0_in <= 16'd1800;

        // 5. Large values
        @(posedge clk); a_in <= 16'd32767; x0_in <= 16'd20;
        @(posedge clk); a_in <= 16'd40000; x0_in <= 16'd18;
        @(posedge clk); a_in <= 16'd50000; x0_in <= 16'd17;
        @(posedge clk); a_in <= 16'd65535; x0_in <= 16'd16;

        // 6. Single-bit sweep
        @(posedge clk); a_in <= 16'd1;     x0_in <= 16'd4096;
        @(posedge clk); a_in <= 16'd2;     x0_in <= 16'd4096;
        @(posedge clk); a_in <= 16'd4;     x0_in <= 16'd2048;
        @(posedge clk); a_in <= 16'd8;     x0_in <= 16'd1500;
        @(posedge clk); a_in <= 16'd16;    x0_in <= 16'd1000;
        @(posedge clk); a_in <= 16'd32;    x0_in <= 16'd800;
        @(posedge clk); a_in <= 16'd64;    x0_in <= 16'd600;
        @(posedge clk); a_in <= 16'd128;   x0_in <= 16'd400;
        @(posedge clk); a_in <= 16'd256;   x0_in <= 16'd256;
        @(posedge clk); a_in <= 16'd512;   x0_in <= 16'd180;
        @(posedge clk); a_in <= 16'd1024;  x0_in <= 16'd128;
        @(posedge clk); a_in <= 16'd2048;  x0_in <= 16'd90;
        @(posedge clk); a_in <= 16'd4096;  x0_in <= 16'd64;
        @(posedge clk); a_in <= 16'd8192;  x0_in <= 16'd45;
        @(posedge clk); a_in <= 16'd16384; x0_in <= 16'd32;
        @(posedge clk); a_in <= 16'd32768; x0_in <= 16'd22;

        // --- End of Data ---
        @(posedge clk); a_in <= 0; x0_in <= 0;

        // --- Wait for last result to exit pipeline ---
        repeat (LATENCY + 5) @(posedge clk);
        $display("Simulation completed all cases.");
        $finish;
    end

    initial begin
        forever begin
            @(posedge clk);
            if (result !== 0 && a_history[8] !== 0) begin
                $display("Time: %t | Input A: %d | Start x0: %d | Result: %d", $time, a_history[8], x0_history[8], result);
            end
        end
    end

    initial begin
        $dumpfile("nr_pipeline.vcd");
        $dumpvars(0, tb_pipeline);
    end
endmodule

out/vcd/nr_pipeline.vcd
$date
	Sat Apr 11 17:42:14 2026
$end
$version
	Icarus Verilog
$end
$timescale
	1ps
$end
$scope module tb_pipeline $end
$var wire 16 ! result [15:0] $end
$var reg 16 " a_in [15:0] $end
$var reg 1 # clk $end
$var reg 1 $ rst $end
$var reg 16 % x0_in [15:0] $end
$var integer 32 & j [31:0] $end
$var integer 32 ' total_inputs [31:0] $end
$scope module dut $end
$var wire 16 ( a_in [15:0] $end
$var wire 1 # clk $end
$var wire 16 ) result [15:0] $end
$var wire 1 $ rst $end
$var wire 16 * x0 [15:0] $end
$scope begin NR_ITER[0] $end
$var reg 16 + a_d1 [15:0] $end
$var reg 16 , a_d2 [15:0] $end
$var reg 16 - a_d3 [15:0] $end
$scope module stage_inst $end
$var wire 16 . a_in [15:0] $end
$var wire 1 # clk $end
$var wire 1 $ rst $end
$var wire 16 / x_in [15:0] $end
$var wire 16 0 x_out [15:0] $end
$var wire 16 1 x_sq_scaled [15:0] $end
$var wire 32 2 x_sq_full [31:0] $end
$var wire 16 3 term_full [15:0] $end
$var wire 16 4 mult_scaled [15:0] $end
$var wire 32 5 mult_full [31:0] $end
$var wire 32 6 ax2_full [31:0] $end
$var reg 16 7 a_reg1 [15:0] $end
$var reg 16 8 term_reg2 [15:0] $end
$var reg 16 9 x_final_reg [15:0] $end
$var reg 16 : x_reg1 [15:0] $end
$var reg 16 ; x_reg2 [15:0] $end
$var reg 16 < x_sq_reg1 [15:0] $end
$upscope $end
$upscope $end
$scope begin NR_ITER[1] $end
$var reg 16 = a_d1 [15:0] $end
$var reg 16 > a_d2 [15:0] $end
$var reg 16 ? a_d3 [15:0] $end
$scope module stage_inst $end
$var wire 16 @ a_in [15:0] $end
$var wire 1 # clk $end
$var wire 1 $ rst $end
$var wire 16 A x_in [15:0] $end
$var wire 16 B x_out [15:0] $end
$var wire 16 C x_sq_scaled [15:0] $end
$var wire 32 D x_sq_full [31:0] $end
$var wire 16 E term_full [15:0] $end
$var wire 16 F mult_scaled [15:0] $end
$var wire 32 G mult_full [31:0] $end
$var wire 32 H ax2_full [31:0] $end
$var reg 16 I a_reg1 [15:0] $end
$var reg 16 J term_reg2 [15:0] $end
$var reg 16 K x_final_reg [15:0] $end
$var reg 16 L x_reg1 [15:0] $end
$var reg 16 M x_reg2 [15:0] $end
$var reg 16 N x_sq_reg1 [15:0] $end
$upscope $end
$upscope $end
$scope begin NR_ITER[2] $end
$var reg 16 O a_d1 [15:0] $end
$var reg 16 P a_d2 [15:0] $end
$var reg 16 Q a_d3 [15:0] $end
$scope module stage_inst $end
$var wire 16 R a_in [15:0] $end
$var wire 1 # clk $end
$var wire 1 $ rst $end
$var wire 16 S x_in [15:0] $end
$var wire 16 T x_out [15:0] $end
$var wire 16 U x_sq_scaled [15:0] $end
$var wire 32 V x_sq_full [31:0] $end
$var wire 16 W term_full [15:0] $end
$var wire 16 X mult_scaled [15:0] $end
$var wire 32 Y mult_full [31:0] $end
$var wire 32 Z ax2_full [31:0] $end
$var reg 16 [ a_reg1 [15:0] $end
$var reg 16 \ term_reg2 [15:0] $end
$var reg 16 ] x_final_reg [15:0] $end
$var reg 16 ^ x_reg1 [15:0] $end
$var reg 16 _ x_reg2 [15:0] $end
$var reg 16 ` x_sq_reg1 [15:0] $end
$upscope $end
$upscope $end
$upscope $end
$upscope $end
$enddefinitions $end
#0
$dumpvars
bx `
bx _
bx ^
bx ]
bx \
bx [
bx Z
bx Y
bx X
bx W
bx V
bx U
bx T
bx S
bx R
bx Q
bx P
bx O
bx N
bx M
bx L
bx K
bx J
bx I
bx H
bx G
bx F
bx E
bx D
bx C
bx B
bx A
bx @
bx ?
bx >
bx =
bx <
bx ;
bx :
bx 9
bx 8
bx 7
bx 6
bx 5
bx 4
bx 3
b0 2
b0 1
bx 0
b0 /
b0 .
bx -
bx ,
bx +
b0 *
bx )
b0 (
b100100 '
bx &
b0 %
1$
0#
b0 "
bx !
$end
#5000
b1100000000 3
b0 4
b0 C
b1100000000 E
b0 F
b0 U
b1100000000 W
b0 X
b0 6
b0 <
b0 7
b0 :
b0 5
b0 8
b0 ;
b0 D
b0 0
b0 9
b0 A
b0 @
b0 -
b0 ,
b0 +
b0 H
b0 N
b0 I
b0 L
b0 G
b0 J
b0 M
b0 V
b0 B
b0 K
b0 S
b0 R
b0 ?
b0 >
b0 =
b0 Z
b0 `
b0 [
b0 ^
b0 Y
b0 \
b0 _
b0 !
b0 )
b0 T
b0 ]
b0 Q
b0 P
b0 O
b1101 &
1#
#10000
0#
#15000
b1101 &
1#
#20000
0#
#25000
b1101 &
1#
#30000
0#
#35000
b1101 &
1#
#40000
0#
#45000
b1101 &
1#
#50000
0#
#55000
b1101 &
1#
#60000
0#
#65000
b1101 &
1#
#70000
0#
#75000
b1101 &
1#
#80000
0#
#85000
b1101 &
1#
#90000
0#
#95000
0$
b1101 &
1#
#100000
0#
#105000
b1100000000 8
b1100000000 J
b1100000000 \
b1101 &
1#
#110000
0#
#115000
b100001000 1
b10000100000010000 2
b100000100 /
b100000100 %
b100000100 *
b11111111 .
b11111111 "
b11111111 (
b1101 &
1#
#120000
0#
#125000
b111111010 3
b100000000 1
b10000011011111000 6
b100001000 <
b11111111 7
b100000100 :
b11111111 +
b10000000000000000 2
b100000000 /
b100000000 %
b100000000 *
b100000000 .
b100000000 "
b100000000 (
b1101 &
1#
#130000
0#
#135000
b11110100 1
b100000000 4
b1000000000 3
b1111010000100100 2
b11111010 /
b11111010 %
b11111010 *
b100000001 .
b100000001 "
b100000001 (
b11111111 ,
b100000000 +
b111111010 8
b100000000111101000 5
b100000100 ;
b100000000 <
b10000000000000000 6
b100000000 7
b100000000 :
b1101 &
1#
#140000
0#
#145000
b1000001100 3
b100000000 C
b1000010 1
b11110100 <
b1111010011110100 6
b100000001 7
b11111010 :
b1000000000 8
b100000000000000000 5
b100000000 ;
b10000000000000000 D
b100000000 0
b100000000 9
b100000000 A
b11111111 @
b11111111 -
b100000000 ,
b100000001 +
b100001000000100 2
b10000010 /
b10000010 %
b10000010 *
b111111111 .
b111111111 "
b111111111 (
b1101 &
1#
#150000
0#
#155000
b111101 1
b1000000001 E
b11111111 4
b1001111101 3
b11110100001001 2
b1111101 /
b1111101 %
b1111101 *
b1000000001 .
b1000000001 "
b1000000001 (
b11111111 =
b1111111100000000 H
b100000000 N
b11111111 I
b100000000 L
b100000000 @
b100000000 -
b100000001 ,
b111111111 +
b1000001100 8
b11111111110111000 5
b11111010 ;
b1000010 <
b1000001110111110 6
b111111111 7
b10000010 :
b1101 &
1#
#160000
0#
#165000
b1010000110 3
b10100001 4
b11111110 C
b1000000000 E
b100000000 F
b100111 1
b111101 <
b111101000111101 6
b1000000001 7
b1111101 :
b1001111101 8
b10100001101111010 5
b10000010 ;
b1111111000000001 D
b11111111 0
b11111111 9
b11111111 A
b100000001 @
b100000001 -
b111111111 ,
b1000000001 +
b10000000000000000 H
b100000000 I
b1000000001 J
b100000000100000000 G
b100000000 M
b11111111 >
b100000000 =
b10011100010000 2
b1100100 /
b1100100 %
b1100100 *
b1111111111 .
b1111111111 "
b1111111111 (
b1101 &
1#
#170000
0#
#175000
b100011 1
b100000000 U
b1000000010 E
b1100101 C
b10011101 4
b1001100101 3
b10001101000001 2
b1011111 /
b1011111 %
b1011111 *
b10000000001 .
b10000000001 "
b10000000001 (
b11111111 R
b11111111 ?
b100000000 >
b100000001 =
b10000000000000000 V
b100000000 B
b100000000 K
b100000000 S
b100000000000000000 G
b1000000000 J
b11111110 N
b1111111011111110 H
b100000001 I
b11111111 L
b111111111 @
b111111111 -
b1000000001 ,
b1111111111 +
b110010101000001 D
b10100001 0
b10100001 9
b10100001 A
b1010000110 8
b10011101101101110 5
b1111101 ;
b100111 <
b1001101111011001 6
b1111111111 7
b1100100 :
b1101 &
1#
#180000
0#
#185000
b1001110100 3
b1110111 4
b1100000 C
b1000110111 E
b11111111 F
b1000000001 W
b10011100 1
b100011 <
b1000110000100011 6
b10000000001 7
b1011111 :
b1001100101 8
b1110111101110100 5
b1100100 ;
b110000001001001 D
b10011101 0
b10011101 9
b10011101 A
b1000000001 @
b1000000001 -
b1111111111 ,
b10000000001 +
b1100101 N
b1100100110011011 H
b111111111 I
b10100001 L
b1000000010 J
b11111111111111110 G
b11111111 M
b100000000 R
b100000000 ?
b100000001 >
b111111111 =
b1111111100000000 Z
b100000000 `
b11111111 [
b100000000 ^
b11111111 O
b1001110001000000 2
b11001000 /
b11001000 %
b11001000 *
b100101100 .
b100101100 "
b100101100 (
b1101 &
1#
#190000
0#
#195000
b1001100 1
b100000000 X
b1000000000 W
b11111110 U
b10110010 F
b1001000000 E
b110111 C
b1110100 4
b1001001010 3
b100110010010000 2
b10001100 /
b10001100 %
b10001100 *
b1010111100 .
b1010111100 "
b1010111100 (
b11111111 P
b100000000 O
b1000000001 \
b100000000100000000 Y
b100000000 _
b10000000000000000 Z
b100000000 [
b100000001 R
b100000001 ?
b111111111 >
b1000000001 =
b1111111000000001 V
b11111111 B
b11111111 K
b11111111 S
b1000110111 J
b10110010010010111 G
b10100001 M
b1100000 N
b1100000001100000 H
b1000000001 I
b10011101 L
b1111111111 @
b1111111111 -
b10000000001 ,
b100101100 +
b11011101010001 D
b1110111 0
b1110111 9
b1110111 A
b1001110100 8
b1110100100001100 5
b1011111 ;
b10011100 <
b1011011011010000 6
b100101100 7
b11001000 :
b1101 &
1#
#200000
0#
#205000
b1000110001 3
b11100100 4
b110100 C
b1000100101 E
b10110000 F
b1111011 U
b1000000010 W
b11001 1
b1001100 <
b1100111111010000 6
b1010111100 7
b10001100 :
b1001001010 8
b11100100111010000 5
b11001000 ;
b11010010010000 D
b1110100 0
b1110100 9
b1110100 A
b10000000001 @
b10000000001 -
b100101100 ,
b1010111100 +
b110111 N
b1101101111001001 H
b1111111111 I
b1110111 L
b1001000000 J
b10110000101000000 G
b10011101 M
b111101111000100 V
b10110010 B
b10110010 K
b10110010 S
b111111111 R
b111111111 ?
b1000000001 >
b1111111111 =
b11111110 `
b1111111011111110 Z
b100000001 [
b11111111 ^
b100000000000000000 Y
b1000000000 \
b100000000 !
b100000000 )
b100000000 T
b100000000 ]
b11111111 Q
b100000000 P
b100000001 O
b1100100000000 2
b1010000 /
b1010000 %
b1010000 *
b10111011100 .
b10111011100 "
b10111011100 (
b1101 &
1#
#210000
0#
#215000
b1110 1
b11111111 X
b1000001011 W
b1111001 U
b1111111 F
b1000110000 E
b11001011 C
b10011001 4
b1001101110 3
b111000010000 2
b111100 /
b111100 %
b111100 *
b101110111000 .
b101110111000 "
b101110111000 (
b100000000 Q
b100000001 P
b111111111 O
b1000000010 \
b11111111111111110 Y
b11111111 _
b1111011 `
b1111010110000101 Z
b111111111 [
b10110010 ^
b1000000001 R
b1000000001 ?
b1111111111 >
b10000000001 =
b111100100000000 V
b10110000 B
b10110000 K
b10110000 S
b1000100101 J
b1111111100110011 G
b1110111 M
b110100 N
b1101000000110100 H
b10000000001 I
b1110100 L
b100101100 @
b100101100 -
b1010111100 ,
b10111011100 +
b1100101100010000 D
b11100100 0
b11100100 9
b11100100 A
b1000110001 8
b10011001011001100 5
b10001100 ;
b11001 <
b1001001001111100 6
b10111011100 7
b1010000 :
b1101 &
1#
#220000
0#
#225000
b1001011100 3
b1100001 4
b1011011 C
b1000010011 E
b1111110 F
b111111 U
b1000001110 W
b10110101 X
b11 1
b1110 <
b1010010000010000 6
b101110111000 7
b111100 :
b1001101110 8
b1100001001100000 5
b1010000 ;
b101101101110001 D
b10011001 0
b10011001 9
b10011001 A
b1010111100 @
b1010111100 -
b10111011100 ,
b101110111000 +
b11001011 N
b1110110111100100 H
b100101100 I
b11100100 L
b1000110000 J
b1111110111000000 G
b1110100 M
b11111100000001 V
b1111111 B
b1111111 K
b1111111 S
b1111111111 R
b1111111111 ?
b10000000001 >
b100101100 =
b1111001 `
b1111001001111001 Z
b1000000001 [
b10110000 ^
b1000001011 \
b10110101110100110 Y
b10110010 _
b11111111 !
b11111111 )
b11111111 T
b11111111 ]
b100000001 Q
b111111111 P
b1000000001 O
b1110000100 2
b11110 /
b11110 %
b11110 *
b10011100010000 .
b10011100010000 "
b10011100010000 (
b1101 &
1#
#230000
0#
#235000
b0 1
b10110100 X
b1000000101 W
b111110 U
b11101100 F
b1000001000 E
b100100 C
b1000110 4
b1010001011 3
b1000000000000000000000000 2
b1000000000000 /
b1000000000000 %
b1000000000000 *
b1 .
b1 "
b1 (
b111111111 Q
b1000000001 P
b1111111111 O
b10110101 !
b10110101 )
b10110101 T
b10110101 ]
b1000001110 \
b10110100110100000 Y
b10110000 _
b111111 `
b1111101111000001 Z
b1111111111 [
b1111111 ^
b10000000001 R
b10000000001 ?
b100101100 >
b1010111100 =
b11111000000100 V
b1111110 B
b1111110 K
b1111110 S
b1000010011 J
b11101100011101100 G
b11100100 M
b1011011 N
b1111100011010100 H
b1010111100 I
b10011001 L
b10111011100 @
b10111011100 -
b101110111000 ,
b10011100010000 +
b10010011000001 D
b1100001 0
b1100001 9
b1100001 A
b1001011100 8
b1000110110010000 5
b111100 ;
b11 <
b111010100110000 6
b10011100010000 7
b11110 :
b1101 &
1#
#240000
0#
#245000
b1100000000 3
b100110 4
b10011 C
b1000101110 E
b10011011 F
b11011001 U
b1000001000 W
b10000000 X
b100000000000000 1
b0 <
b0 6
b1 7
b1000000000000 :
b1010001011 8
b100110001001010 5
b11110 ;
b1001100100100 D
b1000110 0
b1000110 9
b1000110 A
b101110111000 @
b101110111000 -
b10011100010000 ,
b1 +
b100100 N
b1101001011110000 H
b10111011100 I
b1100001 L
b1000001000 J
b10011011011001000 G
b10011001 M
b1101100110010000 V
b11101100 B
b11101100 K
b11101100 S
b100101100 R
b100101100 ?
b1010111100 >
b10111011100 =
b111110 `
b1111100000111110 Z
b10000000001 [
b1111110 ^
b1000000101 \
b10000000001111011 Y
b1111111 _
b10110100 !
b10110100 )
b10110100 T
b10110100 ]
b1000000001 Q
b1111111111 P
b10000000001 O
b10000000000000000000000 2
b100000000000 /
b100000000000 %
b100000000000 *
b11 .
b11 "
b11 (
b1101 &
1#
#250000
0#
#255000
b101111101011110 1
b1111111 X
b1000000010 W
b1011101 U
b1101001 F
b1000100010 E
b101 C
b1100000000000 4
b1001000000 3
b10111110101111000010000 2
b100111000100 /
b100111000100 %
b100111000100 *
b101 .
b101 "
b101 (
b1111111111 Q
b10000000001 P
b100101100 O
b10000000 !
b10000000 )
b10000000 T
b10000000 ]
b1000001000 \
b1111111111110000 Y
b1111110 _
b11011001 `
b1111111001001100 Z
b100101100 [
b11101100 ^
b1010111100 R
b1010111100 ?
b10111011100 >
b101110111000 =
b101110111011001 V
b10011011 B
b10011011 K
b10011011 S
b1000101110 J
b1101001101101110 G
b1100001 M
b10011 N
b1101111010101000 H
b101110111000 I
b1000110 L
b10011100010000 @
b10011100010000 -
b1 ,
b11 +
b10110100100 D
b100110 0
b100110 9
b100110 A
b1100000000 8
b1100000000000000000000 5
b1000000000000 ;
b1100000000000000 6
b100000000000000 <
b11 7
b100000000000 :
b1101 &
1#
#260000
0#
#265000
b100100100 3
b100100000000 4
b100000000000000 C
b1000111101 E
b1001010 F
b101011 U
b11101100 X
b11110100001001 1
b101111101011110 <
b11101110011010110 6
b101 7
b100111000100 :
b1001000000 8
b100100000000000000000 5
b100000000000 ;
b10010000000000000000000000 D
b1100000000000 0
b1100000000000 9
b1100000000000 A
b1 @
b1 -
b11 ,
b101 +
b101 N
b1100001101010000 H
b10011100010000 I
b100110 L
b1000100010 J
b1001010101001100 G
b1000110 M
b10101100010001 V
b1101001 B
b1101001 K
b1101001 S
b10111011100 R
b10111011100 ?
b101110111000 >
b10011100010000 =
b1011101 `
b1111111001001100 Z
b1010111100 [
b10011011 ^
b1000000010 \
b11101100111011000 Y
b11101100 _
b1111111 !
b1111111 )
b1111111 T
b1111111 ]
b10000000001 Q
b100101100 P
b1010111100 O
b1111010000100100000000 2
b11111010000 /
b11111010000 %
b11111010000 *
b111 .
b111 "
b111 (
b1101 &
1#
#270000
0#
#275000
b11000101110000 1
b10011011 X
b1000000101 W
b10101 U
b101010 F
b1011000000 E
b101000100000000 C
b10110010001 4
b101010101 3
b1100010111000001000000 2
b11100001000 /
b11100001000 %
b11100001000 *
b1001 .
b1001 "
b1001 (
b100101100 Q
b1010111100 P
b10111011100 O
b11101100 !
b11101100 )
b11101100 T
b11101100 ]
b10011011100110110 Y
b10011011 _
b101011 `
b1111101111110100 Z
b10111011100 [
b1101001 ^
b101110111000 R
b101110111000 ?
b10011100010000 >
b1 =
b1010101100100 V
b1001010 B
b1001010 K
b1001010 S
b1000111101 J
b101010100001110 G
b100110 M
b100000000000000 N
b100000000000000 H
b1 I
b1100000000000 L
b11 @
b11 -
b101 ,
b111 +
b10100010000000000000000 D
b100100000000 0
b100100000000 9
b100100000000 A
b100100100 8
b10110010001110010000 5
b100111000100 ;
b11110100001001 <
b11010101100111111 6
b111 7
b11111010000 :
b1101 &
1#
#280000
0#
#285000
b101000100 3
b10100110100 4
b1111011111100 C
b1000001101 E
b10000100000000 F
b110 U
b1000001010 W
b1101010 X
b1 1
b11000101110000 <
b11011110011110000 6
b1001 7
b11100001000 :
b101010101 8
b10100110100000010000 5
b11111010000 ;
b111101111110000100001 D
b10110010001 0
b10110010001 9
b10110010001 A
b101 @
b101 -
b111 ,
b1001 +
b101000100000000 N
b1111001100000000 H
b11 I
b100100000000 L
b1011000000 J
b10000100000000000000000 G
b1100000000000 M
b11011100100 V
b101010 B
b101010 K
b101010 S
b10011100010000 R
b10011100010000 ?
b1 >
b11 =
b10101 `
b1111011000011000 Z
b101110111000 [
b1001010 ^
b1000000101 \
b1101010000001101 Y
b1101001 _
b10011011 !
b10011011 )
b10011011 T
b10011011 ]
b1010111100 Q
b10111011100 P
b101110111000 O
b110010000 2
b10100 /
b10100 %
b10100 *
b111111111111111 .
b111111111111111 "
b111111111111111 (
b1101 &
1#
#290000
0#
#295000
b1001011 X
b1000010110 W
b100000100000000 U
b100100111010 F
b1001100110 E
b1101100010010 C
b10001110011 4
b1010000001 3
b101000100 2
b10010 /
b10010 %
b10010 *
b1001110001000000 .
b1001110001000000 "
b1001110001000000 (
b10111011100 Q
b101110111000 P
b10011100010000 O
b1101010 !
b1101010 )
b1101010 T
b1101010 ]
b1000001010 \
b1001011011100100 Y
b1001010 _
b110 `
b1110101001100000 Z
b10011100010000 [
b101010 ^
b1 R
b1 ?
b11 >
b101 =
b100010000010000000000000000 V
b10000100000000 B
b10000100000000 K
b10000100000000 S
b1000001101 J
b100100111010100000000 G
b100100000000 M
b1111011111100 N
b1001101011101100 H
b101 I
b10110010001 L
b111 @
b111 -
b1001 ,
b111111111111111 +
b110110001001010010000 D
b10100110100 0
b10100110100 9
b10100110100 A
b101000100 8
b10001110011000100000 5
b11100001000 ;
b1 <
b111111111111111 6
b111111111111111 7
b10100 :
b1101 &
1#
#300000
0#
#305000
b1001100100 3
b11001 4
b1001111001011 C
b1001000011 E
b11010101100 F
b101010100100001 U
b1010111111 W
b101011 X
b1001110001000000 6
b1001110001000000 7
b10010 :
b1010000001 8
b11001000010100 5
b10100 ;
b100111100101110101001 D
b10001110011 0
b10001110011 9
b10001110011 A
b1001 @
b1001 -
b111111111111111 ,
b1001110001000000 +
b1101100010010 N
b1011110101111110 H
b111 I
b10100110100 L
b1001100110 J
b11010101100111000110 G
b10110010001 M
b10101010010000100100100 V
b100100111010 B
b100100111010 K
b100100111010 S
b11 R
b11 ?
b101 >
b111 =
b100000100000000 `
b100000100000000 Z
b1 [
b10000100000000 ^
b1000010110 \
b101011110011100 Y
b101010 _
b1001011 !
b1001011 )
b1001011 T
b1001011 ]
b101110111000 Q
b10011100010000 P
b1 O
b100100001 2
b10001 /
b10001 %
b10001 *
b1100001101010000 .
b1100001101010000 "
b1100001101010000 (
b1101 &
1#
#310000
0#
#315000
b10110101001111 X
b1000000001 W
b10110010000011 U
b10111100010 F
b1001001110 E
b10 C
b10101 4
b1000111101 3
b100000000 2
b10000 /
b10000 %
b10000 *
b1111111111111111 .
b1111111111111111 "
b1111111111111111 (
b10011100010000 Q
b1 P
b11 O
b101011 !
b101011 )
b101011 T
b101011 ]
b1010111111 \
b10110101001111100000000 Y
b10000100000000 _
b101010100100001 `
b1111111101100011 Z
b11 [
b100100111010 ^
b101 R
b101 ?
b111 >
b1001 =
b1011001000001110010000 V
b11010101100 B
b11010101100 K
b11010101100 S
b1001000011 J
b10111100010010011100 G
b10100110100 M
b1001111001011 N
b1011001000100011 H
b1001 I
b10001110011 L
b111111111111111 @
b111111111111111 -
b1001110001000000 ,
b1100001101010000 +
b1001110001 D
b11001 0
b11001 9
b11001 A
b1001100100 8
b10101100001000 5
b10010 ;
b1100001101010000 6
b1100001101010000 7
b10001 :
b1101 &
1#
#320000
0#
#325000
b1000000001 3
b10011 4
b1 C
b1000000001 E
b10100100000 F
b10001010011011 U
b1000100010 W
b100100111110 X
b0 1
b1111111111111111 6
b1111111111111111 7
b10000 :
b1000111101 8
b10011000001101 5
b10001 ;
b110111001 D
b10101 0
b10101 9
b10101 A
b1001110001000000 @
b1001110001000000 -
b1100001101010000 ,
b1111111111111111 +
b10 N
b1111111111111110 H
b111111111111111 I
b11001 L
b1001001110 J
b10100100000100001010 G
b10001110011 M
b1000101001101110000100 V
b10111100010 B
b10111100010 K
b10111100010 S
b111 R
b111 ?
b1001 >
b111111111111111 =
b10110010000011 `
b1101111010001111 Z
b101 [
b11010101100 ^
b1000000001 \
b100100111110100111010 Y
b100100111010 _
b10110101001111 !
b10110101001111 )
b10110101001111 T
b10110101001111 ]
b1 Q
b11 P
b101 O
b1000000000000000000000000 2
b1000000000000 /
b1000000000000 %
b1000000000000 *
b1 .
b1 "
b1 (
b1101 &
1#
#330000
0#
#335000
b11100011101 X
b1000001110 W
b1101001000100 U
b11001 F
b1001100100 E
b10000 4
b1100000000 3
b10 .
b10 "
b10 (
b11 Q
b101 P
b111 O
b100100111110 !
b100100111110 )
b100100111110 T
b100100111110 ]
b1000100010 \
b11100011101011011000 Y
b11010101100 _
b10001010011011 `
b1111001000111101 Z
b111 [
b10111100010 ^
b1001 R
b1001 ?
b111111111111111 >
b1001110001000000 =
b110100100010000000000 V
b10100100000 B
b10100100000 K
b10100100000 S
b1000000001 J
b11001000011001 G
b11001 M
b1 N
b1001110001000000 H
b1001110001000000 I
b10101 L
b1100001101010000 @
b1100001101010000 -
b1111111111111111 ,
b1 +
b101101001 D
b10011 0
b10011 9
b10011 A
b1000000001 8
b10000000010000 5
b10000 ;
b0 <
b0 6
b1 7
b1000000000000 :
b1101 &
1#
#340000
0#
