rtl/NR_stage_pipeline.v
`timescale 1ns/1ps

module NR_stage_pipeline #(parameter N = 8, parameter W = 16)(
    input  clk, rst,
    input [W-1:0] x_in,
    input [W-1:0] a_in,
    output [W-1:0] x_out
);
    // Stage 1: x^2 (QN.N * QN.N = Q2N.2N -> QN.N after truncation)
    reg [W-1:0] x_reg1, a_reg1, x_sq_reg1;
    wire [(2*W)-1:0] x_sq_full = x_in * x_in;
    wire [W-1:0] x_sq_scaled = (x_sq_full + (1 << (N-1))) >> N; // truncate at x^2 and final multiplication stage to maintain accuracy

    always @(posedge clk) begin
        if (rst) begin
            x_reg1 <= 0; a_reg1 <= 0; x_sq_reg1 <= 0;
        end else begin
            x_reg1 <= x_in;
            a_reg1 <= a_in;
            x_sq_reg1 <= x_sq_scaled;
        end
    end

    // Stage 2: (3 - a*x^2)
    reg [W-1:0] x_reg2, term_reg2;
    wire [(2*W)-1:0] ax2_full = a_reg1 * x_sq_reg1;
    // wire [W-1:0] term_full = (3 << N) - ((ax2_full + (1 << (N-1))) >> N);        // truncation everywhere made converging for large number slower
    wire [W-1:0] term_full = (3 << N) - ((ax2_full) >> N);

    always @(posedge clk) begin
        if (rst) begin
            x_reg2 <= 0; term_reg2 <= 0;
        end else begin
            x_reg2 <= x_reg1;
            term_reg2 <= term_full;
        end
    end

    // Stage 3: (x * term) / 2
    reg [W-1:0] x_final_reg;
    wire [(2*W)-1:0] mult_full = x_reg2 * term_reg2;
    wire [W-1:0] mult_scaled = (mult_full + (1 << (N))) >> (N + 1);

    always @(posedge clk) begin
        if (rst) x_final_reg <= 0;
        else begin
            x_final_reg <= mult_scaled;
        end
    end

    assign x_out = x_final_reg;
endmodule

rtl/top_pipelined.v
`timescale 1ns/1ps

module top_pipelined #(
    parameter N = 8, 
    parameter W = 16,
    parameter N_ITERS = 3
)(
    input clk,
    input rst,
    input [W-1:0] x0,
    input [W-1:0] a_in,
    output [W-1:0] result
);

    wire [W-1:0] x_bus [0:N_ITERS];
    wire [W-1:0] a_pipe [0:N_ITERS];

    assign x_bus[0] = x0;
    assign a_pipe[0] = a_in;

    genvar i;
    generate
        for (i = 0; i < N_ITERS; i = i + 1) begin : NR_ITER
            NR_stage_pipeline #(N, W) stage_inst (
                .clk(clk), .rst(rst),
                .x_in(x_bus[i]), .a_in(a_pipe[i]),
                .x_out(x_bus[i+1])
            );
            reg [W-1:0] a_d1, a_d2, a_d3;

            always @(posedge clk) begin
                if (rst) begin
                    a_d1 <= 0;
                    a_d2 <= 0;
                    a_d3 <= 0;
                end else begin
                    a_d1 <= a_pipe[i];
                    a_d2 <= a_d1;
                    a_d3 <= a_d2;
                end
            end

            assign a_pipe[i+1] = a_d3;
            // assign a_pipe[i+1] = d3;
        end
    endgenerate
    assign result = x_bus[N_ITERS];
endmodule

rtl/LOD.v
`timescale 1ns/1ps

module LOD #(parameter W = 16)(
    input  [W-1:0] x_in,
    output [W-1:0] x_out,
    output reg [$clog2(W)-1:0] index_out
);

    wire [W-1:0] BR_x;
    wire [W-1:0] NOT_out;
    wire [W-1:0] adder_out;
    wire [W-1:0] AND_out;

    // step 1: bit reversal of x_in
    // genvar i;
    // generate
    //     for(i = 0; i < W; i = i+1) begin
    //         assign BR_x[W-i-1] = x_in[i];
    //     end
    // endgenerate

    assign BR_x = bit_reverse(x_in); 

    // step 2: NOT of BR_x
    assign NOT_out = ~BR_x;

    // step 3: 2's complement = NOT + 1
    assign adder_out = NOT_out + 1;

    // step 4: AND between BR_x and its 2's complement
    assign AND_out = BR_x & adder_out;

    // step 5: bit reverse AND_out to get LOD(x_in)
    // generate
    //     for(i = 0; i < W; i = i+1) begin
    //         assign x_out[W-i-1] = AND_out[i];
    //     end
    // endgenerate

    assign x_out = bit_reverse(AND_out);

    function [W-1:0] bit_reverse;
        input [W-1:0] in;
        integer k;
        begin
            for (k = 0; k < W; k = k + 1)
                bit_reverse[k] = in[W-1-k];
        end
    endfunction


    integer i;

    always @(*) begin
        index_out = 0;
        for(i = 0; i < W; i = i + 1) begin
            if (x_in[i])
                index_out = i;
        end
    end

endmodule

rtl/initial_approx.v
`timescale 1ns/1ps

module initial_approx #(parameter N = 8, parameter W = 16) (
    input clk,
    input [W-1:0] a_in,
    // output [W-1:0] approx_out
    output reg [W-1:0] approx_out
);

    wire [W-1:0] lod_out;
    wire [$clog2(W)-1:0] lod_index;
    reg [W-1:0] approx_raw;
    integer i;

    LOD #(W) lod_inst (
        .x_in(a_in),
        .x_out(lod_out),
        .index_out(lod_index)
    );

    always @(*) begin
        approx_raw = 0;

        for (i = 0; i < W; i = i + 1) begin
            if (lod_out[i]) begin
                if (i & 1) begin
                    // ODD j
                    approx_raw[N - ((i+1)>>1)] = 1'b1;
                end else begin
                    // EVEN j
                    approx_raw[N - (i>>1) - 1] = 1'b1;
                    approx_raw[N - (i>>1) - 2] = 1'b1;
                end
            end
        end
    end

    always @(posedge clk) begin
        approx_out <= approx_raw << (N >> 1);
    end
endmodule

rtl/top_InvSqrt.v
`timescale 1ns/1ps

module top_InvSqrt #(
    parameter N = 8, 
    parameter W = 16,
    parameter N_ITERS = 3
)(
    input clk,
    input rst,
    input [W-1:0] a_in,
    output [W-1:0] result
);

    wire [W-1:0] generated_x0;
    reg [W-1:0] a_delayed;

    // 1. Generate the initial guess automatically
    initial_approx #(N, W) approx_unit (
        .clk(clk),
        .a_in(a_in),
        .approx_out(generated_x0)
    );

    // 2. Delay 'a_in' by 1 cycle to match approx_out's register delay
    always @(posedge clk) begin
        if (rst) 
            a_delayed <= 0;
        else     
            a_delayed <= a_in;
    end

    // 3. Feed the generated x0 and delayed 'a' into the NR pipeline
    top_pipelined #(N, W, N_ITERS) nr_pipeline (
        .clk(clk),
        .rst(rst),
        .x0(generated_x0),
        .a_in(a_delayed),
        .result(result)
    );

endmodule

sim/tb_InvSqrt.v
`timescale 1ns/1ps

module tb_InvSqrt;

    parameter N = 16;
    parameter W = 32;
    parameter N_ITERS = 4;
    // Total Latency: 1 (Approx) + (3 * N_ITERS) (Pipeline)
    localparam TOTAL_LATENCY = 1 + (N_ITERS * 3);
    localparam inputs_count = 200;
    reg clk, rst;
    reg [W-1:0] a_in;
    wire [W-1:0] result;
    reg [W-1:0] a_history [0:TOTAL_LATENCY + 1];

    reg [W-1:0] golden_mem [0:inputs_count - 1];
    reg [W-1:0] input_mem [0:inputs_count-1];
    integer out_ptr = 0;
    integer inp_file,golden_out_file, r, i;


    initial begin
        inp_file = $fopen("NR_inputs.txt", "r");
        for (i = 0; i < inputs_count; i = i + 1) begin
            r = $fscanf(inp_file, "%d\n", input_mem[i]);
        end
        $fclose(inp_file);

    end
    
    initial begin
        // golden_out_file = $fopen("NR_values.txt", "r");
        golden_out_file = $fopen("NR_golden_values.txt", "r");
        for (i = 0; i < inputs_count; i = i + 1) begin
            r = $fscanf(golden_out_file, "%d\n", golden_mem[i]);
        end
        $fclose(golden_out_file);
    end


    initial clk = 0;
    always #5 clk = ~clk;

    // Instantiate the full integrated module
    top_InvSqrt #(N, W, N_ITERS) dut (
        .clk(clk), .rst(rst), .a_in(a_in), .result(result)
    );
    
	integer j, k;
    always @(posedge clk) begin
        a_history[0] <= a_in;
        for (j = 1; j <= TOTAL_LATENCY + 1; j = j + 1) begin
            a_history[j] <= a_history[j-1];
        end
    end

    initial begin
        // --- Initialization ---
        rst = 1; a_in = 0;
        repeat(10) @(posedge clk);
        rst = 0;
        @(posedge clk);

        // --- Test Stream ---
        for (k = 0; k < inputs_count; k = k + 1) begin
            @(posedge clk); 
            a_in <= input_mem[k];
        end

        // --- End of Stream ---
        @(posedge clk); a_in <= 0;
        
        repeat (20) @(posedge clk);
        $display("Testbench complete.");
        $finish;
    end

    integer count_0;
    integer diff;

	initial begin
		out_ptr = 0;
        wait (rst == 0);
        count_0 = 0;
        repeat (TOTAL_LATENCY + 2) @(posedge clk); 
        
        forever begin
            @(posedge clk);
            if (out_ptr < inputs_count) begin
                diff = (result > golden_mem[out_ptr]) ? 
                    (result - golden_mem[out_ptr]) : 
                    (golden_mem[out_ptr] - result);

                if (diff == 0)
                    count_0 = count_0 + 1;
    
                $display("Time: %t | Input A: %d | Result: %d | Golden: %d | Diff: %d | Exact Match: %d out of %d", 
                        $time, 
                        a_history[TOTAL_LATENCY-1],
                        result, 
                        golden_mem[out_ptr], 
                        diff,
                        count_0,
                        inputs_count
                    );
                out_ptr = out_ptr + 1;
            end
        end
    end


    initial begin
        $dumpfile("top.vcd");
        $dumpvars(0, tb_InvSqrt);
    end
endmodule

out/vcd/top.vcd
$date
	Wed Apr 29 11:21:25 2026
$end
$version
	Icarus Verilog
$end
$timescale
	1ps
$end
$scope module tb_InvSqrt $end
$var wire 32 ! result [31:0] $end
$var reg 32 " a_in [31:0] $end
$var reg 1 # clk $end
$var reg 1 $ rst $end
$var integer 32 % count_0 [31:0] $end
$var integer 32 & diff [31:0] $end
$var integer 32 ' golden_out_file [31:0] $end
$var integer 32 ( i [31:0] $end
$var integer 32 ) inp_file [31:0] $end
$var integer 32 * j [31:0] $end
$var integer 32 + k [31:0] $end
$var integer 32 , out_ptr [31:0] $end
$var integer 32 - r [31:0] $end
$scope module dut $end
$var wire 32 . a_in [31:0] $end
$var wire 1 # clk $end
$var wire 1 $ rst $end
$var wire 32 / result [31:0] $end
$var wire 32 0 generated_x0 [31:0] $end
$var reg 32 1 a_delayed [31:0] $end
$scope module approx_unit $end
$var wire 32 2 a_in [31:0] $end
$var wire 1 # clk $end
$var wire 32 3 lod_out [31:0] $end
$var wire 5 4 lod_index [4:0] $end
$var reg 32 5 approx_out [31:0] $end
$var reg 32 6 approx_raw [31:0] $end
$var integer 32 7 i [31:0] $end
$scope module lod_inst $end
$var wire 32 8 AND_out [31:0] $end
$var wire 32 9 NOT_out [31:0] $end
$var wire 32 : x_in [31:0] $end
$var wire 32 ; x_out [31:0] $end
$var wire 32 < adder_out [31:0] $end
$var wire 32 = BR_x [31:0] $end
$var reg 5 > index_out [4:0] $end
$var integer 32 ? i [31:0] $end
$scope function bit_reverse $end
$var reg 32 @ in [31:0] $end
$var integer 32 A k [31:0] $end
$upscope $end
$upscope $end
$upscope $end
$scope module nr_pipeline $end
$var wire 32 B a_in [31:0] $end
$var wire 1 # clk $end
$var wire 32 C result [31:0] $end
$var wire 1 $ rst $end
$var wire 32 D x0 [31:0] $end
$scope begin NR_ITER[0] $end
$var reg 32 E a_d1 [31:0] $end
$var reg 32 F a_d2 [31:0] $end
$var reg 32 G a_d3 [31:0] $end
$scope module stage_inst $end
$var wire 32 H a_in [31:0] $end
$var wire 1 # clk $end
$var wire 1 $ rst $end
$var wire 32 I x_in [31:0] $end
$var wire 32 J x_out [31:0] $end
$var wire 32 K x_sq_scaled [31:0] $end
$var wire 64 L x_sq_full [63:0] $end
$var wire 32 M term_full [31:0] $end
$var wire 32 N mult_scaled [31:0] $end
$var wire 64 O mult_full [63:0] $end
$var wire 64 P ax2_full [63:0] $end
$var reg 32 Q a_reg1 [31:0] $end
$var reg 32 R term_reg2 [31:0] $end
$var reg 32 S x_final_reg [31:0] $end
$var reg 32 T x_reg1 [31:0] $end
$var reg 32 U x_reg2 [31:0] $end
$var reg 32 V x_sq_reg1 [31:0] $end
$upscope $end
$upscope $end
$scope begin NR_ITER[1] $end
$var reg 32 W a_d1 [31:0] $end
$var reg 32 X a_d2 [31:0] $end
$var reg 32 Y a_d3 [31:0] $end
$scope module stage_inst $end
$var wire 32 Z a_in [31:0] $end
$var wire 1 # clk $end
$var wire 1 $ rst $end
$var wire 32 [ x_in [31:0] $end
$var wire 32 \ x_out [31:0] $end
$var wire 32 ] x_sq_scaled [31:0] $end
$var wire 64 ^ x_sq_full [63:0] $end
$var wire 32 _ term_full [31:0] $end
$var wire 32 ` mult_scaled [31:0] $end
$var wire 64 a mult_full [63:0] $end
$var wire 64 b ax2_full [63:0] $end
$var reg 32 c a_reg1 [31:0] $end
$var reg 32 d term_reg2 [31:0] $end
$var reg 32 e x_final_reg [31:0] $end
$var reg 32 f x_reg1 [31:0] $end
$var reg 32 g x_reg2 [31:0] $end
$var reg 32 h x_sq_reg1 [31:0] $end
$upscope $end
$upscope $end
$scope begin NR_ITER[2] $end
$var reg 32 i a_d1 [31:0] $end
$var reg 32 j a_d2 [31:0] $end
$var reg 32 k a_d3 [31:0] $end
$scope module stage_inst $end
$var wire 32 l a_in [31:0] $end
$var wire 1 # clk $end
$var wire 1 $ rst $end
$var wire 32 m x_in [31:0] $end
$var wire 32 n x_out [31:0] $end
$var wire 32 o x_sq_scaled [31:0] $end
$var wire 64 p x_sq_full [63:0] $end
$var wire 32 q term_full [31:0] $end
$var wire 32 r mult_scaled [31:0] $end
$var wire 64 s mult_full [63:0] $end
$var wire 64 t ax2_full [63:0] $end
$var reg 32 u a_reg1 [31:0] $end
$var reg 32 v term_reg2 [31:0] $end
$var reg 32 w x_final_reg [31:0] $end
$var reg 32 x x_reg1 [31:0] $end
$var reg 32 y x_reg2 [31:0] $end
$var reg 32 z x_sq_reg1 [31:0] $end
$upscope $end
$upscope $end
$scope begin NR_ITER[3] $end
$var reg 32 { a_d1 [31:0] $end
$var reg 32 | a_d2 [31:0] $end
$var reg 32 } a_d3 [31:0] $end
$scope module stage_inst $end
$var wire 32 ~ a_in [31:0] $end
$var wire 1 # clk $end
$var wire 1 $ rst $end
$var wire 32 !" x_in [31:0] $end
$var wire 32 "" x_out [31:0] $end
$var wire 32 #" x_sq_scaled [31:0] $end
$var wire 64 $" x_sq_full [63:0] $end
$var wire 32 %" term_full [31:0] $end
$var wire 32 &" mult_scaled [31:0] $end
$var wire 64 '" mult_full [63:0] $end
$var wire 64 (" ax2_full [63:0] $end
$var reg 32 )" a_reg1 [31:0] $end
$var reg 32 *" term_reg2 [31:0] $end
$var reg 32 +" x_final_reg [31:0] $end
$var reg 32 ," x_reg1 [31:0] $end
$var reg 32 -" x_reg2 [31:0] $end
$var reg 32 ." x_sq_reg1 [31:0] $end
$upscope $end
$upscope $end
$upscope $end
$upscope $end
$upscope $end
$enddefinitions $end
#0
$dumpvars
bx ."
bx -"
bx ,"
bx +"
bx *"
bx )"
bx ("
bx '"
bx &"
bx %"
bx $"
bx #"
bx ""
bx !"
bx ~
bx }
bx |
bx {
bx z
bx y
bx x
bx w
bx v
bx u
bx t
bx s
bx r
bx q
bx p
bx o
bx n
bx m
bx l
bx k
bx j
bx i
bx h
bx g
bx f
bx e
bx d
bx c
bx b
bx a
bx `
bx _
bx ^
bx ]
bx \
bx [
bx Z
bx Y
bx X
bx W
bx V
bx U
bx T
bx S
bx R
bx Q
bx P
bx O
bx N
bx M
bx L
bx K
bx J
bx I
bx H
bx G
bx F
bx E
bx D
bx C
bx B
b100000 A
b0 @
b100000 ?
b0 >
b0 =
b0 <
b0 ;
b0 :
b11111111111111111111111111111111 9
b0 8
b100000 7
b0 6
bx 5
b0 4
b0 3
b0 2
bx 1
bx 0
bx /
b0 .
b1 -
b0 ,
bx +
bx *
b10000000000000000000000000000011 )
b11001000 (
b10000000000000000000000000000011 '
bx &
bx %
1$
0#
b0 "
bx !
$end
#5000
b0 K
b110000000000000000 M
b0 N
b0 ]
b110000000000000000 _
b0 `
b0 o
b110000000000000000 q
b0 r
b0 #"
b110000000000000000 %"
b0 &"
b0 L
b0 I
b0 0
b0 5
b0 D
b0 P
b0 V
b0 Q
b0 T
b0 O
b0 R
b0 U
b0 ^
b0 J
b0 S
b0 [
b0 Z
b0 G
b0 F
b0 E
b0 b
b0 h
b0 c
b0 f
b0 a
b0 d
b0 g
b0 p
b0 \
b0 e
b0 m
b0 l
b0 Y
b0 X
b0 W
b0 t
b0 z
b0 u
b0 x
b0 s
b0 v
b0 y
b0 $"
b0 n
b0 w
b0 !"
b0 ~
b0 k
b0 j
b0 i
b0 ("
b0 ."
b0 )"
b0 ,"
b0 '"
b0 *"
b0 -"
b0 !
b0 /
b0 C
b0 ""
b0 +"
b0 }
b0 |
b0 {
b0 H
b0 1
b0 B
b1111 *
1#
#10000
0#
#15000
b1111 *
1#
#20000
0#
#25000
b1111 *
1#
#30000
0#
#35000
b1111 *
1#
#40000
0#
#45000
b1111 *
1#
#50000
0#
#55000
b1111 *
1#
#60000
0#
#65000
b1111 *
1#
#70000
0#
#75000
b1111 *
1#
#80000
0#
#85000
b1111 *
1#
#90000
0#
#95000
b0 %
0$
b1111 *
1#
#100000
0#
#105000
b110000000000000000 R
b110000000000000000 d
b110000000000000000 v
b110000000000000000 *"
b1111 *
b0 +
1#
#110000
0#
#115000
b100000000 6
b100000 7
b1000000000000000 3
b1000000000000000 ;
b10000000000000000 8
b10011101111100010000000000000000 <
b10011101111100001111111111111111 9
b1111 4
b1111 >
b100000 ?
b1100010000011110000000000000000 =
b100000 A
b10000000000000000 @
b1111000001000110 "
b1111000001000110 .
b1111000001000110 2
b1111000001000110 :
b1 +
b1111 *
1#
#120000
0#
#125000
b100000 7
b1000000000 6
b10000000000000 3
b10000000000000 ;
b10000000000000000 K
b1000000000000000000 8
b100111000001000000000000000000 <
b100111000000111111111111111111 9
b100000 ?
b1101 4
b1101 >
b11011000111111000000000000000000 =
b100000 A
b1000000000000000000 @
b100000000000000000000000000000000 L
b10000000000000000 I
b10000000000000000 0
b10000000000000000 5
b10000000000000000 D
b1111000001000110 H
b1111000001000110 1
b1111000001000110 B
b11111100011011 "
b11111100011011 .
b11111100011011 2
b11111100011011 :
b1111 *
b10 +
1#
#130000
0#
#135000
b100000 7
b100000000 6
b1000000000000000 3
b1000000000000000 ;
b10000000000000000 8
b10001010100110010000000000000000 <
b10001010100110001111111111111111 9
b100000111110111010 M
b1000000000000000000 K
b100000 ?
b1111 4
b1111 >
b1110101011001110000000000000000 =
b100000 A
b10000000000000000 @
b1110011010101110 "
b1110011010101110 .
b1110011010101110 2
b1110011010101110 :
b11111100011011 H
b11111100011011 1
b11111100011011 B
b1111000001000110 E
b11110000010001100000000000000000 P
b10000000000000000 V
b1111000001000110 Q
b10000000000000000 T
b10000000000000000000000000000000000 L
b100000000000000000 I
b100000000000000000 0
b100000000000000000 5
b100000000000000000 D
b11 +
b1111 *
1#
#140000
0#
#145000
b10000000000000000 K
b100000001110010100 M
b10000011111011101 N
b11010011001101010000000000000000 <
b11010011001101001111111111111111 9
b100000 ?
b1111 4
b1111 >
b101100110010110000000000000000 =
b100000 A
b1101001100110100 @
b100000000000000000000000000000000 L
b10000000000000000 I
b10000000000000000 0
b10000000000000000 5
b10000000000000000 D
b1000000000000000000 V
b11111100011011000000000000000000 P
b11111100011011 Q
b100000000000000000 T
b100000111110111010 R
b1000001111101110100000000000000000 O
b10000000000000000 U
b1111000001000110 F
b11111100011011 E
b1110011010101110 H
b1110011010101110 1
b1110011010101110 B
b1101001100110100 "
b1101001100110100 .
b1101001100110100 2
b1101001100110100 :
b1111 *
b100 +
1#
#150000
0#
#155000
b100000 7
b110000000 6
b100000000000000 3
b100000000000000 ;
b100000000000000000 8
b11111011100000000000000000 <
b11111011011111111111111111 9
b10000111111111000 ]
b100000001110010100 N
b100001100101010010 M
b100000 ?
b1110 4
b1110 >
b11111100000100100000000000000000 =
b100000 A
b100000000000000000 @
b100100000111111 "
b100100000111111 .
b100100000111111 2
b100100000111111 :
b1101001100110100 H
b1101001100110100 1
b1101001100110100 B
b1111000001000110 Z
b1111000001000110 G
b11111100011011 F
b1110011010101110 E
b100001111111101111101010011001001 ^
b10000011111011101 J
b10000011111011101 S
b10000011111011101 [
b100000001110010100 R
b10000000111001010000000000000000000 O
b100000000000000000 U
b10000000000000000 V
b11100110101011100000000000000000 P
b1110011010101110 Q
b10000000000000000 T
b101 +
b1111 *
1#
#160000
0#
#165000
b100000 7
b100000000 6
b1000000000000000 3
b1000000000000000 ;
b100100000000000000 K
b100010110011001100 M
b10000110010101001 N
b1000000111001011101 ]
b100000000010111110 _
b10000000000000000 8
b1111010101000010000000000000000 <
b1111010101000001111111111111111 9
b100000 ?
b1111 4
b1111 >
b10000101010111110000000000000000 =
b100000 A
b10000000000000000 @
b1001000000000000000000000000000000 L
b11000000000000000 I
b11000000000000000 0
b11000000000000000 5
b11000000000000000 D
b11010011001101000000000000000000 P
b1101001100110100 Q
b100001100101010010 R
b1000011001010100100000000000000000 O
b10000000000000000 U
b10000001110010111001100110110010000 ^
b100000001110010100 J
b100000001110010100 S
b100000001110010100 [
b11111100011011 Z
b11111100011011 G
b1110011010101110 F
b1101001100110100 E
b11111111010000101101110111010000 b
b10000111111111000 h
b1111000001000110 c
b10000011111011101 f
b1111000001000110 W
b100100000111111 H
b100100000111111 1
b100100000111111 B
b1111101010100001 "
b1111101010100001 .
b1111101010100001 2
b1111101010100001 :
b1111 *
b110 +
1#
#170000
0#
#175000
b100000 7
b1100000000 6
b1000000000000 3
b1000000000000 ;
b10000000000000000000 8
b10010000101110000000000000000000 <
b10010000101101111111111111111111 9
b10000100000111111 `
b100000000000001010 _
b10001100111110010 ]
b10001011001100110 N
b100101110101110011 M
b10000000000000000 K
b100000 ?
b1100 4
b1100 >
b1101111010010000000000000000000 =
b100000 A
b10000000000000000000 @
b1001011110110 "
b1001011110110 .
b1001011110110 2
b1001011110110 :
b1111101010100001 H
b1111101010100001 1
b1111101010100001 B
b1111000001000110 X
b11111100011011 W
b100000000010111110 d
b1000010000011111011101011000000110 a
b10000011111011101 g
b1000000111001011101 h
b11111111111101100110011011001111 b
b11111100011011 c
b100000001110010100 f
b1110011010101110 Z
b1110011010101110 G
b1101001100110100 F
b100100000111111 E
b100011001111100100100011110010001 ^
b10000110010101001 J
b10000110010101001 S
b10000110010101001 [
b1000101100110011000000000000000000 O
b100010110011001100 R
b100100000000000000 V
b10100010100011011100000000000000 P
b100100000111111 Q
b11000000000000000 T
b100000000000000000000000000000000 L
b10000000000000000 I
b10000000000000000 0
b10000000000000000 5
b10000000000000000 D
b111 +
b1111 *
1#
#180000
0#
#185000
b100000 7
b100000000 6
b1000000000000000 3
b1000000000000000 ;
b10010000000000000000 K
b100000010101011111 M
b11100011000010110 N
b10010111011000010 ]
b100000000111110001 _
b100000001110011110 `
b10001000011000010 o
b10000000000000000 8
b1110001101010000000000000000 <
b1110001101001111111111111111 9
b100000 ?
b1111 4
b1111 >
b11110001110010110000000000000000 =
b100000 A
b10000000000000000 @
b100100000000000000000000000000000000 L
b110000000000000000 I
b110000000000000000 0
b110000000000000000 5
b110000000000000000 D
b10000000000000000 V
b11111010101000010000000000000000 P
b1111101010100001 Q
b10000000000000000 T
b100101110101110011 R
b1110001100001011001000000000000000 O
b11000000000000000 U
b100101110110000011011000010100100 ^
b10001011001100110 J
b10001011001100110 S
b10001011001100110 [
b1101001100110100 Z
b1101001100110100 G
b100100000111111 F
b1111101010100001 E
b10001100111110010 h
b11111110000011110000111001111100 b
b1110011010101110 c
b10000110010101001 f
b100000000000001010 d
b10000000111001111000010001111001000 a
b100000001110010100 g
b100010000110000011111111110000001 p
b10000100000111111 \
b10000100000111111 e
b10000100000111111 m
b1111000001000110 l
b1111000001000110 Y
b11111100011011 X
b1110011010101110 W
b1001011110110 H
b1001011110110 1
b1001011110110 B
b1101001110001111 "
b1101001110001111 .
b1101001110001111 2
b1101001110001111 :
b1111 *
b1000 +
1#
#190000
0#
#195000
b100000 7
b110000000 6
b100000000000000 3
b100000000000000 ;
b100000000000000000 8
b101000101111100000000000000000 <
b101000101111011111111111111111 9
b100000000000000000 q
b1000000111010000101 o
b10000110110101110 `
b100000011000111001 _
b110010010101110010 ]
b10000001010110000 N
b100101010101011010 M
b10000000000000000 K
b100000 ?
b1110 4
b1110 >
b11010111010000100000000000000000 =
b100000 A
b100000000000000000 @
b100001011101011 "
b100001011101011 .
b100001011101011 2
b100001011101011 :
b1101001110001111 H
b1101001110001111 1
b1101001110001111 B
b1111000001000110 i
b100000000000000000111010100001100 t
b10001000011000010 z
b1111000001000110 u
b10000100000111111 x
b11111100011011 l
b11111100011011 Y
b1110011010101110 X
b1101001100110100 W
b10000001110100001010001010110000100 p
b100000001110011110 \
b100000001110011110 e
b100000001110011110 m
b100000000111110001 d
b1000011011010110111001010000011001 a
b10000110010101001 g
b10010111011000010 h
b11111001110001110110010101101000 b
b1101001100110100 c
b10001011001100110 f
b100100000111111 Z
b100100000111111 G
b1111101010100001 F
b1001011110110 E
b1100100101011100100000100111100100 ^
b11100011000010110 J
b11100011000010110 S
b11100011000010110 [
b100000010101011111 R
b1000000101010111110000000000000000 O
b10000000000000000 U
b10010000000000000000 V
b10101010101001100000000000000000 P
b1001011110110 Q
b110000000000000000 T
b100000000000000000000000000000000 L
b10000000000000000 I
b10000000000000000 0
b10000000000000000 5
b10000000000000000 D
b1001 +
b1111 *
1#
#200000
0#
#205000
b100000 7
b100000000 6
b1000000000000000 3
b1000000000000000 ;
b100100000000000000 K
b100010110001110001 M
b111000000000000111 N
b10000010101100111 ]
b100001110010110010 _
b10001100111001000 `
b10001110000010111 o
b10000100000111111 r
b10000000000000000 8
b10001100001101010000000000000000 <
b10001100001101001111111111111111 9
b100000 ?
b1111 4
b1111 >
b1110011110010110000000000000000 =
b100000 A
b10000000000000000 @
b1001000000000000000000000000000000 L
b11000000000000000 I
b11000000000000000 0
b11000000000000000 5
b11000000000000000 D
b10000000000000000 V
b11010011100011110000000000000000 P
b1101001110001111 Q
b10000000000000000 T
b100101010101011010 R
b11100000000000011100000000000000000 O
b110000000000000000 U
b100000101011001110011100100000000 ^
b10000001010110000 J
b10000001010110000 S
b10000001010110000 [
b1111101010100001 Z
b1111101010100001 G
b1001011110110 F
b1101001110001111 E
b110010010101110010 h
b11100011010011100100011100001110 b
b100100000111111 c
b11100011000010110 f
b100000011000111001 d
b1000110011100100000110000010110110 a
b10001011001100110 g
b100011100000101110010001001000100 p
b10000110110101110 \
b10000110110101110 e
b10000110110101110 m
b1110011010101110 l
b1110011010101110 Y
b1101001100110100 X
b100100000111111 W
b1000000111010000101 z
b100000000000000000100001100000111 t
b11111100011011 u
b100000001110011110 x
b100000000000000000 v
b1000010000011111100000000000000000 s
b10000100000111111 y
b1111000001000110 j
b11111100011011 i
b100001011101011 H
b100001011101011 1
b100001011101011 B
b1101001111001110 "
b1101001111001110 .
b1101001111001110 2
b1101001111001110 :
b1111 *
b1010 +
1#
#210000
0#
#215000
b100000 7
b110000000 6
b100000000000000 3
b100000000000000 ;
b100000000000000000 8
b110101100101100000000000000000 <
b110101100101011111111111111111 9
b10001000011000010 #"
b100000001110011110 r
b100000000000000011 q
b10011011000101001 o
b11101111110001001 `
b100000000000010110 _
b11000100000000110001 ]
b10001011000111001 N
b100110100101110000 M
b10000000000000000 K
b100000 ?
b1110 4
b1110 >
b11001010011010100000000000000000 =
b100000 A
b100000000000000000 @
b101011001010011 "
b101011001010011 .
b101011001010011 2
b101011001010011 :
b1101001111001110 H
b1101001111001110 1
b1101001111001110 B
b1111000001000110 ~
b1111000001000110 k
b11111100011011 j
b1110011010101110 i
b100010000110000011111111110000001 $"
b10000100000111111 n
b10000100000111111 w
b10000100000111111 !"
b10000000111001111000000000000000000 s
b100000001110011110 y
b10001110000010111 z
b11111111111111011100000110100010 t
b1110011010101110 u
b10000110110101110 x
b1101001100110100 l
b1101001100110100 Y
b100100000111111 X
b1111101010100001 W
b100110110001010001010110001000000 p
b10001100111001000 \
b10001100111001000 e
b10001100111001000 m
b100001110010110010 d
b1110111111000100100010001101001100 a
b11100011000010110 g
b10000010101100111 h
b11111111111010101111101111000111 b
b1111101010100001 c
b10000001010110000 f
b1001011110110 Z
b1001011110110 G
b1101001110001111 F
b100001011101011 E
b110001000000001100010000000000110001 ^
b111000000000000111 J
b111000000000000111 S
b111000000000000111 [
b100010110001110001 R
b1000101100011100010000000000000000 O
b10000000000000000 U
b100100000000000000 V
b10010110100100001100000000000000 P
b100001011101011 Q
b11000000000000000 T
b100000000000000000000000000000000 L
b10000000000000000 I
b10000000000000000 0
b10000000000000000 5
b10000000000000000 D
b1011 +
b1111 *
1#
#220000
0#
#225000
b100100000000000000 K
b100010110000110010 M
b11100111100010100 N
b10010111001100000 ]
b100001011110110111 _
b10000001010111011 `
b111000001001000010 o
b100000000000011110 q
b10000110110110000 r
b1000000111010000101 #"
b100000000000000000 %"
b10001111110110100000000000000000 <
b10001111110110011111111111111111 9
b100000 ?
b1110 4
b1110 >
b1110000001001100000000000000000 =
b100000 A
b110010000001110 @
b1001000000000000000000000000000000 L
b11000000000000000 I
b11000000000000000 0
b11000000000000000 5
b11000000000000000 D
b10000000000000000 V
b11010011110011100000000000000000 P
b1101001111001110 Q
b10000000000000000 T
b100110100101110000 R
b1110011110001010000000000000000000 O
b11000000000000000 U
b100101110010111111101100010110001 ^
b10001011000111001 J
b10001011000111001 S
b10001011000111001 [
b1101001110001111 Z
b1101001110001111 G
b100001011101011 F
b1101001111001110 E
b11000100000000110001 h
b11101000010010010010000100010110 b
b1001011110110 c
b111000000000000111 f
b100000000000010110 d
b1000000101011101100011101100100000 a
b10000001010110000 g
b1110000010010000011111011101010001 p
b11101111110001001 \
b11101111110001001 e
b11101111110001001 m
b100100000111111 l
b100100000111111 Y
b1111101010100001 X
b1001011110110 W
b10011011000101001 z
b11111111111000101100101101010100 t
b1101001100110100 u
b10001100111001000 x
b100000000000000011 v
b1000011011010111110010100100001010 s
b10000110110101110 y
b10000001110100001010001010110000100 $"
b100000001110011110 n
b100000001110011110 w
b100000001110011110 !"
b11111100011011 ~
b11111100011011 k
b1110011010101110 j
b1101001100110100 i
b100000000000000000111010100001100 ("
b10001000011000010 ."
b1111000001000110 )"
b10000100000111111 ,"
b1111000001000110 {
b101011001010011 H
b101011001010011 1
b101011001010011 B
b110010000001110 "
b110010000001110 .
b110010000001110 2
b110010000001110 :
b1111 *
b1100 +
1#
#230000
0#
