rtl/NR_stage_pipeline.v
`timescale 1ns/1ps

module NR_stage_pipeline #(parameter N = 8, parameter W = 16)(
    input  clk, rst,
    input [W-1:0] x_in,
    input [W-1:0] a_in,
    output [W-1:0] x_out
);
    // Stage 1: x^2 (QN.N * QN.N = Q2N.2N -> QN.N after truncation)
    reg [W-1:0] x_reg1, a_reg1, x_sq_reg1;
    wire [(2*W)-1:0] x_sq_full = x_in * x_in;
    wire [W-1:0] x_sq_scaled = (x_sq_full + (1 << (N-1))) >> N; // truncate at x^2 and final multiplication stage to maintain accuracy

    always @(posedge clk) begin
        if (rst) begin
            x_reg1 <= 0; a_reg1 <= 0; x_sq_reg1 <= 0;
        end else begin
            x_reg1 <= x_in;
            a_reg1 <= a_in;
            x_sq_reg1 <= x_sq_scaled;
        end
    end

    // Stage 2: (3 - a*x^2)
    reg [W-1:0] x_reg2, term_reg2;
    wire [(2*W)-1:0] ax2_full = a_reg1 * x_sq_reg1;
    // wire [W-1:0] term_full = (3 << N) - ((ax2_full + (1 << (N-1))) >> N);        // truncation everywhere made converging for large number slower
    wire [W-1:0] term_full = (3 << N) - ((ax2_full) >> N);

    always @(posedge clk) begin
        if (rst) begin
            x_reg2 <= 0; term_reg2 <= 0;
        end else begin
            x_reg2 <= x_reg1;
            term_reg2 <= term_full;
        end
    end

    // Stage 3: (x * term) / 2
    reg [W-1:0] x_final_reg;
    wire [(2*W)-1:0] mult_full = x_reg2 * term_reg2;
    wire [W-1:0] mult_scaled = (mult_full + (1 << (N))) >> (N + 1);

    always @(posedge clk) begin
        if (rst) x_final_reg <= 0;
        else begin
            x_final_reg <= mult_scaled;
        end
    end

    assign x_out = x_final_reg;
endmodule

rtl/top_pipelined.v
`timescale 1ns/1ps

module top_pipelined #(
    parameter N = 8, 
    parameter W = 16,
    parameter N_ITERS = 3
)(
    input clk,
    input rst,
    input [W-1:0] x0,
    input [W-1:0] a_in,
    output [W-1:0] result
);

    wire [W-1:0] x_bus [0:N_ITERS];
    wire [W-1:0] a_pipe [0:N_ITERS];

    assign x_bus[0] = x0;
    assign a_pipe[0] = a_in;

    genvar i;
    generate
        for (i = 0; i < N_ITERS; i = i + 1) begin : NR_ITER
            NR_stage_pipeline #(N, W) stage_inst (
                .clk(clk), .rst(rst),
                .x_in(x_bus[i]), .a_in(a_pipe[i]),
                .x_out(x_bus[i+1])
            );
            reg [W-1:0] a_d1, a_d2, a_d3;

            always @(posedge clk) begin
                if (rst) begin
                    a_d1 <= 0;
                    a_d2 <= 0;
                    a_d3 <= 0;
                end else begin
                    a_d1 <= a_pipe[i];
                    a_d2 <= a_d1;
                    a_d3 <= a_d2;
                end
            end

            assign a_pipe[i+1] = a_d3;
            // assign a_pipe[i+1] = d3;
        end
    endgenerate
    assign result = x_bus[N_ITERS];
endmodule

rtl/LOD.v
`timescale 1ns/1ps

module LOD #(parameter W = 16)(
    input  [W-1:0] x_in,
    output [W-1:0] x_out,
    output reg [$clog2(W)-1:0] index_out
);

    wire [W-1:0] BR_x;
    wire [W-1:0] NOT_out;
    wire [W-1:0] adder_out;
    wire [W-1:0] AND_out;

    // step 1: bit reversal of x_in
    // genvar i;
    // generate
    //     for(i = 0; i < W; i = i+1) begin
    //         assign BR_x[W-i-1] = x_in[i];
    //     end
    // endgenerate

    assign BR_x = bit_reverse(x_in); 

    // step 2: NOT of BR_x
    assign NOT_out = ~BR_x;

    // step 3: 2's complement = NOT + 1
    assign adder_out = NOT_out + 1;

    // step 4: AND between BR_x and its 2's complement
    assign AND_out = BR_x & adder_out;

    // step 5: bit reverse AND_out to get LOD(x_in)
    // generate
    //     for(i = 0; i < W; i = i+1) begin
    //         assign x_out[W-i-1] = AND_out[i];
    //     end
    // endgenerate

    assign x_out = bit_reverse(AND_out);

    function [W-1:0] bit_reverse;
        input [W-1:0] in;
        integer k;
        begin
            for (k = 0; k < W; k = k + 1)
                bit_reverse[k] = in[W-1-k];
        end
    endfunction


    integer i;

    always @(*) begin
        index_out = 0;
        for(i = 0; i < W; i = i + 1) begin
            if (x_in[i])
                index_out = i;
        end
    end

endmodule

rtl/initial_approx.v
`timescale 1ns/1ps

module initial_approx #(parameter N = 8, parameter W = 16) (
    input clk,
    input [W-1:0] a_in,
    // output [W-1:0] approx_out
    output reg [W-1:0] approx_out
);

    wire [W-1:0] lod_out;
    wire [$clog2(W)-1:0] lod_index;
    reg [W-1:0] approx_raw;
    integer i;

    LOD #(W) lod_inst (
        .x_in(a_in),
        .x_out(lod_out),
        .index_out(lod_index)
    );

    always @(*) begin
        approx_raw = 0;

        for (i = 0; i < W; i = i + 1) begin
            if (lod_out[i]) begin
                if (i | 1'b0) begin
                    // ODD j
                    approx_raw[N - ((i+1)>>1)] = 1'b1;
                end else begin
                    // EVEN j
                    approx_raw[N - (i>>1) - 1] = 1'b1;
                    approx_raw[N - (i>>1) - 2] = 1'b1;
                end
            end
        end
    end

    always @(posedge clk) begin
        approx_out <= approx_raw << (N >> 1);
    end
endmodule

rtl/top_InvSqrt.v
`timescale 1ns/1ps

module top_InvSqrt #(
    parameter N = 8, 
    parameter W = 16,
    parameter N_ITERS = 3
)(
    input clk,
    input rst,
    input [W-1:0] a_in,
    output [W-1:0] result
);

    wire [W-1:0] generated_x0;
    reg [W-1:0] a_delayed;

    // 1. Generate the initial guess automatically
    initial_approx #(N, W) approx_unit (
        .clk(clk),
        .a_in(a_in),
        .approx_out(generated_x0)
    );

    // 2. Delay 'a_in' by 1 cycle to match approx_out's register delay
    always @(posedge clk) begin
        if (rst) 
            a_delayed <= 0;
        else     
            a_delayed <= a_in;
    end

    // 3. Feed the generated x0 and delayed 'a' into the NR pipeline
    top_pipelined #(N, W, N_ITERS) nr_pipeline (
        .clk(clk),
        .rst(rst),
        .x0(generated_x0),
        .a_in(a_delayed),
        .result(result)
    );

endmodule

sim/tb_InvSqrt.v
`timescale 1ns/1ps

module tb_InvSqrt;

    parameter N = 16;
    parameter W = 32;
    parameter N_ITERS = 4;
    // Total Latency: 1 (Approx) + (3 * N_ITERS) (Pipeline)
    localparam TOTAL_LATENCY = 1 + (N_ITERS * 3);
    localparam inputs_count = 200;
    reg clk, rst;
    reg [W-1:0] a_in;
    wire [W-1:0] result;
    reg [W-1:0] a_history [0:TOTAL_LATENCY + 1];

    reg [W-1:0] golden_mem [0:inputs_count - 1];
    reg [W-1:0] input_mem [0:inputs_count-1];
    integer out_ptr = 0;
    integer inp_file,golden_out_file, r, i;


    initial begin
        inp_file = $fopen("NR_inputs.txt", "r");
        for (i = 0; i < inputs_count; i = i + 1) begin
            r = $fscanf(inp_file, "%d\n", input_mem[i]);
        end
        $fclose(inp_file);

    end
    
    initial begin
        // golden_out_file = $fopen("NR_values.txt", "r");
        golden_out_file = $fopen("NR_golden_values.txt", "r");
        for (i = 0; i < inputs_count; i = i + 1) begin
            r = $fscanf(golden_out_file, "%d\n", golden_mem[i]);
        end
        $fclose(golden_out_file);
    end


    initial clk = 0;
    always #5 clk = ~clk;

    // Instantiate the full integrated module
    top_InvSqrt #(N, W, N_ITERS) dut (
        .clk(clk), .rst(rst), .a_in(a_in), .result(result)
    );
    
	integer j, k;
    always @(posedge clk) begin
        a_history[0] <= a_in;
        for (j = 1; j <= TOTAL_LATENCY + 1; j = j + 1) begin
            a_history[j] <= a_history[j-1];
        end
    end

    initial begin
        // --- Initialization ---
        rst = 1; a_in = 0;
        repeat(10) @(posedge clk);
        rst = 0;
        @(posedge clk);

        // --- Test Stream ---
        for (k = 0; k < inputs_count; k = k + 1) begin
            @(posedge clk); 
            a_in <= input_mem[k];
        end

        // --- End of Stream ---
        @(posedge clk); a_in <= 0;
        
        repeat (20) @(posedge clk);
        $display("Testbench complete.");
        $finish;
    end

    integer count_0;
    integer diff;

	initial begin
		out_ptr = 0;
        wait (rst == 0);
        count_0 = 0;
        repeat (TOTAL_LATENCY + 2) @(posedge clk); 
        
        forever begin
            @(posedge clk);
            if (out_ptr < inputs_count) begin
                diff = (result > golden_mem[out_ptr]) ? 
                    (result - golden_mem[out_ptr]) : 
                    (golden_mem[out_ptr] - result);

                if (diff == 0)
                    count_0 = count_0 + 1;
    
                $display("Time: %t | Input A: %d | Result: %d | Golden: %d | Diff: %d | Exact Match: %d out of %d", 
                        $time, 
                        a_history[TOTAL_LATENCY-1],
                        result, 
                        golden_mem[out_ptr], 
                        diff,
                        count_0,
                        inputs_count
                    );
                out_ptr = out_ptr + 1;
            end
        end
    end


    initial begin
        $dumpfile("top.vcd");
        $dumpvars(0, tb_InvSqrt);
    end
endmodule

out/vcd/top.vcd
$date
	Sat May 16 11:14:24 2026
$end
$version
	Icarus Verilog
$end
$timescale
	1ps
$end
$scope module tb_InvSqrt $end
$var wire 32 ! result [31:0] $end
$var reg 32 " a_in [31:0] $end
$var reg 1 # clk $end
$var reg 1 $ rst $end
$var integer 32 % count_0 [31:0] $end
$var integer 32 & diff [31:0] $end
$var integer 32 ' golden_out_file [31:0] $end
$var integer 32 ( i [31:0] $end
$var integer 32 ) inp_file [31:0] $end
$var integer 32 * j [31:0] $end
$var integer 32 + k [31:0] $end
$var integer 32 , out_ptr [31:0] $end
$var integer 32 - r [31:0] $end
$scope module dut $end
$var wire 32 . a_in [31:0] $end
$var wire 1 # clk $end
$var wire 1 $ rst $end
$var wire 32 / result [31:0] $end
$var wire 32 0 generated_x0 [31:0] $end
$var reg 32 1 a_delayed [31:0] $end
$scope module approx_unit $end
$var wire 32 2 a_in [31:0] $end
$var wire 1 # clk $end
$var wire 32 3 lod_out [31:0] $end
$var wire 5 4 lod_index [4:0] $end
$var reg 32 5 approx_out [31:0] $end
$var reg 32 6 approx_raw [31:0] $end
$var integer 32 7 i [31:0] $end
$scope module lod_inst $end
$var wire 32 8 AND_out [31:0] $end
$var wire 32 9 NOT_out [31:0] $end
$var wire 32 : x_in [31:0] $end
$var wire 32 ; x_out [31:0] $end
$var wire 32 < adder_out [31:0] $end
$var wire 32 = BR_x [31:0] $end
$var reg 5 > index_out [4:0] $end
$var integer 32 ? i [31:0] $end
$scope function bit_reverse $end
$var reg 32 @ in [31:0] $end
$var integer 32 A k [31:0] $end
$upscope $end
$upscope $end
$upscope $end
$scope module nr_pipeline $end
$var wire 32 B a_in [31:0] $end
$var wire 1 # clk $end
$var wire 32 C result [31:0] $end
$var wire 1 $ rst $end
$var wire 32 D x0 [31:0] $end
$scope begin NR_ITER[0] $end
$var reg 32 E a_d1 [31:0] $end
$var reg 32 F a_d2 [31:0] $end
$var reg 32 G a_d3 [31:0] $end
$scope module stage_inst $end
$var wire 32 H a_in [31:0] $end
$var wire 1 # clk $end
$var wire 1 $ rst $end
$var wire 32 I x_in [31:0] $end
$var wire 32 J x_out [31:0] $end
$var wire 32 K x_sq_scaled [31:0] $end
$var wire 64 L x_sq_full [63:0] $end
$var wire 32 M term_full [31:0] $end
$var wire 32 N mult_scaled [31:0] $end
$var wire 64 O mult_full [63:0] $end
$var wire 64 P ax2_full [63:0] $end
$var reg 32 Q a_reg1 [31:0] $end
$var reg 32 R term_reg2 [31:0] $end
$var reg 32 S x_final_reg [31:0] $end
$var reg 32 T x_reg1 [31:0] $end
$var reg 32 U x_reg2 [31:0] $end
$var reg 32 V x_sq_reg1 [31:0] $end
$upscope $end
$upscope $end
$scope begin NR_ITER[1] $end
$var reg 32 W a_d1 [31:0] $end
$var reg 32 X a_d2 [31:0] $end
$var reg 32 Y a_d3 [31:0] $end
$scope module stage_inst $end
$var wire 32 Z a_in [31:0] $end
$var wire 1 # clk $end
$var wire 1 $ rst $end
$var wire 32 [ x_in [31:0] $end
$var wire 32 \ x_out [31:0] $end
$var wire 32 ] x_sq_scaled [31:0] $end
$var wire 64 ^ x_sq_full [63:0] $end
$var wire 32 _ term_full [31:0] $end
$var wire 32 ` mult_scaled [31:0] $end
$var wire 64 a mult_full [63:0] $end
$var wire 64 b ax2_full [63:0] $end
$var reg 32 c a_reg1 [31:0] $end
$var reg 32 d term_reg2 [31:0] $end
$var reg 32 e x_final_reg [31:0] $end
$var reg 32 f x_reg1 [31:0] $end
$var reg 32 g x_reg2 [31:0] $end
$var reg 32 h x_sq_reg1 [31:0] $end
$upscope $end
$upscope $end
$scope begin NR_ITER[2] $end
$var reg 32 i a_d1 [31:0] $end
$var reg 32 j a_d2 [31:0] $end
$var reg 32 k a_d3 [31:0] $end
$scope module stage_inst $end
$var wire 32 l a_in [31:0] $end
$var wire 1 # clk $end
$var wire 1 $ rst $end
$var wire 32 m x_in [31:0] $end
$var wire 32 n x_out [31:0] $end
$var wire 32 o x_sq_scaled [31:0] $end
$var wire 64 p x_sq_full [63:0] $end
$var wire 32 q term_full [31:0] $end
$var wire 32 r mult_scaled [31:0] $end
$var wire 64 s mult_full [63:0] $end
$var wire 64 t ax2_full [63:0] $end
$var reg 32 u a_reg1 [31:0] $end
$var reg 32 v term_reg2 [31:0] $end
$var reg 32 w x_final_reg [31:0] $end
$var reg 32 x x_reg1 [31:0] $end
$var reg 32 y x_reg2 [31:0] $end
$var reg 32 z x_sq_reg1 [31:0] $end
$upscope $end
$upscope $end
$scope begin NR_ITER[3] $end
$var reg 32 { a_d1 [31:0] $end
$var reg 32 | a_d2 [31:0] $end
$var reg 32 } a_d3 [31:0] $end
$scope module stage_inst $end
$var wire 32 ~ a_in [31:0] $end
$var wire 1 # clk $end
$var wire 1 $ rst $end
$var wire 32 !" x_in [31:0] $end
$var wire 32 "" x_out [31:0] $end
$var wire 32 #" x_sq_scaled [31:0] $end
$var wire 64 $" x_sq_full [63:0] $end
$var wire 32 %" term_full [31:0] $end
$var wire 32 &" mult_scaled [31:0] $end
$var wire 64 '" mult_full [63:0] $end
$var wire 64 (" ax2_full [63:0] $end
$var reg 32 )" a_reg1 [31:0] $end
$var reg 32 *" term_reg2 [31:0] $end
$var reg 32 +" x_final_reg [31:0] $end
$var reg 32 ," x_reg1 [31:0] $end
$var reg 32 -" x_reg2 [31:0] $end
$var reg 32 ." x_sq_reg1 [31:0] $end
$upscope $end
$upscope $end
$upscope $end
$upscope $end
$upscope $end
$enddefinitions $end
#0
$dumpvars
bx ."
bx -"
bx ,"
bx +"
bx *"
bx )"
bx ("
bx '"
bx &"
bx %"
bx $"
bx #"
bx ""
bx !"
bx ~
bx }
bx |
bx {
bx z
bx y
bx x
bx w
bx v
bx u
bx t
bx s
bx r
bx q
bx p
bx o
bx n
bx m
bx l
bx k
bx j
bx i
bx h
bx g
bx f
bx e
bx d
bx c
bx b
bx a
bx `
bx _
bx ^
bx ]
bx \
bx [
bx Z
bx Y
bx X
bx W
bx V
bx U
bx T
bx S
bx R
bx Q
bx P
bx O
bx N
bx M
bx L
bx K
bx J
bx I
bx H
bx G
bx F
bx E
bx D
bx C
bx B
b100000 A
b0 @
b100000 ?
b0 >
b0 =
b0 <
b0 ;
b0 :
b11111111111111111111111111111111 9
b0 8
b100000 7
b0 6
bx 5
b0 4
b0 3
b0 2
bx 1
bx 0
bx /
b0 .
b1 -
b0 ,
bx +
bx *
b10000000000000000000000000000011 )
b11001000 (
b10000000000000000000000000000011 '
bx &
bx %
1$
0#
b0 "
bx !
$end
#5000
b0 K
b110000000000000000 M
b0 N
b0 ]
b110000000000000000 _
b0 `
b0 o
b110000000000000000 q
b0 r
b0 #"
b110000000000000000 %"
b0 &"
b0 L
b0 I
b0 0
b0 5
b0 D
b0 P
b0 V
b0 Q
b0 T
b0 O
b0 R
b0 U
b0 ^
b0 J
b0 S
b0 [
b0 Z
b0 G
b0 F
b0 E
b0 b
b0 h
b0 c
b0 f
b0 a
b0 d
b0 g
b0 p
b0 \
b0 e
b0 m
b0 l
b0 Y
b0 X
b0 W
b0 t
b0 z
b0 u
b0 x
b0 s
b0 v
b0 y
b0 $"
b0 n
b0 w
b0 !"
b0 ~
b0 k
b0 j
b0 i
b0 ("
b0 ."
b0 )"
b0 ,"
b0 '"
b0 *"
b0 -"
b0 !
b0 /
b0 C
b0 ""
b0 +"
b0 }
b0 |
b0 {
b0 H
b0 1
b0 B
b1111 *
1#
#10000
0#
#15000
b1111 *
1#
#20000
0#
#25000
b1111 *
1#
#30000
0#
#35000
b1111 *
1#
#40000
0#
#45000
b1111 *
1#
#50000
0#
#55000
b1111 *
1#
#60000
0#
#65000
b1111 *
1#
#70000
0#
#75000
b1111 *
1#
#80000
0#
#85000
b1111 *
1#
#90000
0#
#95000
b0 %
0$
b1111 *
1#
#100000
0#
#105000
b110000000000000000 R
b110000000000000000 d
b110000000000000000 v
b110000000000000000 *"
b1111 *
b0 +
1#
#110000
0#
#115000
b1100000000000000 6
b100000 7
b1 3
b1 ;
b10000000000000000000000000000000 8
b10000000000000000000000000000000 <
b1111111111111111111111111111111 9
b100000 ?
b10000000000000000000000000000000 =
b100000 A
b10000000000000000000000000000000 @
b1 "
b1 .
b1 2
b1 :
b1 +
b1111 *
1#
#120000
0#
#125000
b100000 7
b1000000000000000 6
b10 3
b10 ;
b10010000000000000000000000000000 K
b1000000000000000000000000000000 8
b11000000000000000000000000000000 <
b10111111111111111111111111111111 9
b1 4
b1 >
b100000 ?
b1000000000000000000000000000000 =
b100000 A
b1000000000000000000000000000000 @
b100100000000000000000000000000000000000000000000 L
b110000000000000000000000 I
b110000000000000000000000 0
b110000000000000000000000 5
b110000000000000000000000 D
b1 H
b1 1
b1 B
b10 "
b10 .
b10 2
b10 :
b1111 *
b10 +
1#
#130000
0#
#135000
b100000 7
b110000000000000 6
b100 3
b100 ;
b100000000000000000000000000000 8
b11100000000000000000000000000000 <
b11011111111111111111111111111111 9
b100111000000000000 M
b1000000000000000000000000000000 K
b100000 ?
b10 4
b10 >
b100000000000000000000000000000 =
b100000 A
b100000000000000000000000000000 @
b100 "
b100 .
b100 2
b100 :
b10 H
b10 1
b10 B
b1 E
b10010000000000000000000000000000 P
b10010000000000000000000000000000 V
b1 Q
b110000000000000000000000 T
b10000000000000000000000000000000000000000000000 L
b100000000000000000000000 I
b100000000000000000000000 0
b100000000000000000000000 5
b100000000000000000000000 D
b11 +
b1111 *
1#
#140000
0#
#145000
b100000 7
b100000000000000 6
b1000 3
b1000 ;
b100100000000000000000000000000 K
b101000000000000000 M
b111010100000000000000000 N
b10000000000000000000000000000 8
b11110000000000000000000000000000 <
b11101111111111111111111111111111 9
b100000 ?
b11 4
b11 >
b10000000000000000000000000000 =
b100000 A
b10000000000000000000000000000 @
b1001000000000000000000000000000000000000000000 L
b11000000000000000000000 I
b11000000000000000000000 0
b11000000000000000000000 5
b11000000000000000000000 D
b1000000000000000000000000000000 V
b10000000000000000000000000000000 P
b10 Q
b100000000000000000000000 T
b100111000000000000 R
b11101010000000000000000000000000000000000 O
b110000000000000000000000 U
b1 F
b10 E
b100 H
b100 1
b100 B
b1000 "
b1000 .
b1000 2
b1000 :
b1111 *
b100 +
1#
#150000
0#
#155000
b100000 7
b11000000000000 6
b10000 3
b10000 ;
b1000000000000000000000000000 8
b11111000000000000000000000000000 <
b11110111111111111111111111111111 9
b11010101111001000000000000000000 ]
b101000000000000000000000 N
b100111000000000000 M
b10000000000000000000000000000 K
b100000 ?
b100 4
b100 >
b1000000000000000000000000000 =
b100000 A
b1000000000000000000000000000 @
b10000 "
b10000 .
b10000 2
b10000 :
b1000 H
b1000 1
b1000 B
b1 Z
b1 G
b10 F
b100 E
b110101011110010000000000000000000000000000000000 ^
b111010100000000000000000 J
b111010100000000000000000 S
b111010100000000000000000 [
b101000000000000000 R
b10100000000000000000000000000000000000000 O
b100000000000000000000000 U
b100100000000000000000000000000 V
b10010000000000000000000000000000 P
b100 Q
b11000000000000000000000 T
b100000000000000000000000000000000000000000000 L
b10000000000000000000000 I
b10000000000000000000000 0
b10000000000000000000000 5
b10000000000000000000000 D
b101 +
b1111 *
1#
#160000
0#
#165000
b100000 7
b10000000000000 6
b100000 3
b100000 ;
b1001000000000000000000000000 K
b101000000000000000 M
b11101010000000000000000 N
b1100100000000000000000000000000 ]
b100010101000011100 _
b100000000000000000000000000 8
b11111100000000000000000000000000 <
b11111011111111111111111111111111 9
b100000 ?
b101 4
b101 >
b100000000000000000000000000 =
b100000 A
b100000000000000000000000000 @
b10010000000000000000000000000000000000000000 L
b1100000000000000000000 I
b1100000000000000000000 0
b1100000000000000000000 5
b1100000000000000000000 D
b10000000000000000000000000000 V
b10000000000000000000000000000000 P
b1000 Q
b10000000000000000000000 T
b100111000000000000 R
b1110101000000000000000000000000000000000 O
b11000000000000000000000 U
b11001000000000000000000000000000000000000000000 ^
b101000000000000000000000 J
b101000000000000000000000 S
b101000000000000000000000 [
b10 Z
b10 G
b100 F
b1000 E
b11010101111001000000000000000000 b
b11010101111001000000000000000000 h
b1 c
b111010100000000000000000 f
b1 W
b10000 H
b10000 1
b10000 B
b100000 "
b100000 .
b100000 2
b100000 :
b1111 *
b110 +
1#
#170000
0#
#175000
b10011100000000000000000000000000 <
b10011011111111111111111111111111 9
b111111010011111011001100 `
b100011100000000000 _
b110101011110010000000000000000 ]
b10100000000000000000000 N
b100111000000000000 M
b100000000000000000000000000 K
b100000 ?
b101 4
b101 >
b1100100000000000000000000000000 =
b100000 A
b100110 @
b100110 "
b100110 .
b100110 2
b100110 :
b100000 H
b100000 1
b100000 B
b1 X
b10 W
b100010101000011100 d
b11111101001111101100110000000000000000000 a
b111010100000000000000000 g
b1100100000000000000000000000000 h
b11001000000000000000000000000000 b
b10 c
b101000000000000000000000 f
b100 Z
b100 G
b1000 F
b10000 E
b1101010111100100000000000000000000000000000000 ^
b11101010000000000000000 J
b11101010000000000000000 S
b11101010000000000000000 [
b101000000000000000 R
b1010000000000000000000000000000000000000 O
b10000000000000000000000 U
b1001000000000000000000000000 V
b10010000000000000000000000000000 P
b10000 Q
b1100000000000000000000 T
b1000000000000000000000000000000000000000000 L
b1000000000000000000000 I
b1000000000000000000000 0
b1000000000000000000000 5
b1000000000000000000000 D
b111 +
b1111 *
1#
#180000
0#
#185000
b100000 7
b1100000000000 6
b1000000 3
b1000000 ;
b101000000000000000 M
b1110101000000000000000 N
b11001000000000000000000000000 ]
b100010101000011100 _
b101100011000000000000000 `
b11111010100001010010111010011111 o
b10000000000000000000000000 8
b11111110000000000000000000000000 <
b11111101111111111111111111111111 9
b100000 ?
b110 4
b110 >
b10000000000000000000000000 =
b100000 A
b10000000000000000000000000 @
b100000000000000000000000000 V
b10000000000000000000000000000000 P
b100000 Q
b1000000000000000000000 T
b100111000000000000 R
b111010100000000000000000000000000000000 O
b1100000000000000000000 U
b110010000000000000000000000000000000000000000 ^
b10100000000000000000000 J
b10100000000000000000000 S
b10100000000000000000000 [
b1000 Z
b1000 G
b10000 F
b100000 E
b110101011110010000000000000000 h
b11010101111001000000000000000000 b
b100 c
b11101010000000000000000 f
b100011100000000000 d
b10110001100000000000000000000000000000000 a
b101000000000000000000000 g
b111110101000010100101110100111110111001010010000 p
b111111010011111011001100 \
b111111010011111011001100 e
b111111010011111011001100 m
b1 l
b1 Y
b10 X
b100 W
b100110 H
b100110 1
b100110 B
b1000000 "
b1000000 .
b1000000 2
b1000000 :
b1111 *
b1000 +
1#
#190000
0#
#195000
b100000 7
b1000000000000 6
b10000000 3
b10000000 ;
b1000000000000000000000000 8
b11111111000000000000000000000000 <
b11111110111111111111111111111111 9
b100000010101111011 q
b1111011000100100100000000000000 o
b11111101001111101100110 `
b100011100000000000 _
b1101010111100100000000000000 ]
b1010000000000000000000 N
b100110100000000000 M
b10010000000000000000000000 K
b100000 ?
b111 4
b111 >
b1000000000000000000000000 =
b100000 A
b1000000000000000000000000 @
b10000000 "
b10000000 .
b10000000 2
b10000000 :
b1000000 H
b1000000 1
b1000000 B
b1 i
b11111010100001010010111010011111 t
b11111010100001010010111010011111 z
b1 u
b111111010011111011001100 x
b10 l
b10 Y
b100 X
b1000 W
b11110110001001001000000000000000000000000000000 p
b101100011000000000000000 \
b101100011000000000000000 e
b101100011000000000000000 m
b100010101000011100 d
b1111110100111110110011000000000000000000 a
b11101010000000000000000 g
b11001000000000000000000000000 h
b11001000000000000000000000000000 b
b1000 c
b10100000000000000000000 f
b10000 Z
b10000 G
b100000 F
b100110 E
b11010101111001000000000000000000000000000000 ^
b1110101000000000000000 J
b1110101000000000000000 S
b1110101000000000000000 [
b101000000000000000 R
b101000000000000000000000000000000000000 O
b1000000000000000000000 U
b10011000000000000000000000000000 P
b100110 Q
b100100000000000000000000000000000000000000 L
b110000000000000000000 I
b110000000000000000000 0
b110000000000000000000 5
b110000000000000000000 D
b1001 +
b1111 *
1#
#200000
0#
#205000
b1000000000000000000000000 K
b100111000000000000 M
b1001101000000000000000 N
b110010000000000000000000000 ]
b100010101000011100 _
b10110001100000000000000 `
b111110101000010100101110101000 o
b100000100111011100 q
b111111111111010011000000 r
b101101000000000000000000000000 <
b101100111111111111111111111111 9
b100000 ?
b111 4
b111 >
b11010011000000000000000000000000 =
b100000 A
b11001011 @
b10000000000000000000000000000000000000000 L
b100000000000000000000 I
b100000000000000000000 0
b100000000000000000000 5
b100000000000000000000 D
b10010000000000000000000000 V
b10010000000000000000000000000000 P
b1000000 Q
b110000000000000000000 T
b100110100000000000000000000000000000000 O
b100110100000000000 R
b1100100000000000000000000000000000000000000 ^
b1010000000000000000000 J
b1010000000000000000000 S
b1010000000000000000000 [
b100000 Z
b100000 G
b100110 F
b1000000 E
b1101010111100100000000000000 h
b11010101111001000000000000000000 b
b10000 c
b1110101000000000000000 f
b100011100000000000 d
b1011000110000000000000000000000000000000 a
b10100000000000000000000 g
b1111101010000101001011101001111101110010100100 p
b11111101001111101100110 \
b11111101001111101100110 e
b11111101001111101100110 m
b100 l
b100 Y
b1000 X
b10000 W
b1111011000100100100000000000000 z
b11110110001001001000000000000000 t
b10 u
b101100011000000000000000 x
b100000010101111011 v
b11111111111101001011111110010100000000100 s
b111111010011111011001100 y
b1 j
b10 i
b10000000 H
b10000000 1
b10000000 B
b11001011 "
b11001011 .
b11001011 2
b11001011 :
b1111 *
b1010 +
1#
#210000
0#
#215000
b10111001000000000000000000000000 <
b10111000111111111111111111111111 9
b11111111111010011000000001111111 #"
b101101001110101100000101 r
b100000010101111011 q
b11110110001001001000000000000 o
b1111110100111110110011 `
b100011100000000000 _
b101110010100100000000000000 ]
b111010100000000000000 N
b101000000000000000 M
b100000 ?
b111 4
b111 >
b1000111000000000000000000000000 =
b100000 A
b11100010 @
b11100010 "
b11100010 .
b11100010 2
b11100010 :
b11001011 H
b11001011 1
b11001011 B
b1 ~
b1 k
b10 j
b100 i
b111111111110100110000000011111101001000000000000 $"
b111111111111010011000000 n
b111111111111010011000000 w
b111111111111010011000000 !"
b100000100111011100 v
b10110100111010110000010100000000000000000 s
b101100011000000000000000 y
b111110101000010100101110101000 z
b11111010100001010010111010100000 t
b100 u
b11111101001111101100110 x
b1000 l
b1000 Y
b10000 X
b100000 W
b111101100010010010000000000000000000000000000 p
b10110001100000000000000 \
b10110001100000000000000 e
b10110001100000000000000 m
b100010101000011100 d
b111111010011111011001100000000000000000 a
b1110101000000000000000 g
b110010000000000000000000000 h
b11001000000000000000000000000000 b
b100000 c
b1010000000000000000000 f
b100110 Z
b100110 G
b1000000 F
b10000000 E
b1011100101001000000000000000000000000000000 ^
b1001101000000000000000 J
b1001101000000000000000 S
b1001101000000000000000 [
b100111000000000000 R
b11101010000000000000000000000000000000 O
b110000000000000000000 U
b1000000000000000000000000 V
b10000000000000000000000000000000 P
b10000000 Q
b100000000000000000000 T
b1011 +
b1111 *
1#
#220000
0#
#225000
b100000 7
b110000000000 6
b100000000 3
b100000000 ;
b100011010100000000 M
b101000000000000000000 N
b11010101111001000000000000 ]
b100010001111111011 _
b1011000110000000000000 `
b1111101010000101001011101010 o
b100000100111011100 q
b11111111111101001100000 r
b1111111110110110101011011001010 #"
b100000000000010111 %"
b100000000000000000000000 8
b11111111100000000000000000000000 <
b11111111011111111111111111111111 9
b100000 ?
b1000 4
b1000 >
b100000000000000000000000 =
b100000 A
b100000000000000000000000 @
b11001011000000000000000000000000 P
b11001011 Q
b101000000000000000 R
b10100000000000000000000000000000000000 O
b100000000000000000000 U
b110101011110010000000000000000000000000000 ^
b111010100000000000000 J
b111010100000000000000 S
b111010100000000000000 [
b1000000 Z
b1000000 G
b10000000 F
b11001011 E
b101110010100100000000000000 h
b11011100000001011000000000000000 b
b100110 c
b1001101000000000000000 f
b100011100000000000 d
b101100011000000000000000000000000000000 a
b1010000000000000000000 g
b11111010100001010010111010011111011100101001 p
b1111110100111110110011 \
b1111110100111110110011 e
b1111110100111110110011 m
b10000 l
b10000 Y
b100000 X
b100110 W
b11110110001001001000000000000 z
b11110110001001001000000000000000 t
b1000 u
b10110001100000000000000 x
b100000010101111011 v
b1111111111110100101111111001010000000010 s
b11111101001111101100110 y
b11111111101101101010110110010100010111000011001 $"
b101101001110101100000101 n
b101101001110101100000101 w
b101101001110101100000101 !"
b10 ~
b10 k
b100 j
b1000 i
b11111111111010011000000001111111 ("
b11111111111010011000000001111111 ."
b1 )"
b111111111111010011000000 ,"
b1 {
b11100010 H
b11100010 1
b11100010 B
b100000000 "
b100000000 .
b100000000 2
b100000000 :
b1111 *
b1100 +
1#
#230000
0#
