rtl/NR_stage_pipeline.v
`timescale 1ns/1ps

module NR_stage_pipeline #(parameter N = 8, parameter W = 16)(
    input  clk, rst,
    input [W-1:0] x_in,
    input [W-1:0] a_in,
    output [W-1:0] x_out
);
    // Stage 1: x^2 (Q8.8 * Q8.8 = Q16.16)
    reg [W-1:0] x_reg1, a_reg1, x_sq_reg1;
    wire [(2*W)-1:0] x_sq_full = x_in * x_in;

    always @(posedge clk) begin
        if (rst) begin
            x_reg1 <= 0; a_reg1 <= 0; x_sq_reg1 <= 0;
        end else begin
            x_reg1 <= x_in;
            a_reg1 <= a_in;
            x_sq_reg1 <= x_sq_full >>> N;
        end
    end

    // Stage 2: (3 - a*x^2)
    reg [W-1:0] x_reg2, term_reg2;
    wire [(2*W)-1:0] ax2_full = a_reg1 * x_sq_reg1;

    always @(posedge clk) begin
        if (rst) begin
            x_reg2 <= 0; term_reg2 <= 0;
        end else begin
            x_reg2 <= x_reg1;
            term_reg2 <= (3 << N) - (ax2_full >>> N);
        end
    end

    // Stage 3: (x * term) / 2
    reg [W-1:0] x_final_reg;
    wire [(2*W)-1:0] mult_full = x_reg2 * term_reg2;

    always @(posedge clk) begin
        if (rst) x_final_reg <= 0;
        else begin
            x_final_reg <= mult_full >>> (N + 1);
        end
    end

    assign x_out = x_final_reg;
endmodule

rtl/top_pipelined.v
`timescale 1ns/1ps

module top_pipelined #(
    parameter N = 8, 
    parameter W = 16,
    parameter N_ITERS = 3
)(
    input clk,
    input rst,
    input [W-1:0] x0,
    input [W-1:0] a_in,
    output [W-1:0] result
);

    wire [W-1:0] x_bus [0:N_ITERS];
    wire [W-1:0] a_pipe [0:N_ITERS];

    assign x_bus[0] = x0;
    assign a_pipe[0] = a_in;

    genvar i;
    generate
        for (i = 0; i < N_ITERS; i = i + 1) begin : NR_ITER
            NR_stage_pipeline #(N, W) stage_inst (
                .clk(clk), .rst(rst),
                .x_in(x_bus[i]), .a_in(a_pipe[i]),
                .x_out(x_bus[i+1])
            );
            reg [W-1:0] a_d1, a_d2, a_d3;

            always @(posedge clk) begin
                if (rst) begin
                    a_d1 <= 0;
                    a_d2 <= 0;
                    a_d3 <= 0;
                end else begin
                    a_d1 <= a_pipe[i];
                    a_d2 <= a_d1;
                    a_d3 <= a_d2;
                end
            end

            assign a_pipe[i+1] = a_d3;
            // assign a_pipe[i+1] = d3;
        end
    endgenerate
    assign result = x_bus[N_ITERS];
endmodule

rtl/LOD.v
`timescale 1ns/1ps

module LOD #(parameter W = 16)(
    input  [W-1:0] x_in,
    output [W-1:0] x_out
);

    wire [W-1:0] BR_x;
    wire [W-1:0] NOT_out;
    wire [W-1:0] adder_out;
    wire [W-1:0] AND_out;

    // step 1: bit reversal of x_in
    // genvar i;
    // generate
    //     for(i = 0; i < W; i = i+1) begin
    //         assign BR_x[W-i-1] = x_in[i];
    //     end
    // endgenerate

    assign BR_x = bit_reverse(x_in); 

    // step 2: NOT of BR_x
    assign NOT_out = ~BR_x;

    // step 3: 2's complement = NOT + 1
    assign adder_out = NOT_out + 1;

    // step 4: AND between BR_x and its 2's complement
    assign AND_out = BR_x & adder_out;

    // step 5: bit reverse AND_out to get LOD(x_in)
    // generate
    //     for(i = 0; i < W; i = i+1) begin
    //         assign x_out[W-i-1] = AND_out[i];
    //     end
    // endgenerate

    assign x_out = bit_reverse(AND_out);

    function [W-1:0] bit_reverse;
        input [W-1:0] in;
        integer k;
        begin
            for (k = 0; k < W; k = k + 1)
                bit_reverse[k] = in[W-1-k];
        end
    endfunction


    // integer i;
    // always @(*) begin
    //     x_out = 0;
    //     for(i = 0; i < W; i = i + 1) begin
    //         if (x_in[i])
    //             x_out = i;
    //     end
    // end

endmodule

rtl/initial_approx.v
`timescale 1ns/1ps

module initial_approx #(parameter N = 8, parameter W = 16) (
    input clk,
    input [W-1:0] a_in,
    // output [W-1:0] approx_out
    output reg [W-1:0] approx_out
);

    // integer j;
    // integer i;
    // integer shift;

    // wire [W-1:0] lod_out;

    // LOD #(W) lod_inst (
    //     .x_in(a_in),
    //     .x_out(lod_out)
    // );

    

    // always @(*) begin
    //     approx_out = 0;

    //     // extract index from one-hot
    //     j = 0;
    //     for (i = 0; i < W; i = i + 1) begin
    //         if (lod_out[i])
    //             j = i;
    //     end


    //     if (j[0]) begin
    //         // ODD
    //         if (j >= N) begin
    //             shift = (j - N + 1) >> 1;
    //             if ((N - shift) >= 0 && (N - shift) < W)
    //                 approx_out[N - shift] = 1'b1;
    //         end else begin
    //             shift = (N - j) >> 1;
    //             if ((N + shift) < W)
    //                 approx_out[N + shift] = 1'b1;
    //         end

    //     end 
    //     else begin
    //         // EVEN
    //         if (j >= N) begin
    //             shift = (j - N) >> 1;
    //             if ((N - (shift+1)) >= 0 && (N - (shift+1)) < W)
    //                 approx_out[N - (shift+1)] = 1'b1;

    //             if ((N - (shift+2)) >= 0 && (N - (shift+2)) < W)
    //                 approx_out[N - (shift+2)] = 1'b1;

    //         end else begin
    //             shift = (N - j) >> 1;
    //             if ((N + shift) < W)
    //                 approx_out[N + shift] = 1'b1;
    //         end
    //     end
    // end


    wire [W-1:0] lod_out;
    reg [W-1:0] approx_raw;
    integer i;

    LOD #(W) lod_inst (
        .x_in(a_in),
        .x_out(lod_out)
    );

    always @(*) begin
        approx_raw = 0;

        for (i = 0; i < W; i = i + 1) begin
            if (lod_out[i]) begin
                if (i % 2 == 1) begin
                    // ODD j
                    approx_raw[N - ((i+1)>>1)] = 1'b1;
                end else begin
                    // EVEN j
                    approx_raw[N - (i>>1) - 1] = 1'b1;
                    approx_raw[N - (i>>1) - 2] = 1'b1;
                end
            end
        end
    end

    always @(posedge clk) begin
        approx_out <= approx_raw << 4;
    end
endmodule

rtl/top_InvSqrt.v
`timescale 1ns/1ps

module top_InvSqrt #(
    parameter N = 8, 
    parameter W = 16,
    parameter N_ITERS = 3
)(
    input clk,
    input rst,
    input [W-1:0] a_in,
    output [W-1:0] result
);

    wire [W-1:0] generated_x0;
    reg [W-1:0] a_delayed;

    // 1. Generate the initial guess automatically
    initial_approx #(N, W) approx_unit (
        .clk(clk),
        .a_in(a_in),
        .approx_out(generated_x0)
    );

    // 2. Delay 'a_in' by 1 cycle to match approx_out's register delay
    always @(posedge clk) begin
        if (rst) 
            a_delayed <= 0;
        else     
            a_delayed <= a_in;
    end

    // 3. Feed the generated x0 and delayed 'a' into the NR pipeline
    top_pipelined #(N, W, N_ITERS) nr_pipeline (
        .clk(clk),
        .rst(rst),
        .x0(generated_x0),
        .a_in(a_delayed),
        .result(result)
    );

endmodule

sim/tb_InvSqrt.v
`timescale 1ns/1ps

module tb_InvSqrt;

    parameter N = 8;
    parameter W = 16;
    parameter N_ITERS = 3;
    // Total Latency: 1 (Approx) + (3 * N_ITERS) (Pipeline)
    localparam TOTAL_LATENCY = 1 + (N_ITERS * 3);
    localparam inputs_count = 33;
    reg clk, rst;
    reg [W-1:0] a_in;
    wire [W-1:0] result;

    reg [W-1:0] golden_mem [0:inputs_count - 1];
    integer out_ptr = 0;
    integer file, r, i;

    initial begin
        file = $fopen("NR_golden_values.txt", "r");
        for (i = 0; i < inputs_count; i = i + 1) begin
            r = $fscanf(file, "%d\n", golden_mem[i]);
        end
        $fclose(file);
    end

    reg [W-1:0] a_history [0:TOTAL_LATENCY + 2];

    initial clk = 0;
    always #5 clk = ~clk;

    // Instantiate the full integrated module
    top_InvSqrt #(N, W, N_ITERS) dut (
        .clk(clk), .rst(rst), .a_in(a_in), .result(result)
    );

    always @(posedge clk) begin
        a_history[0] <= a_in;
        for (integer j = 1; j <= TOTAL_LATENCY + 1; j = j + 1) begin
            a_history[j] <= a_history[j-1];
        end
    end

    initial begin
        // --- Initialization ---
        rst = 1; a_in = 0;
        repeat(10) @(posedge clk);
        rst = 0;
        @(posedge clk);

        // Boundary around 1.0 (Q8.8 transition)
        @(posedge clk); a_in <= 16'd254;
        @(posedge clk); a_in <= 16'd255;
        @(posedge clk); a_in <= 16'd256;
        @(posedge clk); a_in <= 16'd257;

        // Powers of 2
        @(posedge clk); a_in <= 16'd1;     
        @(posedge clk); a_in <= 16'd4;     
        @(posedge clk); a_in <= 16'd16;    
        @(posedge clk); a_in <= 16'd64;    
        @(posedge clk); a_in <= 16'd256;   
        @(posedge clk); a_in <= 16'd1024;  
        @(posedge clk); a_in <= 16'd4096;  
        @(posedge clk); a_in <= 16'd16384; 
        @(posedge clk); a_in <= 16'd32768; 

        // Perfect Squares (Easy verification)
        @(posedge clk); a_in <= 16'd576;   
        @(posedge clk); a_in <= 16'd2304;  
        @(posedge clk); a_in <= 16'd6400;  
        @(posedge clk); a_in <= 16'd16384; 
        @(posedge clk); a_in <= 16'd36864; 

        @(posedge clk); a_in <= 16'd511;   
        @(posedge clk); a_in <= 16'd512;   
        @(posedge clk); a_in <= 16'd513;   
        @(posedge clk); a_in <= 16'd2047;  
        @(posedge clk); a_in <= 16'd2048;  
        @(posedge clk); a_in <= 16'd2049;  

        @(posedge clk); a_in <= 16'hAAAA;  
        @(posedge clk); a_in <= 16'h5555;  
        @(posedge clk); a_in <= 16'd12345; 
        @(posedge clk); a_in <= 16'd54321; 
        @(posedge clk); a_in <= 16'd65535; 

        // Very Small Values
        @(posedge clk); a_in <= 16'd2;
        @(posedge clk); a_in <= 16'd3;
        @(posedge clk); a_in <= 16'd5;
        @(posedge clk); a_in <= 16'd7;

        // --- End of Stream ---
        @(posedge clk); a_in <= 0;
        
        // Wait for pipeline to empty (1 + 9 stages = 10 cycles total)
        repeat (20) @(posedge clk);
        $display("Testbench complete.");
        $finish;
    end

initial begin
        out_ptr = 0;
        
        wait (rst == 0);
        
        repeat (TOTAL_LATENCY + 2) @(posedge clk);
        
        forever begin
            @(posedge clk);
            if (out_ptr < inputs_count) begin
                $display("Time: %t | Input A: %d | Result: %d | Golden: %d | Diff: %d", 
                        $time, 
                        a_history[TOTAL_LATENCY-1], // This is a_history[9]
                        result, 
                        golden_mem[out_ptr], 
                        (result > golden_mem[out_ptr]) ? result - golden_mem[out_ptr] : golden_mem[out_ptr] - result
                );
                out_ptr = out_ptr + 1;
            end
        end
    end

    initial begin
        $dumpfile("top.vcd");
        $dumpvars(0, tb_InvSqrt);
    end
endmodule

out/vcd/top.vcd
$date
	Mon Apr  6 01:02:44 2026
$end
$version
	Icarus Verilog
$end
$timescale
	1ps
$end
$scope module tb_InvSqrt $end
$var wire 16 ! result [15:0] $end
$var reg 16 " a_in [15:0] $end
$var reg 1 # clk $end
$var reg 1 $ rst $end
$var integer 32 % file [31:0] $end
$var integer 32 & i [31:0] $end
$var integer 32 ' out_ptr [31:0] $end
$var integer 32 ( r [31:0] $end
$scope module dut $end
$var wire 16 ) a_in [15:0] $end
$var wire 1 # clk $end
$var wire 1 $ rst $end
$var wire 16 * result [15:0] $end
$var wire 16 + generated_x0 [15:0] $end
$var reg 16 , a_delayed [15:0] $end
$scope module approx_unit $end
$var wire 16 - a_in [15:0] $end
$var wire 1 # clk $end
$var wire 16 . lod_out [15:0] $end
$var reg 16 / approx_out [15:0] $end
$var reg 16 0 approx_raw [15:0] $end
$var integer 32 1 i [31:0] $end
$scope module lod_inst $end
$var wire 16 2 AND_out [15:0] $end
$var wire 16 3 NOT_out [15:0] $end
$var wire 16 4 x_in [15:0] $end
$var wire 16 5 x_out [15:0] $end
$var wire 16 6 adder_out [15:0] $end
$var wire 16 7 BR_x [15:0] $end
$scope function bit_reverse $end
$var reg 16 8 in [15:0] $end
$var integer 32 9 k [31:0] $end
$upscope $end
$upscope $end
$upscope $end
$scope module nr_pipeline $end
$var wire 16 : a_in [15:0] $end
$var wire 1 # clk $end
$var wire 16 ; result [15:0] $end
$var wire 1 $ rst $end
$var wire 16 < x0 [15:0] $end
$scope begin NR_ITER[0] $end
$var reg 16 = a_d1 [15:0] $end
$var reg 16 > a_d2 [15:0] $end
$var reg 16 ? a_d3 [15:0] $end
$scope module stage_inst $end
$var wire 16 @ a_in [15:0] $end
$var wire 1 # clk $end
$var wire 1 $ rst $end
$var wire 16 A x_in [15:0] $end
$var wire 16 B x_out [15:0] $end
$var wire 32 C x_sq_full [31:0] $end
$var wire 32 D mult_full [31:0] $end
$var wire 32 E ax2_full [31:0] $end
$var reg 16 F a_reg1 [15:0] $end
$var reg 16 G term_reg2 [15:0] $end
$var reg 16 H x_final_reg [15:0] $end
$var reg 16 I x_reg1 [15:0] $end
$var reg 16 J x_reg2 [15:0] $end
$var reg 16 K x_sq_reg1 [15:0] $end
$upscope $end
$upscope $end
$scope begin NR_ITER[1] $end
$var reg 16 L a_d1 [15:0] $end
$var reg 16 M a_d2 [15:0] $end
$var reg 16 N a_d3 [15:0] $end
$scope module stage_inst $end
$var wire 16 O a_in [15:0] $end
$var wire 1 # clk $end
$var wire 1 $ rst $end
$var wire 16 P x_in [15:0] $end
$var wire 16 Q x_out [15:0] $end
$var wire 32 R x_sq_full [31:0] $end
$var wire 32 S mult_full [31:0] $end
$var wire 32 T ax2_full [31:0] $end
$var reg 16 U a_reg1 [15:0] $end
$var reg 16 V term_reg2 [15:0] $end
$var reg 16 W x_final_reg [15:0] $end
$var reg 16 X x_reg1 [15:0] $end
$var reg 16 Y x_reg2 [15:0] $end
$var reg 16 Z x_sq_reg1 [15:0] $end
$upscope $end
$upscope $end
$scope begin NR_ITER[2] $end
$var reg 16 [ a_d1 [15:0] $end
$var reg 16 \ a_d2 [15:0] $end
$var reg 16 ] a_d3 [15:0] $end
$scope module stage_inst $end
$var wire 16 ^ a_in [15:0] $end
$var wire 1 # clk $end
$var wire 1 $ rst $end
$var wire 16 _ x_in [15:0] $end
$var wire 16 ` x_out [15:0] $end
$var wire 32 a x_sq_full [31:0] $end
$var wire 32 b mult_full [31:0] $end
$var wire 32 c ax2_full [31:0] $end
$var reg 16 d a_reg1 [15:0] $end
$var reg 16 e term_reg2 [15:0] $end
$var reg 16 f x_final_reg [15:0] $end
$var reg 16 g x_reg1 [15:0] $end
$var reg 16 h x_reg2 [15:0] $end
$var reg 16 i x_sq_reg1 [15:0] $end
$upscope $end
$upscope $end
$upscope $end
$upscope $end
$scope begin $ivl_for_loop0 $end
$var integer 32 j j [31:0] $end
$upscope $end
$upscope $end
$enddefinitions $end
#0
$dumpvars
bx j
bx i
bx h
bx g
bx f
bx e
bx d
bx c
bx b
bx a
bx `
bx _
bx ^
bx ]
bx \
bx [
bx Z
bx Y
bx X
bx W
bx V
bx U
bx T
bx S
bx R
bx Q
bx P
bx O
bx N
bx M
bx L
bx K
bx J
bx I
bx H
bx G
bx F
bx E
bx D
bx C
bx B
bx A
bx @
bx ?
bx >
bx =
bx <
bx ;
bx :
b10000 9
b0 8
b0 7
b0 6
b0 5
b0 4
b1111111111111111 3
b0 2
b10000 1
b0 0
bx /
b0 .
b0 -
bx ,
bx +
bx *
b0 )
b1 (
b0 '
b100001 &
b10000000000000000000000000000011 %
1$
0#
b0 "
bx !
$end
#5000
b0 C
b0 A
b0 +
b0 /
b0 <
b0 E
b0 K
b0 F
b0 I
b0 D
b0 G
b0 J
b0 R
b0 B
b0 H
b0 P
b0 O
b0 ?
b0 >
b0 =
b0 T
b0 Z
b0 U
b0 X
b0 S
b0 V
b0 Y
b0 a
b0 Q
b0 W
b0 _
b0 ^
b0 N
b0 M
b0 L
b0 c
b0 i
b0 d
b0 g
b0 b
b0 e
b0 h
b0 !
b0 *
b0 ;
b0 `
b0 f
b0 ]
b0 \
b0 [
b0 @
b0 ,
b0 :
b1100 j
1#
#10000
0#
#15000
b1100 j
1#
#20000
0#
#25000
b1100 j
1#
#30000
0#
#35000
b1100 j
1#
#40000
0#
#45000
b1100 j
1#
#50000
0#
#55000
b1100 j
1#
#60000
0#
#65000
b1100 j
1#
#70000
0#
#75000
b1100 j
1#
#80000
0#
#85000
b1100 j
1#
#90000
0#
#95000
b1100 j
0$
1#
#100000
0#
#105000
b1100000000 G
b1100000000 V
b1100000000 e
b1100 j
1#
#110000
0#
#115000
b10000 0
b10000 1
b10000000 .
b10000000 5
b100000000 2
b1000000100000000 6
b1000000011111111 3
b111111100000000 7
b10000 9
b100000000 8
b11111110 "
b11111110 )
b11111110 -
b11111110 4
b1100 j
1#
#120000
0#
#125000
b100000000 6
b11111111 3
b1111111100000000 7
b10000 9
b11111111 8
b10000000000000000 C
b100000000 A
b100000000 +
b100000000 /
b100000000 <
b11111110 @
b11111110 ,
b11111110 :
b11111111 "
b11111111 )
b11111111 -
b11111111 4
b1100 j
1#
#130000
0#
#135000
b10000 1
b1100 0
b100000000 .
b100000000 5
b10000000 2
b1111111110000000 6
b1111111101111111 3
b10000000 7
b10000 9
b10000000 8
b100000000 "
b100000000 )
b100000000 -
b100000000 4
b11111111 @
b11111111 ,
b11111111 :
b11111110 =
b1111111000000000 E
b100000000 K
b11111110 F
b100000000 I
b1100 j
1#
#140000
0#
#145000
b111111110000000 6
b111111101111111 3
b1000000010000000 7
b10000 9
b100000001 8
b1001000000000000 C
b11000000 A
b11000000 +
b11000000 /
b11000000 <
b1111111100000000 E
b11111111 F
b1000000010 G
b100000001000000000 D
b100000000 J
b11111110 >
b11111111 =
b100000000 @
b100000000 ,
b100000000 :
b100000001 "
b100000001 )
b100000001 -
b100000001 4
b1100 j
1#
#150000
0#
#155000
b10000 1
b11000000 0
b1 .
b1 5
b1000000000000000 2
b1000000000000000 6
b111111111111111 3
b1000000000000000 7
b10000 9
b1000000000000000 8
b1 "
b1 )
b1 -
b1 4
b100000001 @
b100000001 ,
b100000001 :
b11111110 O
b11111110 ?
b11111111 >
b100000000 =
b10000001000000001 R
b100000001 B
b100000001 H
b100000001 P
b100000000100000000 D
b1000000001 G
b10010000 K
b1001000000000000 E
b100000000 F
b11000000 I
b1100 j
1#
#160000
0#
#165000
b10000 1
b1100000 0
b100 .
b100 5
b10000000000000 2
b1110000000000000 6
b1101111111111111 3
b10000000000000 7
b10000 9
b10000000000000 8
b100100000000000000000000 C
b110000000000 A
b110000000000 +
b110000000000 /
b110000000000 <
b1001000010010000 E
b100000001 F
b1001110000 G
b11101010000000000 D
b11000000 J
b10000000000000000 R
b100000000 B
b100000000 H
b100000000 P
b11111111 O
b11111111 ?
b100000000 >
b100000001 =
b1111111111111100 T
b100000010 Z
b11111110 U
b100000001 X
b11111110 L
b1 @
b1 ,
b1 :
b100 "
b100 )
b100 -
b100 4
b1100 j
1#
#170000
0#
#175000
b10000 1
b110000 0
b10000 .
b10000 5
b100000000000 2
b1111100000000000 6
b1111011111111111 3
b100000000000 7
b10000 9
b100000000000 8
b10000 "
b10000 )
b10000 -
b10000 4
b100 @
b100 ,
b100 :
b11111110 M
b11111111 L
b1000000001 V
b100000001100000001 S
b100000001 Y
b100000000 Z
b1111111100000000 T
b11111111 U
b100000000 X
b100000000 O
b100000000 ?
b100000001 >
b1 =
b1101010111100100 R
b11101010 B
b11101010 H
b11101010 P
b1001000000000000 K
b1001000000000000 E
b1 F
b110000000000 I
b1001000000000000000000 C
b11000000000 A
b11000000000 +
b11000000000 /
b11000000000 <
b1100 j
1#
#180000
0#
#185000
b10000 1
b11000 0
b1000000 .
b1000000 5
b1000000000 2
b1111111000000000 6
b1111110111111111 3
b1000000000 7
b10000 9
b1000000000 8
b10010000000000000000 C
b1100000000 A
b1100000000 +
b1100000000 /
b1100000000 <
b10010000000000 K
b1001000000000000 E
b100 F
b11000000000 I
b111010100000000000000 D
b110000000000 J
b100000001 O
b100000001 ?
b1 >
b100 =
b11010101 Z
b1101010100000000 T
b100000000 U
b11101010 X
b100000000100000000 S
b100000000 Y
b10000001000000001 a
b100000001 Q
b100000001 W
b100000001 _
b11111110 ^
b11111110 N
b11111111 M
b100000000 L
b10000 @
b10000 ,
b10000 :
b1000000 "
b1000000 )
b1000000 -
b1000000 4
b1100 j
1#
#190000
0#
#195000
b10000 1
b1100 0
b100000000 .
b100000000 5
b10000000 2
b1111111110000000 6
b1111111101111111 3
b10000000 7
b10000 9
b10000000 8
b100000000 "
b100000000 )
b100000000 -
b100000000 4
b1000000 @
b1000000 ,
b1000000 :
b11111110 [
b1111111111111100 c
b100000010 i
b11111110 d
b100000001 g
b11111111 ^
b11111111 N
b100000000 M
b100000001 L
b10000000000000000 a
b100000000 Q
b100000000 W
b100000000 _
b1000101011 V
b11111101101001110 S
b11101010 Y
b1101010111010101 T
b100000001 U
b1 O
b1 ?
b100 >
b10000 =
b110101011110010000000000 R
b111010100000 B
b111010100000 H
b111010100000 P
b11101010000000000000 D
b11000000000 J
b100100000000 K
b1001000000000000 E
b10000 F
b1100000000 I
b100100000000000000 C
b110000000 A
b110000000 +
b110000000 /
b110000000 <
b1100 j
1#
#200000
0#
#205000
b10000 1
b110 0
b10000000000 .
b10000000000 5
b100000 2
b1111111111100000 6
b1111111111011111 3
b100000 7
b10000 9
b100000 8
b1001000000000000 C
b11000000 A
b11000000 +
b11000000 /
b11000000 <
b1001000000 K
b1001000000000000 E
b1000000 F
b110000000 I
b1110101000000000000 D
b1100000000 J
b1101010111100100000000 R
b11101010000 B
b11101010000 H
b11101010000 P
b100 O
b100 ?
b10000 >
b1000000 =
b1101010111100100 Z
b1101010111100100 T
b1 U
b111010100000 X
b1111101000001001 a
b11111101 Q
b11111101 W
b11111101 _
b100000000 ^
b100000000 N
b100000001 M
b1 L
b100000000 i
b1111111100000000 c
b11111111 d
b100000000 g
b1000000001 e
b100000001100000001 b
b100000001 h
b11111110 \
b11111111 [
b100000000 @
b100000000 ,
b100000000 :
b10000000000 "
b10000000000 )
b10000000000 -
b10000000000 4
b1100 j
1#
#210000
0#
#215000
b10000 1
b11 0
b1000000000000 .
b1000000000000 5
b1000 2
b1111111111111000 6
b1111111111110111 3
b1000 7
b10000 9
b1000 8
b1000000000000 "
b1000000000000 )
b1000000000000 -
b1000000000000 4
b10000000000 @
b10000000000 ,
b10000000000 :
b11111110 ]
b11111111 \
b100000000 [
b100000001 !
b100000001 *
b100000001 ;
b100000001 `
b100000001 f
b100000000100000000 b
b100000000 h
b11111010 i
b1111101000000000 c
b100000000 d
b11111101 g
b100000001 ^
b100000001 N
b1 M
b100 L
b111111011010011100000 S
b111010100000 Y
b11010101111001 Z
b1101010111100100 T
b100 U
b11101010000 X
b10000 O
b10000 ?
b1000000 >
b100000000 =
b11010101111001000000 R
b1110101000 B
b1110101000 H
b1110101000 P
b111010100000000000 D
b110000000 J
b10010000 K
b1001000000000000 E
b100000000 F
b11000000 I
b10010000000000 C
b1100000 A
b1100000 +
b1100000 /
b1100000 <
b1100 j
1#
#220000
0#
#225000
b10000 1
b1 0
b100000000000000 .
b100000000000000 5
b10 2
b1111111111111110 6
b1111111111111101 3
b10 7
b10000 9
b10 8
b100100000000 C
b110000 A
b110000 +
b110000 /
b110000 <
b100100 K
b1001000000000000 E
b10000000000 F
b1100000 I
b11101010000000000 D
b11000000 J
b110101011110010000 R
b111010100 B
b111010100 H
b111010100 P
b1000000 O
b1000000 ?
b100000000 >
b10000000000 =
b110101011110 Z
b1101010111100000 T
b10000 U
b1110101000 X
b11111101101001110000 S
b11101010000 Y
b111110110100010110100100 a
b111111011010 Q
b111111011010 W
b111111011010 _
b1 ^
b1 N
b100 M
b10000 L
b1111101011111010 c
b100000001 d
b1000000110 e
b11111111111101110 b
b11111101 h
b100000000 !
b100000000 *
b100000000 ;
b100000000 `
b100000000 f
b11111111 ]
b100000000 \
b100000001 [
b1000000000000 @
b1000000000000 ,
b1000000000000 :
b100000000000000 "
b100000000000000 )
b100000000000000 -
b100000000000000 4
b1100 j
b1 '
1#
#230000
0#
#235000
b10000 1
b1 0
b1000000000000000 .
b1000000000000000 5
b1 2
b1111111111111111 6
b1111111111111110 3
b1 7
b10000 9
b1 8
b1000000000000000 "
b1000000000000000 )
b1000000000000000 -
b1000000000000000 4
b100000000000000 @
b100000000000000 ,
b100000000000000 :
b100000000 ]
b100000001 \
b1 [
b11111111 !
b11111111 *
b11111111 ;
b11111111 `
b11111111 f
b1111101101000101 i
b1111101101000101 c
b1 d
b111111011010 g
b100 ^
b100 N
b10000 M
b1000000 L
b1111101101000101101001 a
b11111101101 Q
b11111101101 W
b11111101101 _
b1111110110100111000 S
b1110101000 Y
b1101010111 Z
b1101010111000000 T
b1000000 U
b111010100 X
b100000000 O
b100000000 ?
b10000000000 >
b1000000000000 =
b1101010111100100 R
b11101010 B
b11101010 H
b11101010 P
b1110101000000000 D
b1100000 J
b1001 K
b1001000000000000 E
b1000000000000 F
b110000 I
b100000000 C
b10000 A
b10000 +
b10000 /
b10000 <
b1100 j
b10 '
1#
#240000
0#
#245000
b10000 1
b1000 0
b1000000000 .
b1000000000 5
b1000000 2
b1111110111000000 6
b1111110110111111 3
b1001000000 7
b10000 9
b1000000 8
b1 K
b100000000000000 E
b100000000000000 F
b10000 I
b111010100000000 D
b110000 J
b11010101111001 R
b1110101 B
b1110101 H
b1110101 P
b10000000000 O
b10000000000 ?
b1000000000000 >
b100000000000000 =
b11010101 Z
b1101010100000000 T
b100000000 U
b11101010 X
b111111011010011100 S
b111010100 Y
b11111011000001100100 a
b1111110110 Q
b1111110110 W
b1111110110 _
b10000 ^
b10000 N
b1000000 M
b100000000 L
b11111011010001 i
b1111101101000100 c
b100 d
b11111101101 g
b1000000101 e
b1000000000001101000010 b
b111111011010 h
b100000001 ]
b1 \
b100 [
b1000000000000000 @
b1000000000000000 ,
b1000000000000000 :
b1001000000 "
b1001000000 )
b1001000000 -
b1001000000 4
b1100 j
b11 '
1#
#250000
0#
#255000
b10000 1
b100 0
b100000000000 .
b100000000000 5
b10000 2
b1111111101110000 6
b1111111101101111 3
b10010000 7
b10000 9
b10000 8
b100100000000 "
b100100000000 )
b100100000000 -
b100100000000 4
b1001000000 @
b1001000000 ,
b1001000000 :
b1 ]
b100 \
b10000 [
b1000000000001 !
b1000000000001 *
b1000000000001 ;
b1000000000001 `
b1000000000001 f
b100000000000110100001 b
b11111101101 h
b111110110000 i
b1111101100000000 c
b10000 d
b1111110110 g
b1000000 ^
b1000000 N
b100000000 M
b10000000000 L
b111110110000011001 a
b111111011 Q
b111111011 W
b111111011 _
b11111101101001110 S
b11101010 Y
b110101 Z
b1101010000000000 T
b10000000000 U
b1110101 X
b1000000000000 O
b1000000000000 ?
b100000000000000 >
b1000000000000000 =
b110100100100 R
b111010 B
b111010 H
b111010 P
b1011000000 G
b10110000000000 D
b10000 J
b1000000000000000 E
b1000000000000000 F
b100000000000000 C
b10000000 A
b10000000 +
b10000000 /
b10000000 <
b1100 j
b100 '
1#
#260000
0#
#265000
b10000 1
b11 0
b1000000000000 .
b1000000000000 5
b1000 2
b1111111101101000 6
b1111111101100111 3
b10011000 7
b10000 9
b1000 8
b1000000000000 C
b1000000 A
b1000000 +
b1000000 /
b1000000 <
b1000000 K
b1001000000000000 E
b1001000000 F
b10000000 I
b10100000000000 D
b1010000000 G
b111100100 R
b10110 B
b10110 H
b10110 P
b100000000000000 O
b100000000000000 ?
b1000000000000000 >
b1001000000 =
b1101 Z
b1101000000000000 T
b1000000000000 U
b111010 X
b1000101100 V
b1111111000011100 S
b1110101 Y
b1111101000001001 a
b11111101 Q
b11111101 W
b11111101 _
b100000000 ^
b100000000 N
b10000000000 M
b1000000000000 L
b1111101100 i
b1111101100000000 c
b1000000 d
b111111011 g
b1111111111111001110 b
b1111110110 h
b100000000000 !
b100000000000 *
b100000000000 ;
b100000000000 `
b100000000000 f
b100 ]
b10000 \
b1000000 [
b100100000000 @
b100100000000 ,
b100100000000 :
b1100100000000 "
b1100100000000 )
b1100100000000 -
b1100100000000 4
b1100 j
b101 '
1#
#270000
0#
#275000
b10000 1
b1 0
b100000000000000 .
b100000000000000 5
b10 2
b1111111111111110 6
b1111111111111101 3
b10 7
b10000 9
b10 8
b100000000000000 "
b100000000000000 )
b100000000000000 -
b100000000000000 4
b1100100000000 @
b1100100000000 ,
b1100100000000 :
b10000 ]
b1000000 \
b100000000 [
b1111111111 !
b1111111111 *
b1111111111 ;
b1111111111 `
b1111111111 f
b111111111111100111 b
b111111011 h
b11111010 i
b1111101000000000 c
b100000000 d
b11111101 g
b10000000000 ^
b10000000000 N
b1000000000000 M
b100000000000000 L
b11111100000001 a
b1111111 Q
b1111111 W
b1111111 _
b1000110000 V
b111111011100000 S
b111010 Y
b1 Z
b100000000000000 T
b100000000000000 U
b10110 X
b1000000000000000 O
b1000000000000000 ?
b1001000000 >
b100100000000 =
b110010000 R
b10100 B
b10100 H
b10100 P
b1001110000 G
b10011100000000000 D
b10000000 J
b10000 K
b1001000000000000 E
b100100000000 F
b1000000 I
b100100000000 C
b110000 A
b110000 +
b110000 /
b110000 <
b1100 j
b110 '
1#
#280000
0#
#285000
b10000 1
b1 0
b1000000000000000 .
b1000000000000000 5
b1 2
b1111111111110111 6
b1111111111110110 3
b1001 7
b10000 9
b1 8
b100000000 C
b10000 A
b10000 +
b10000 /
b10000 <
b1001 K
b1110000100000000 E
b1100100000000 F
b110000 I
b1001110000000000 D
b1000000 J
b101111100010000 R
b10011100 B
b10011100 H
b10011100 P
b1001000000 O
b1001000000 ?
b100100000000 >
b1100100000000 =
b1000000000000000 T
b1000000000000000 U
b10100 X
b1011000000 V
b11110010000000 S
b10110 Y
b111110000001 a
b111111 Q
b111111 W
b111111 _
b1000000000000 ^
b1000000000000 N
b100000000000000 M
b1000000000000000 L
b111111 i
b1111110000000000 c
b10000000000 d
b1111111 g
b1000000110 e
b11111111111101110 b
b11111101 h
b111111111 !
b111111111 *
b111111111 ;
b111111111 `
b111111111 f
b1000000 ]
b100000000 \
b10000000000 [
b100000000000000 @
b100000000000000 ,
b100000000000000 :
b1001000000000000 "
b1001000000000000 )
b1001000000000000 -
b1001000000000000 4
b1100 j
b111 '
1#
#290000
0#
